Workbook

Sheet Feuil1
A1: Q1 : Êtes-vous | B1: Q2 : Si vous avez coché sage-femme diplômé(e), depuis combien de temps exercez-vous ? | C1: Q3 : Dans quelle structure exercez-vous ? | D1: Q4 : Sur une échelle de 1 à 5, comment évalueriez-vous votre niveau de connaissance de l’ostéopathie ? | E1: Q5 : Quelle est selon vous, la place de l’ostéopathie dans la prise en charge globale de la femme enceinte ? | F1: Q6 : Vous sentez-vous suffisamment informé(e) sur l’ostéopathie et ses indications durant la grossesse ? | G1: Q7 : Avez-vous accès, au sein de votre structure, à un réseau d’ostéopathes vers lesquels orienter vos patientes ? | H1: Q8 : La collaboration avec un(e) ostéopathe fait-elle partie intégrante de votre pratique ? | I1: Q9 : Si oui, dans quel(s) cadre(s) ? | J1: Q10 : Comment estimez-vous vos connaissances concernant le syndrome de Lacomme (douleurs ligamentaires lombo-pelviennes de grossesse) ? | K1: Q11 : Comment identifiez-vous ce syndrome dans votre pratique ? | L1: Q12 : A quelle fréquence rencontrez-vous des patientes présentant un syndrome de Lacomme ? | M1: Q13 : Estimez-vous qu’il y a un retard diagnostic à la prise en charge de ce syndrome ? | N1: Q14 : Si oui, quelles sont les principales raisons de ce retard diagnostic ? | O1: Q15 : Classez les différentes prises en charge dans l’ordre que vous recommanderiez pour une patiente atteinte du syndrome de Lacomme : [Premier choix ] | P1: Q15 : Classez les différentes prises en charge dans l’ordre que vous recommanderiez pour une patiente atteinte du syndrome de Lacomme : [Second choix ] | Q1: Q15 : Classez les différentes prises en charge dans l’ordre que vous recommanderiez pour une patiente atteinte du syndrome de Lacomme : [Troisième choix ] | R1: Q15 : Classez les différentes prises en charge dans l’ordre que vous recommanderiez pour une patiente atteinte du syndrome de Lacomme : [Quatrième choix ] | S1: Q15 : Classez les différentes prises en charge dans l’ordre que vous recommanderiez pour une patiente atteinte du syndrome de Lacomme : [Cinquième choix ] | T1: Q15 : Classez les différentes prises en charge dans l’ordre que vous recommanderiez pour une patiente atteinte du syndrome de Lacomme : [Sixième choix ] | U1: Q16 : Pensez-vous que l'ostéopathie constitue une approche pertinente pour traiter le syndrome de Lacomme et qu’elle mérite d’être recommandée aux patientes concernées ? | V1: Q17 : Si oui, à quel moment ? | W1: Q18 : Pensez-vous que les patientes sont suffisamment informées sur les possibilités de prises en charge ostéopathiques du syndrome de Lacomme ? | X1: Q19 : Quels sont les facteurs qui permettraient de favoriser l’intégration de l’ostéopathie dans la prise en charge du syndrome de Lacomme ? | Y1: Q20 : Quels sont, selon vous, les freins à l’intégration de l’ostéopathie dans la pratique sage-femme ? | Z1: Q21 : Quels sont les facteurs qui influencent votre décision de recommander ou non l’ostéopathie ? | AA1: Q22 : Les recommandations officielles (HAS, CNGOF, Ordre des sages-femmes) influencent-elles votre décision d’orienter vers l’ostéopathie ? | AB1: Q23 : Pensez-vous que la collaboration entre sages-femmes et ostéopathes pourrait améliorer la prise en charge des femmes enceintes ? | AC1: Q24 : Seriez-vous favorable à l’intégration d’ostéopathes dans les équipes pluridisciplinaires périnatales ? | AD1: Q25 : Quels éléments pourraient favoriser une meilleure collaboration entre sages-femmes et ostéopathes ? | AE1: Q26 : Souhaitez-vous partager une expérience ou un avis personnel concernant l’ostéopathie dans la prise en charge du syndrome de Lacomme ? | AF1: Q26 : Souhaitez-vous partager une expérience ou un avis personnel concernant l’ostéopathie dans la prise en charge du syndrome de Lacomme ? | AG1: Q27 : Souhaitez-vous partager une expérience ou un avis personnel concernant l’ostéopathie et la collaboration avec les sages-femmes ? | AH1: Q27 : Souhaitez-vous partager une expérience ou un avis personnel concernant l’ostéopathie et la collaboration avec les sages-femmes ? | AI1: Q28 : Y a-t-il un élément ou un commentaire supplémentaire que vous souhaiteriez apporter ? | AJ1: Q28 : Y a-t-il un élément ou un commentaire supplémentaire que vous souhaiteriez apporter ?
A2: Étudiant(e) sage-femme en 5e année | B2: 0 | C2: 0 | D2: 4 | E2: 4 | F2: 3 | G2: Oui | H2: Oui, occasionnellement (> ou = à 1 fois par mois) | I2: Douleurs lombaires et/ou pelviennes, Post-partum, Allaitement, Nouveau-né | J2: 4 | K2: Interrogatoire | L2: A chaque suivi | M2: Oui | N2: Absence de recommandations professionnelles claires | O2: Exercices/Etirements | P2: Ostéopathie | Q2: Conseils posturaux | R2: Traitements médicamenteux (antalgiques/analgésiques) | S2: Ceinture de maintien/Support pelvien | T2: Repos/Limitation de mouvement | U2: 5 | V2: Dès les premiers symptômes | W2: 1 | X2: Preuves scientifiques, Réduction du coût des séances pour les patientes, Reconnaissance institutionnelle | Y2: Peu de contenus pédagogiques sur les principes ostéopathiques inscrits au parcours académique, Absence de connaissances sur la pratique ostéopathique, Insuffisance de preuves scientifiques, Coût pour les patientes, Absence de reconnaissance institutionnelle | Z2: Motivation des patientes pour une prise en charge manuelle complémentaire | AA2: Oui | AB2: Oui | AC2: Oui | AD2: Preuves de résultats positifs des traitements ostéopathiques, Demande des patientes, Encadrement institutionnel et recommandations officielles | AE2: Le syndrome de Lacomme est beaucoup expliqué par les SF comme « maux qui font partie des symptômes de la grossesse » et donc plutôt un discours de « ça passera » | AF2: Banalisation du syndrome de Lacomme, Absence de connaissances sur le syndrome de Lacomme | AG2: 0 | AH2: 0 | AI2: 0 | AJ2: 0
A3: Étudiant(e) sage-femme en 5e année | B3: 0 | C3: 0 | D3: 2 | E3: 3 | F3: 3 | G3: Oui | H3: Oui, occasionnellement (> ou = à 1 fois par mois) | I3: Suivi prénatal de grossesse, Douleurs lombaires et/ou pelviennes | J3: 2 | K3: Interrogatoire | L3: Rarement (> ou = à 1 fois tous les 3 mois) | M3: Sans avis | N3: 0 | O3: Conseils posturaux | P3: Exercices/Etirements | Q3: Ceinture de maintien/Support pelvien | R3: Ostéopathie | S3: Traitements médicamenteux (antalgiques/analgésiques) | T3: Repos/Limitation de mouvement | U3: 4 | V3: En cas d’absence de réussite d’autres prises en charge | W3: 2 | X3: Contenus pédagogiques sur les principes ostéopathiques inscrits au parcours académique, Réduction du coût des séances pour les patientes, Intégration de l’ostéopathie dans les structures de santé | Y3: Absence de connaissances sur la pratique ostéopathique, Insuffisance de collaboration interprofessionnelle avec des ostéopathes, Coût pour les patientes, Absence de reconnaissance institutionnelle | Z3: Caractère chronique ou aigu des douleurs, Spécialisation de l’ostéopathe en périnatalité, Motivation des patientes pour une prise en charge manuelle complémentaire, Disponibilité et/ou accessibilité d’ostéopathes dans votre réseau, Collaboration interprofessionnelle préexistante, Convictions personnelles concernant cette approche thérapeutique | AA3: Sans avis | AB3: Oui | AC3: Oui | AD3: Preuves de résultats positifs des traitements ostéopathiques, Formations sémiologiques supplémentaires des ostéopathes, Mise en place de protocoles règlementés | AE3: 0 | AF3: 0 | AG3: 0 | AH3: 0 | AI3: 0 | AJ3: 0
A4: Étudiant(e) sage-femme en 5e année | B4: 0 | C4: 0 | D4: 2 | E4: 3 | F4: 2 | G4: Non | H4: Non | I4: 0 | J4: 4 | K4: Interrogatoire, Examen clinique, En excluant d’autres causes possibles de douleurs pelviennes pendant la grossesse | L4: Rarement (> ou = à 1 fois tous les 3 mois) | M4: Sans avis | N4: Absence de formation spécifique sur le syndrome, Assimilation du syndrome à des lombalgies non spécifiques | O4: Conseils posturaux | P4: Ostéopathie | Q4: Exercices/Etirements | R4: Ceinture de maintien/Support pelvien | S4: Repos/Limitation de mouvement | T4: Traitements médicamenteux (antalgiques/analgésiques) | U4: 4 | V4: Dès les premiers symptômes | W4: 2 | X4: Contenus pédagogiques sur les principes ostéopathiques inscrits au parcours académique, Preuves scientifiques, Réduction du coût des séances pour les patientes | Y4: Peu de contenus pédagogiques sur les principes ostéopathiques inscrits au parcours académique, Absence de connaissances sur la pratique ostéopathique, Insuffisance de preuves scientifiques, Coût pour les patientes | Z4: Spécialisation de l’ostéopathe en périnatalité, Motivation des patientes pour une prise en charge manuelle complémentaire | AA4: Oui | AB4: Oui | AC4: Oui | AD4: Preuves de résultats positifs des traitements ostéopathiques, Encadrement institutionnel et recommandations officielles | AE4: 0 | AF4: 0 | AG4: 0 | AH4: 0 | AI4: 0 | AJ4: 0
A5: Étudiant(e) sage-femme en 5e année | B5: 0 | C5: 0 | D5: 1 | E5: 4 | F5: 2 | G5: Non | H5: Oui, occasionnellement (> ou = à 1 fois par mois) | I5: Douleurs lombaires et/ou pelviennes | J5: 2 | K5: Interrogatoire, Examen clinique | L5: Occasionnellement (> ou = à 1 fois par mois) | M5: Oui | N5: Sous-estimation des plaintes des patientes | O5: Conseils posturaux | P5: Repos/Limitation de mouvement, Conseils posturaux | Q5: Exercices/Etirements | R5: Ceinture de maintien/Support pelvien | S5: Ostéopathie | T5: Traitements médicamenteux (antalgiques/analgésiques) | U5: 5 | V5: Dès les premiers symptômes | W5: 3 | X5: Contenus pédagogiques sur les principes ostéopathiques inscrits au parcours académique, Reconnaissance institutionnelle | Y5: Peu de contenus pédagogiques sur les principes ostéopathiques inscrits au parcours académique, Absence de connaissances sur la pratique ostéopathique | Z5: Motivation des patientes pour une prise en charge manuelle complémentaire | AA5: Oui | AB5: Oui | AC5: Oui | AD5: Mise en place de protocoles règlementés, Encadrement institutionnel et recommandations officielles | AE5: 0 | AF5: 0 | AG5: 0 | AH5: 0 | AI5: 0 | AJ5: 0
A6: Étudiant(e) sage-femme en 5e année | B6: 0 | C6: 0 | D6: 1 | E6: 3 | F6: 2 | G6: Oui | H6: Oui, occasionnellement (> ou = à 1 fois par mois) | I6: Douleurs lombaires et/ou pelviennes, Post-partum | J6: 4 | K6: Interrogatoire, Examen clinique, En excluant d’autres causes possibles de douleurs pelviennes pendant la grossesse | L6: Rarement (> ou = à 1 fois tous les 3 mois) | M6: Oui | N6: Absence de formation spécifique sur le syndrome, Assimilation du syndrome à des lombalgies non spécifiques | O6: Conseils posturaux | P6: Exercices/Etirements | Q6: Ceinture de maintien/Support pelvien | R6: Ostéopathie | S6: Repos/Limitation de mouvement | T6: Traitements médicamenteux (antalgiques/analgésiques) | U6: 4 | V6: En cas d’absence de réussite d’autres prises en charge | W6: 1 | X6: Contenus pédagogiques sur les principes ostéopathiques inscrits au parcours académique, Retours de patientes, Preuves scientifiques, Médiatisation/Réseaux sociaux, Réduction du coût des séances pour les patientes, Reconnaissance institutionnelle, Intégration de l’ostéopathie dans les structures de santé | Y6: Peu de contenus pédagogiques sur les principes ostéopathiques inscrits au parcours académique, Absence de connaissances sur la pratique ostéopathique, Insuffisance de preuves scientifiques | Z6: Caractère chronique ou aigu des douleurs, Réponse ou non aux autres traitements, Motivation des patientes pour une prise en charge manuelle complémentaire, Disponibilité et/ou accessibilité d’ostéopathes dans votre réseau | AA6: Sans avis | AB6: Oui | AC6: Oui | AD6: Preuves de résultats positifs des traitements ostéopathiques, Demande des patientes, Formations sémiologiques supplémentaires des ostéopathes, Recommandations par d’autres professionnels de santé, Absence ou inefficacité d’autres solutions thérapeutiques, Mise en place de protocoles règlementés, Encadrement institutionnel et recommandations officielles | AE6: 0 | AF6: 0 | AG6: 0 | AH6: 0 | AI6: 0 | AJ6: 0
A7: Étudiant(e) sage-femme en 5e année | B7: 0 | C7: 0 | D7: 4 | E7: 4 | F7: 4 | G7: Non | H7: Oui, occasionnellement (> ou = à 1 fois par mois) | I7: Suivi prénatal de grossesse, Douleurs lombaires et/ou pelviennes, Post-partum | J7: 3 | K7: Interrogatoire, Examen clinique, En excluant d’autres causes possibles de douleurs pelviennes pendant la grossesse | L7: Rarement (> ou = à 1 fois tous les 3 mois) | M7: Non | N7: 0 | O7: Exercices/Etirements | P7: Ceinture de maintien/Support pelvien | Q7: Ostéopathie | R7: Conseils posturaux | S7: Repos/Limitation de mouvement | T7: Traitements médicamenteux (antalgiques/analgésiques) | U7: 4 | V7: Dès les premiers symptômes | W7: 3 | X7: Retours de patientes, Intégration de l’ostéopathie dans les structures de santé | Y7: Peu de contenus pédagogiques sur les principes ostéopathiques inscrits au parcours académique, Absence de connaissances sur la pratique ostéopathique, Insuffisance de preuves scientifiques, Coût pour les patientes | Z7: Caractère chronique ou aigu des douleurs, Spécialisation de l’ostéopathe en périnatalité, Motivation des patientes pour une prise en charge manuelle complémentaire, Expérience personnelle antérieure positive ou négative avec l’ostéopathie | AA7: Sans avis | AB7: Oui | AC7: Oui | AD7: Preuves de résultats positifs des traitements ostéopathiques | AE7: 0 | AF7: 0 | AG7: 0 | AH7: 0 | AI7: 0 | AJ7: 0
A8: Étudiant(e) sage-femme en 5e année | B8: 0 | C8: Mixte | D8: 1 | E8: 3 | F8: 1 | G8: Non | H8: Oui, rarement (< à 1 fois par mois) | I8: Douleurs lombaires et/ou pelviennes, Nouveau-né | J8: 2 | K8: Interrogatoire, En excluant d’autres causes possibles de douleurs pelviennes pendant la grossesse | L8: Rarement (> ou = à 1 fois tous les 3 mois) | M8: Oui | N8: Absence de formation spécifique sur le syndrome, Sous-estimation des plaintes des patientes | O8: Conseils posturaux | P8: Exercices/Etirements | Q8: Ceinture de maintien/Support pelvien | R8: Ostéopathie | S8: Traitements médicamenteux (antalgiques/analgésiques) | T8: Repos/Limitation de mouvement | U8: 4 | V8: Dès les premiers symptômes | W8: 2 | X8: Contenus pédagogiques sur les principes ostéopathiques inscrits au parcours académique, Preuves scientifiques, Médiatisation/Réseaux sociaux, Réduction du coût des séances pour les patientes | Y8: Peu de contenus pédagogiques sur les principes ostéopathiques inscrits au parcours académique, Insuffisance de collaboration interprofessionnelle avec des ostéopathes, Coût pour les patientes | Z8: Caractère chronique ou aigu des douleurs, Réponse ou non aux autres traitements, Spécialisation de l’ostéopathe en périnatalité, Motivation des patientes pour une prise en charge manuelle complémentaire, Disponibilité et/ou accessibilité d’ostéopathes dans votre réseau | AA8: Oui | AB8: Oui | AC8: Oui | AD8: Preuves de résultats positifs des traitements ostéopathiques, Demande des patientes, Formations sémiologiques supplémentaires des ostéopathes, Mise en place de protocoles règlementés, Encadrement institutionnel et recommandations officielles | AE8: 0 | AF8: 0 | AG8: 0 | AH8: 0 | AI8: 0 | AJ8: 0
A9: Étudiant(e) sage-femme en 5e année | B9: 0 | C9: 0 | D9: 2 | E9: 4 | F9: 1 | G9: Oui | H9: Non | I9: Douleurs lombaires et/ou pelviennes | J9: 4 | K9: Interrogatoire, Examen clinique, En excluant d’autres causes possibles de douleurs pelviennes pendant la grossesse | L9: Fréquemment (> ou = à 1 fois par semaine) | M9: Oui | N9: Absence de formation spécifique sur le syndrome, Sous-estimation des plaintes des patientes, Absence de recommandations professionnelles claires | O9: Conseils posturaux | P9: Exercices/Etirements | Q9: Ostéopathie | R9: Traitements médicamenteux (antalgiques/analgésiques) | S9: Ceinture de maintien/Support pelvien | T9: Repos/Limitation de mouvement | U9: 5 | V9: Dès les premiers symptômes | W9: 1 | X9: Contenus pédagogiques sur les principes ostéopathiques inscrits au parcours académique, Retours de patientes, Reconnaissance institutionnelle, Intégration de l’ostéopathie dans les structures de santé | Y9: Peu de contenus pédagogiques sur les principes ostéopathiques inscrits au parcours académique, Absence de connaissances sur la pratique ostéopathique, Insuffisance de collaboration interprofessionnelle avec des ostéopathes, Absence de reconnaissance institutionnelle | Z9: Caractère chronique ou aigu des douleurs, Motivation des patientes pour une prise en charge manuelle complémentaire, Collaboration interprofessionnelle préexistante | AA9: Oui | AB9: Oui | AC9: Oui | AD9: Preuves de résultats positifs des traitements ostéopathiques, Demande des patientes, Mise en place de protocoles règlementés, Encadrement institutionnel et recommandations officielles | AE9: 0 | AF9: 0 | AG9: 0 | AH9: 0 | AI9: 0 | AJ9: 0
A10: Étudiant(e) sage-femme en 5e année | B10: 0 | C10: 0 | D10: 3 | E10: 4 | F10: 4 | G10: Oui | H10: Oui, occasionnellement (> ou = à 1 fois par mois) | I10: Douleurs lombaires et/ou pelviennes, Troubles digestifs associés, Post-partum, Allaitement | J10: 4 | K10: Interrogatoire, Examen clinique, En excluant d’autres causes possibles de douleurs pelviennes pendant la grossesse | L10: Occasionnellement (> ou = à 1 fois par mois) | M10: Oui | N10: Absence de formation spécifique sur le syndrome, Assimilation du syndrome à des lombalgies non spécifiques, Difficultés d’accès aux thérapies non médicamenteuses, Absence de recommandations professionnelles claires | O10: Conseils posturaux | P10: Exercices/Etirements | Q10: Ceinture de maintien/Support pelvien | R10: Ostéopathie | S10: Traitements médicamenteux (antalgiques/analgésiques) | T10: Repos/Limitation de mouvement | U10: 5 | V10: En cas d’absence de réussite d’autres prises en charge | W10: 2 | X10: Preuves scientifiques, Réduction du coût des séances pour les patientes, Reconnaissance institutionnelle, Intégration de l’ostéopathie dans les structures de santé | Y10: Absence de connaissances sur la pratique ostéopathique, Coût pour les patientes, Absence de reconnaissance institutionnelle | Z10: Caractère chronique ou aigu des douleurs, Réponse ou non aux autres traitements, Spécialisation de l’ostéopathe en périnatalité, Motivation des patientes pour une prise en charge manuelle complémentaire, Disponibilité et/ou accessibilité d’ostéopathes dans votre réseau | AA10: 0 | AB10: Oui | AC10: Oui | AD10: Preuves de résultats positifs des traitements ostéopathiques, Formations sémiologiques supplémentaires des ostéopathes, Absence ou inefficacité d’autres solutions thérapeutiques, Mise en place de protocoles règlementés, Encadrement institutionnel et recommandations officielles | AE10: 0 | AF10: 0 | AG10: 0 | AH10: 0 | AI10: 0 | AJ10: 0
A11: Étudiant(e) sage-femme en 5e année | B11: 0 | C11: 0 | D11: 1 | E11: 3 | F11: 3 | G11: Oui | H11: Non | I11: Douleurs lombaires et/ou pelviennes, Post-partum, Allaitement | J11: 2 | K11: Interrogatoire, En excluant d’autres causes possibles de douleurs pelviennes pendant la grossesse | L11: Jamais | M11: Sans avis | N11: Absence de formation spécifique sur le syndrome, Assimilation du syndrome à des lombalgies non spécifiques, Absence de recommandations professionnelles claires | O11: Repos/Limitation de mouvement | P11: Ceinture de maintien/Support pelvien | Q11: Conseils posturaux | R11: Ostéopathie | S11: Exercices/Etirements | T11: Traitements médicamenteux (antalgiques/analgésiques) | U11: 4 | V11: En cas d’absence de réussite d’autres prises en charge | W11: 1 | X11: Contenus pédagogiques sur les principes ostéopathiques inscrits au parcours académique, Preuves scientifiques, Médiatisation/Réseaux sociaux, Réduction du coût des séances pour les patientes, Intégration de l’ostéopathie dans les structures de santé | Y11: Peu de contenus pédagogiques sur les principes ostéopathiques inscrits au parcours académique, Absence de connaissances sur la pratique ostéopathique, Insuffisance de preuves scientifiques, Insuffisance de collaboration interprofessionnelle avec des ostéopathes | Z11: Caractère chronique ou aigu des douleurs, Réponse ou non aux autres traitements, Spécialisation de l’ostéopathe en périnatalité, Motivation des patientes pour une prise en charge manuelle complémentaire, Disponibilité et/ou accessibilité d’ostéopathes dans votre réseau, Collaboration interprofessionnelle préexistante, Convictions personnelles concernant cette approche thérapeutique, Expérience personnelle antérieure positive ou négative avec l’ostéopathie | AA11: Oui | AB11: Oui | AC11: Oui | AD11: Formations sémiologiques supplémentaires des ostéopathes, Recommandations par d’autres professionnels de santé | AE11: 0 | AF11: 0 | AG11: 0 | AH11: 0 | AI11: 0 | AJ11: 0
A12: Étudiant(e) sage-femme en 5e année | B12: 0 | C12: 0 | D12: 3 | E12: 4 | F12: 4 | G12: Sans avis | H12: Oui, occasionnellement (> ou = à 1 fois par mois) | I12: Suivi prénatal de grossesse, Préparation à l’accouchement, Douleurs lombaires et/ou pelviennes, Post-partum | J12: 2 | K12: Interrogatoire, Examen clinique, En excluant d’autres causes possibles de douleurs pelviennes pendant la grossesse | L12: Rarement (> ou = à 1 fois tous les 3 mois) | M12: Sans avis | N12: Absence de formation spécifique sur le syndrome, Difficultés d’accès aux thérapies non médicamenteuses, Absence de recommandations professionnelles claires | O12: Exercices/Etirements | P12: Conseils posturaux | Q12: Ceinture de maintien/Support pelvien | R12: Ostéopathie | S12: Traitements médicamenteux (antalgiques/analgésiques) | T12: Repos/Limitation de mouvement | U12: 4 | V12: Dès les premiers symptômes | W12: 2 | X12: Contenus pédagogiques sur les principes ostéopathiques inscrits au parcours académique, Retours de patientes, Preuves scientifiques, Réduction du coût des séances pour les patientes | Y12: Insuffisance de preuves scientifiques, Insuffisance de collaboration interprofessionnelle avec des ostéopathes, Coût pour les patientes | Z12: Caractère chronique ou aigu des douleurs, Réponse ou non aux autres traitements, Motivation des patientes pour une prise en charge manuelle complémentaire, Disponibilité et/ou accessibilité d’ostéopathes dans votre réseau | AA12: Oui | AB12: Oui | AC12: Oui | AD12: Preuves de résultats positifs des traitements ostéopathiques, Demande des patientes, Absence ou inefficacité d’autres solutions thérapeutiques, Mise en place de protocoles règlementés | AE12: 0 | AF12: 0 | AG12: 0 | AH12: 0 | AI12: 0 | AJ12: 0
A13: Étudiant(e) sage-femme en 5e année | B13: 0 | C13: 0 | D13: 1 | E13: 3 | F13: 1 | G13: Sans avis | H13: Non | I13: 0 | J13: 2 | K13: Interrogatoire, Examen clinique, En excluant d’autres causes possibles de douleurs pelviennes pendant la grossesse | L13: Jamais | M13: Oui | N13: Absence de formation spécifique sur le syndrome | O13: Repos/Limitation de mouvement | P13: Conseils posturaux | Q13: Exercices/Etirements | R13: Ceinture de maintien/Support pelvien | S13: Traitements médicamenteux (antalgiques/analgésiques) | T13: Ostéopathie | U13: 4 | V13: En cas d’absence de réussite d’autres prises en charge | W13: 1 | X13: Contenus pédagogiques sur les principes ostéopathiques inscrits au parcours académique, Preuves scientifiques, Réduction du coût des séances pour les patientes, Intégration de l’ostéopathie dans les structures de santé | Y13: Peu de contenus pédagogiques sur les principes ostéopathiques inscrits au parcours académique, Absence de connaissances sur la pratique ostéopathique, Insuffisance de collaboration interprofessionnelle avec des ostéopathes | Z13: Caractère chronique ou aigu des douleurs, Réponse ou non aux autres traitements, Spécialisation de l’ostéopathe en périnatalité, Motivation des patientes pour une prise en charge manuelle complémentaire, Disponibilité et/ou accessibilité d’ostéopathes dans votre réseau, Collaboration interprofessionnelle préexistante, Convictions personnelles concernant cette approche thérapeutique | AA13: Non | AB13: Oui | AC13: Oui | AD13: Demande des patientes, Formations sémiologiques supplémentaires des ostéopathes, Absence ou inefficacité d’autres solutions thérapeutiques, Mise en place de protocoles règlementés, Encadrement institutionnel et recommandations officielles | AE13: 0 | AF13: 0 | AG13: 0 | AH13: 0 | AI13: 0 | AJ13: 0
A14: Sage-femme diplômé(e) | B14: Moins de 2 ans | C14: Hospitalier | D14: 4 | E14: 5 | F14: 3 | G14: Non | H14: Oui, occasionnellement (> ou = à 1 fois par mois) | I14: Suivi prénatal de grossesse, Douleurs lombaires et/ou pelviennes, Post-partum | J14: 4 | K14: Interrogatoire, En excluant d’autres causes possibles de douleurs pelviennes pendant la grossesse | L14: Fréquemment (> ou = à 1 fois par semaine) | M14: Non | N14: Assimilation du syndrome à des lombalgies non spécifiques, Absence de recommandations professionnelles claires | O14: Ceinture de maintien/Support pelvien | P14: Conseils posturaux | Q14: Ostéopathie | R14: Exercices/Etirements | S14: Traitements médicamenteux (antalgiques/analgésiques) | T14: Repos/Limitation de mouvement | U14: 5 | V14: Dès les premiers symptômes | W14: 3 | X14: Contenus pédagogiques sur les principes ostéopathiques inscrits au parcours académique, Preuves scientifiques, Reconnaissance institutionnelle, Intégration de l’ostéopathie dans les structures de santé | Y14: Coût pour les patientes, Absence de reconnaissance institutionnelle | Z14: Spécialisation de l’ostéopathe en périnatalité, Motivation des patientes pour une prise en charge manuelle complémentaire, Disponibilité et/ou accessibilité d’ostéopathes dans votre réseau, Collaboration interprofessionnelle préexistante, Convictions personnelles concernant cette approche thérapeutique, Expérience personnelle antérieure positive ou négative avec l’ostéopathie | AA14: Sans avis | AB14: Oui | AC14: Oui | AD14: Demande des patientes, Formations sémiologiques supplémentaires des ostéopathes, Recommandations par d’autres professionnels de santé, Mise en place de protocoles règlementés, Encadrement institutionnel et recommandations officielles | AE14: 0 | AF14: 0 | AG14: J'ai déjà rencontré des ostéopathes et kinésithérapeute spécialisés en périnatalité et c'était très intéressant car ils ont des connaissances en terme de mobilité, posture etc que nous sages femmes n'avons pas du tout. Nous avons tour intérêt à travailler ensemble. | AH14: Favorable à l’intégration de l’ostéopathie, Collaboration interprofessionnelle, Spécialisation en périnatalité | AI14: Étude très intéressante qui mérite d'être publiée dans une revue médicale car l'ostéopathie est encore beaucoup rejeté par certains professionnels de santé | AJ14: Etude intéressante, Intérêt scientifique, Présence de réticences professionnelles à l'ostéopathie
A15: Sage-femme diplômé(e) | B15: 5 à 10 ans | C15: Hospitalier | D15: 4 | E15: 4 | F15: 4 | G15: Non | H15: Oui, occasionnellement (> ou = à 1 fois par mois) | I15: Douleurs lombaires et/ou pelviennes, Post-partum | J15: 4 | K15: Interrogatoire, Examen clinique | L15: Occasionnellement (> ou = à 1 fois par mois) | M15: Oui | N15: Sous-estimation des plaintes des patientes, Difficultés d’accès aux thérapies non médicamenteuses | O15: Exercices/Etirements | P15: Ostéopathie | Q15: Ceinture de maintien/Support pelvien | R15: Conseils posturaux | S15: Repos/Limitation de mouvement | T15: Traitements médicamenteux (antalgiques/analgésiques) | U15: 4 | V15: En cas d’absence de réussite d’autres prises en charge | W15: 1 | X15: Preuves scientifiques, Médiatisation/Réseaux sociaux, Intégration de l’ostéopathie dans les structures de santé | Y15: Insuffisance de preuves scientifiques, Insuffisance de collaboration interprofessionnelle avec des ostéopathes | Z15: Convictions personnelles concernant cette approche thérapeutique, Expérience personnelle antérieure positive ou négative avec l’ostéopathie | AA15: Non | AB15: Oui | AC15: Oui | AD15: Mise en place de protocoles règlementés, Encadrement institutionnel et recommandations officielles | AE15: 0 | AF15: 0 | AG15: 0 | AH15: 0 | AI15: 0 | AJ15: 0
A16: Sage-femme diplômé(e) | B16: 5 à 10 ans | C16: Hospitalier | D16: 3 | E16: 5 | F16: 4 | G16: Non | H16: Oui, occasionnellement (> ou = à 1 fois par mois) | I16: Préparation à l’accouchement, Post-partum | J16: 5 | K16: Interrogatoire, Examen clinique | L16: Occasionnellement (> ou = à 1 fois par mois) | M16: Oui | N16: Assimilation du syndrome à des lombalgies non spécifiques | O16: Ostéopathie | P16: Conseils posturaux | Q16: Traitements médicamenteux (antalgiques/analgésiques) | R16: Exercices/Etirements | S16: Ceinture de maintien/Support pelvien | T16: Repos/Limitation de mouvement | U16: 5 | V16: Dès les premiers symptômes | W16: 2 | X16: Contenus pédagogiques sur les principes ostéopathiques inscrits au parcours académique, Intégration de l’ostéopathie dans les structures de santé | Y16: Peu de contenus pédagogiques sur les principes ostéopathiques inscrits au parcours académique, Insuffisance de collaboration interprofessionnelle avec des ostéopathes, Coût pour les patientes | Z16: Caractère chronique ou aigu des douleurs, Spécialisation de l’ostéopathe en périnatalité, Motivation des patientes pour une prise en charge manuelle complémentaire, Disponibilité et/ou accessibilité d’ostéopathes dans votre réseau | AA16: Non | AB16: Oui | AC16: Oui | AD16: Demande des patientes, Encadrement institutionnel et recommandations officielles | AE16: 0 | AF16: 0 | AG16: 0 | AH16: 0 | AI16: 0 | AJ16: 0
A17: Sage-femme diplômé(e) | B17: 5 à 10 ans | C17: Hospitalier | D17: 2 | E17: 3 | F17: 2 | G17: Non | H17: Oui, rarement (< à 1 fois par mois) | I17: Post-partum | J17: 3 | K17: Interrogatoire, Examen clinique | L17: Occasionnellement (> ou = à 1 fois par mois) | M17: Sans avis | N17: 0 | O17: Exercices/Etirements | P17: Traitements médicamenteux (antalgiques/analgésiques) | Q17: Ostéopathie, Conseils posturaux | R17: Ceinture de maintien/Support pelvien | S17: Repos/Limitation de mouvement | T17: Traitements médicamenteux (antalgiques/analgésiques) | U17: 4 | V17: Dès les premiers symptômes | W17: 2 | X17: Contenus pédagogiques sur les principes ostéopathiques inscrits au parcours académique, Preuves scientifiques, Réduction du coût des séances pour les patientes, Reconnaissance institutionnelle, Intégration de l’ostéopathie dans les structures de santé | Y17: Peu de contenus pédagogiques sur les principes ostéopathiques inscrits au parcours académique, Absence de connaissances sur la pratique ostéopathique, Insuffisance de preuves scientifiques, Insuffisance de collaboration interprofessionnelle avec des ostéopathes, Coût pour les patientes, Absence de reconnaissance institutionnelle | Z17: Spécialisation de l’ostéopathe en périnatalité, Motivation des patientes pour une prise en charge manuelle complémentaire, Expérience personnelle antérieure positive ou négative avec l’ostéopathie | AA17: Oui | AB17: Oui | AC17: Oui | AD17: Preuves de résultats positifs des traitements ostéopathiques, Mise en place de protocoles règlementés, Encadrement institutionnel et recommandations officielles | AE17: 0 | AF17: 0 | AG17: 0 | AH17: 0 | AI17: 0 | AJ17: 0
A18: Sage-femme diplômé(e) | B18: Plus de 10 ans | C18: Hospitalier | D18: 3 | E18: 3 | F18: 3 | G18: Non | H18: Oui, occasionnellement (> ou = à 1 fois par mois) | I18: Douleurs lombaires et/ou pelviennes, Post-partum, Fertilité | J18: 4 | K18: Interrogatoire, Examen clinique, En excluant d’autres causes possibles de douleurs pelviennes pendant la grossesse | L18: Fréquemment (> ou = à 1 fois par semaine) | M18: Oui | N18: Assimilation du syndrome à des lombalgies non spécifiques, Sous-estimation des plaintes des patientes, Absence de recommandations professionnelles claires | O18: Conseils posturaux | P18: Traitements médicamenteux (antalgiques/analgésiques) | Q18: Ostéopathie | R18: Ceinture de maintien/Support pelvien | S18: Repos/Limitation de mouvement | T18: Exercices/Etirements | U18: 5 | V18: Dès les premiers symptômes | W18: 2 | X18: Contenus pédagogiques sur les principes ostéopathiques inscrits au parcours académique, Retours de patientes, Intégration de l’ostéopathie dans les structures de santé | Y18: Insuffisance de preuves scientifiques, Insuffisance de collaboration interprofessionnelle avec des ostéopathes | Z18: Réponse ou non aux autres traitements, Spécialisation de l’ostéopathe en périnatalité, Convictions personnelles concernant cette approche thérapeutique | AA18: Oui | AB18: Oui | AC18: Oui | AD18: Preuves de résultats positifs des traitements ostéopathiques | AE18: 0 | AF18: 0 | AG18: 0 | AH18: 0 | AI18: 0 | AJ18: 0
A19: Sage-femme diplômé(e) | B19: 2 à 5 ans | C19: Hospitalier | D19: 2 | E19: 3 | F19: 3 | G19: Non | H19: Oui, occasionnellement (> ou = à 1 fois par mois) | I19: Douleurs lombaires et/ou pelviennes, Post-partum | J19: 5 | K19: Interrogatoire, Examen clinique | L19: Fréquemment (> ou = à 1 fois par semaine) | M19: Non | N19: 0 | O19: Exercices/Etirements | P19: Conseils posturaux | Q19: Ceinture de maintien/Support pelvien | R19: Traitements médicamenteux (antalgiques/analgésiques) | S19: Ostéopathie | T19: Repos/Limitation de mouvement | U19: 4 | V19: Dès les premiers symptômes | W19: 3 | X19: Contenus pédagogiques sur les principes ostéopathiques inscrits au parcours académique, Preuves scientifiques, Reconnaissance institutionnelle | Y19: Insuffisance de preuves scientifiques, Absence de reconnaissance institutionnelle | Z19: Réponse ou non aux autres traitements | AA19: Oui | AB19: Oui | AC19: Oui | AD19: Preuves de résultats positifs des traitements ostéopathiques, Mise en place de protocoles règlementés, Encadrement institutionnel et recommandations officielles | AE19: 0 | AF19: 0 | AG19: 0 | AH19: 0 | AI19: 0 | AJ19: 0
A20: Sage-femme diplômé(e) | B20: 5 à 10 ans | C20: Hospitalier | D20: 1 | E20: 4 | F20: 2 | G20: Sans avis | H20: Non | I20: 0 | J20: 2 | K20: En excluant d’autres causes possibles de douleurs pelviennes pendant la grossesse | L20: Occasionnellement (> ou = à 1 fois par mois) | M20: Sans avis | N20: 0 | O20: Repos/Limitation de mouvement | P20: Exercices/Etirements | Q20: Conseils posturaux | R20: Ostéopathie | S20: Ceinture de maintien/Support pelvien | T20: Traitements médicamenteux (antalgiques/analgésiques) | U20: 5 | V20: En cas d’absence de réussite d’autres prises en charge | W20: 3 | X20: Contenus pédagogiques sur les principes ostéopathiques inscrits au parcours académique, Retours de patientes, Preuves scientifiques, Médiatisation/Réseaux sociaux, Réduction du coût des séances pour les patientes, Reconnaissance institutionnelle, Intégration de l’ostéopathie dans les structures de santé | Y20: Peu de contenus pédagogiques sur les principes ostéopathiques inscrits au parcours académique, Absence de connaissances sur la pratique ostéopathique | Z20: Caractère chronique ou aigu des douleurs, Réponse ou non aux autres traitements, Spécialisation de l’ostéopathe en périnatalité | AA20: Sans avis | AB20: Oui | AC20: Oui | AD20: Preuves de résultats positifs des traitements ostéopathiques, Demande des patientes | AE20: 0 | AF20: 0 | AG20: 0 | AH20: 0 | AI20: 0 | AJ20: 0
A21: Sage-femme diplômé(e) | B21: Moins de 2 ans | C21: Hospitalier | D21: 4 | E21: 5 | F21: 3 | G21: Non | H21: Non | I21: 0 | J21: 3 | K21: Interrogatoire, Examen clinique | L21: Rarement (> ou = à 1 fois tous les 3 mois) | M21: Oui | N21: Absence de formation spécifique sur le syndrome, Assimilation du syndrome à des lombalgies non spécifiques, Sous-estimation des plaintes des patientes | O21: Repos/Limitation de mouvement | P21: Repos/Limitation de mouvement | Q21: Repos/Limitation de mouvement | R21: Ceinture de maintien/Support pelvien | S21: Ceinture de maintien/Support pelvien | T21: Ceinture de maintien/Support pelvien | U21: 5 | V21: Dès les premiers symptômes | W21: 2 | X21: Contenus pédagogiques sur les principes ostéopathiques inscrits au parcours académique, Médiatisation/Réseaux sociaux, Réduction du coût des séances pour les patientes, Intégration de l’ostéopathie dans les structures de santé | Y21: Peu de contenus pédagogiques sur les principes ostéopathiques inscrits au parcours académique, Absence de connaissances sur la pratique ostéopathique, Insuffisance de preuves scientifiques | Z21: Spécialisation de l’ostéopathe en périnatalité, Motivation des patientes pour une prise en charge manuelle complémentaire, Moment de la douleur, Disponibilité et/ou accessibilité d’ostéopathes dans votre réseau, Convictions personnelles concernant cette approche thérapeutique | AA21: Sans avis | AB21: Oui | AC21: Oui | AD21: Preuves de résultats positifs des traitements ostéopathiques, Demande des patientes | AE21: 0 | AF21: 0 | AG21: 0 | AH21: 0 | AI21: 0 | AJ21: 0
A22: Sage-femme diplômé(e) | B22: Plus de 10 ans | C22: Hospitalier | D22: 3 | E22: 2 | F22: 3 | G22: Non | H22: Non | I22: 0 | J22: 4 | K22: Interrogatoire, Examen clinique, En excluant d’autres causes possibles de douleurs pelviennes pendant la grossesse | L22: Occasionnellement (> ou = à 1 fois par mois) | M22: Non | N22: 0 | O22: Conseils posturaux | P22: Ceinture de maintien/Support pelvien | Q22: Ostéopathie | R22: Traitements médicamenteux (antalgiques/analgésiques) | S22: Exercices/Etirements | T22: Repos/Limitation de mouvement | U22: 3 | V22: En cas d’absence de réussite d’autres prises en charge | W22: 2 | X22: Preuves scientifiques, Reconnaissance institutionnelle, Intégration de l’ostéopathie dans les structures de santé | Y22: Insuffisance de preuves scientifiques, Insuffisance de collaboration interprofessionnelle avec des ostéopathes, Absence de reconnaissance institutionnelle | Z22: Réponse ou non aux autres traitements, Spécialisation de l’ostéopathe en périnatalité, Motivation des patientes pour une prise en charge manuelle complémentaire, Collaboration interprofessionnelle préexistante, Convictions personnelles concernant cette approche thérapeutique | AA22: Oui | AB22: Oui | AC22: Oui | AD22: Demande des patientes, Formations sémiologiques supplémentaires des ostéopathes, Mise en place de protocoles règlementés, Encadrement institutionnel et recommandations officielles | AE22: 0 | AF22: 0 | AG22: 0 | AH22: 0 | AI22: 0 | AJ22: 0
A23: Sage-femme diplômé(e) | B23: Plus de 10 ans | C23: Hospitalier | D23: 1 | E23: 4 | F23: 1 | G23: Non | H23: Non | I23: 0 | J23: 3 | K23: Interrogatoire, Examen clinique, En excluant d’autres causes possibles de douleurs pelviennes pendant la grossesse | L23: Rarement (> ou = à 1 fois tous les 3 mois) | M23: Oui | N23: Absence de formation spécifique sur le syndrome, Assimilation du syndrome à des lombalgies non spécifiques, Sous-estimation des plaintes des patientes, Difficultés d’accès aux thérapies non médicamenteuses, Absence de recommandations professionnelles claires | O23: Exercices/Etirements | P23: Traitements médicamenteux (antalgiques/analgésiques) | Q23: Conseils posturaux | R23: Ceinture de maintien/Support pelvien | S23: Repos/Limitation de mouvement | T23: Ostéopathie | U23: 4 | V23: Dès les premiers symptômes | W23: 1 | X23: Retours de patientes, Preuves scientifiques, Réduction du coût des séances pour les patientes, Intégration de l’ostéopathie dans les structures de santé | Y23: Absence de connaissances sur la pratique ostéopathique, Insuffisance de preuves scientifiques | Z23: Réponse ou non aux autres traitements, Collaboration interprofessionnelle préexistante | AA23: Sans avis | AB23: Sans avis | AC23: Sans avis | AD23: Mise en place de protocoles règlementés | AE23: 0 | AF23: 0 | AG23: 0 | AH23: 0 | AI23: 0 | AJ23: 0
A24: Sage-femme diplômé(e) | B24: Plus de 10 ans | C24: Hospitalier | D24: 2 | E24: 3 | F24: 4 | G24: Oui | H24: Oui, rarement (< à 1 fois par mois) | I24: Douleurs lombaires et/ou pelviennes, Post-partum, Sphère émotionnelle | J24: 5 | K24: Interrogatoire, Examen clinique, En excluant d’autres causes possibles de douleurs pelviennes pendant la grossesse | L24: Occasionnellement (> ou = à 1 fois par mois) | M24: Non | N24: 0 | O24: Conseils posturaux | P24: Exercices/Etirements | Q24: Traitements médicamenteux (antalgiques/analgésiques) | R24: Ceinture de maintien/Support pelvien | S24: Ostéopathie | T24: Repos/Limitation de mouvement | U24: 3 | V24: En cas d’absence de réussite d’autres prises en charge | W24: 4 | X24: Preuves scientifiques, Réduction du coût des séances pour les patientes, Reconnaissance institutionnelle | Y24: Insuffisance de preuves scientifiques, Coût pour les patientes, Absence de reconnaissance institutionnelle | Z24: Réponse ou non aux autres traitements, Motivation des patientes pour une prise en charge manuelle complémentaire, Disponibilité et/ou accessibilité d’ostéopathes dans votre réseau, Collaboration interprofessionnelle préexistante, Coût pour les patientes | AA24: Oui | AB24: Sans avis | AC24: Sans avis | AD24: Preuves de résultats positifs des traitements ostéopathiques, Mise en place de protocoles règlementés, Encadrement institutionnel et recommandations officielles | AE24: 0 | AF24: 0 | AG24: en ai bénéficié personnellement mais sans effet notable, hormis moment d'écoute et de réassurance, j'étais plutôt favorable à cette pratique mais l'absence de preuves scientifiques et le coût de la.séance inaccessible à une partie de nos patientes m'empêchent de le conseiller à large échelle. malgré tout ai une consœur formée, à qui j'adresse des patientes en cas d'échec d'autres solutions car pris en charge comme une consultation sage-femme à l'hôpital | AH24: Bénéfices subjectifs, Insuffisance de preuves scientifiques, Coût pout les patientes, Collaboration interprofessionnelle, | AI24: 0 | AJ24: 0
A25: Sage-femme diplômé(e) | B25: Plus de 10 ans | C25: Hospitalier | D25: 2 | E25: 2 | F25: 1 | G25: Non | H25: Non | I25: Douleurs lombaires et/ou pelviennes, Post-partum | J25: 3 | K25: Interrogatoire, Examen clinique, En excluant d’autres causes possibles de douleurs pelviennes pendant la grossesse | L25: Fréquemment (> ou = à 1 fois par semaine) | M25: Non | N25: 0 | O25: Conseils posturaux | P25: Traitements médicamenteux (antalgiques/analgésiques) | Q25: Ostéopathie | R25: Exercices/Etirements | S25: Ceinture de maintien/Support pelvien | T25: Repos/Limitation de mouvement | U25: 3 | V25: En cas d’absence de réussite d’autres prises en charge | W25: 2 | X25: Réduction du coût des séances pour les patientes | Y25: Coût pour les patientes | Z25: Réponse ou non aux autres traitements, Spécialisation de l’ostéopathe en périnatalité, Motivation des patientes pour une prise en charge manuelle complémentaire | AA25: Sans avis | AB25: Sans avis | AC25: Non | AD25: Mise en place de protocoles règlementés | AE25: 0 | AF25: 0 | AG25: 0 | AH25: 0 | AI25: 0 | AJ25: 0
A26: Sage-femme diplômé(e) | B26: Plus de 10 ans | C26: Libéral | D26: 2 | E26: 5 | F26: 4 | G26: Oui | H26: Oui, régulièrement (> ou = à 1 fois par semaine) | I26: Suivi prénatal de grossesse, Préparation à l’accouchement, Douleurs lombaires et/ou pelviennes, Post-partum | J26: 2 | K26: En excluant d’autres causes possibles de douleurs pelviennes pendant la grossesse | L26: Rarement (> ou = à 1 fois tous les 3 mois) | M26: Oui | N26: Sous-estimation des plaintes des patientes, Absence de recommandations professionnelles claires | O26: Exercices/Etirements | P26: Conseils posturaux | Q26: Ostéopathie | R26: Ceinture de maintien/Support pelvien | S26: Traitements médicamenteux (antalgiques/analgésiques) | T26: Repos/Limitation de mouvement | U26: 3 | V26: En cas d’absence de réussite d’autres prises en charge | W26: 4 | X26: Preuves scientifiques | Y26: Peu de contenus pédagogiques sur les principes ostéopathiques inscrits au parcours académique, Insuffisance de preuves scientifiques, Absence de reconnaissance institutionnelle | Z26: Motivation des patientes pour une prise en charge manuelle complémentaire | AA26: Non | AB26: Oui | AC26: Oui | AD26: Mise en place de protocoles règlementés, Encadrement institutionnel et recommandations officielles | AE26: 0 | AF26: 0 | AG26: 0 | AH26: 0 | AI26: 0 | AJ26: 0
A27: Sage-femme diplômé(e) | B27: Plus de 10 ans | C27: Mixte | D27: 4 | E27: 1 | F27: 4 | G27: Oui | H27: Non | I27: 0 | J27: 5 | K27: Interrogatoire, Examen clinique, En excluant d’autres causes possibles de douleurs pelviennes pendant la grossesse | L27: Occasionnellement (> ou = à 1 fois par mois) | M27: Oui | N27: Absence de formation spécifique sur le syndrome, Assimilation du syndrome à des lombalgies non spécifiques, Sous-estimation des plaintes des patientes, Absence de recommandations professionnelles claires | O27: Exercices/Etirements | P27: Traitements médicamenteux (antalgiques/analgésiques) | Q27: Conseils posturaux | R27: Ceinture de maintien/Support pelvien | S27: Ostéopathie | T27: Repos/Limitation de mouvement | U27: 2 | V27: 0 | W27: 1 | X27: Preuves scientifiques | Y27: Insuffisance de preuves scientifiques | Z27: Motivation des patientes pour une prise en charge manuelle complémentaire, Convictions personnelles concernant cette approche thérapeutique | AA27: Oui | AB27: Non | AC27: Non | AD27: Preuves de résultats positifs des traitements ostéopathiques, Encadrement institutionnel et recommandations officielles | AE27: 0 | AF27: 0 | AG27: Actes hors nomenclature à l'efficacité non proouvée, ce serait une forme d'abus de faiblesse de laisser des patientes dépenser de l'argent en leur faisant croire que ça va les aider. | AH27: Insuffisance de preuves scientifiques, Freins éthiques et scientifiques | AI27: aujourd'hui les instances de référence (santé.gouv, inserm, ... alertenet sur les dangers de la pratique de l'ostéopathie. Les bénéfices ne sont pas avérés alors que les risques, complications et retards de prise en charge sont réels. Je ne reccomande plus la pratique de l'ostéopathie à mes patientes et encore moins pour les bébés | AJ27: Insuffisance de preuves scientifiques, Non recommandation institutionnelle de l'ostéopathie, Convictions personnelles, Présence de réticences professionnelles à l'ostéopathie
A28: Sage-femme diplômé(e) | B28: Plus de 10 ans | C28: Hospitalier | D28: 1 | E28: 3 | F28: 1 | G28: Oui | H28: Oui, rarement (< à 1 fois par mois) | I28: Suivi prénatal de grossesse, Douleurs lombaires et/ou pelviennes, Post-partum, Allaitement | J28: 3 | K28: Interrogatoire, Examen clinique, En excluant d’autres causes possibles de douleurs pelviennes pendant la grossesse | L28: Fréquemment (> ou = à 1 fois par semaine) | M28: Sans avis | N28: Sous-estimation des plaintes des patientes, Absence de recommandations professionnelles claires | O28: Exercices/Etirements | P28: Ostéopathie | Q28: Conseils posturaux | R28: Ceinture de maintien/Support pelvien | S28: Traitements médicamenteux (antalgiques/analgésiques) | T28: Repos/Limitation de mouvement | U28: 4 | V28: En cas d’absence de réussite d’autres prises en charge | W28: 4 | X28: Retours de patientes, Preuves scientifiques, Réduction du coût des séances pour les patientes, Reconnaissance institutionnelle, Intégration de l’ostéopathie dans les structures de santé | Y28: Insuffisance de preuves scientifiques, Insuffisance de collaboration interprofessionnelle avec des ostéopathes, Coût pour les patientes | Z28: Caractère chronique ou aigu des douleurs, Réponse ou non aux autres traitements, Motivation des patientes pour une prise en charge manuelle complémentaire, Disponibilité et/ou accessibilité d’ostéopathes dans votre réseau, Convictions personnelles concernant cette approche thérapeutique, Expérience personnelle antérieure positive ou négative avec l’ostéopathie | AA28: Non | AB28: Oui | AC28: Oui | AD28: Preuves de résultats positifs des traitements ostéopathiques, Demande des patientes, Absence ou inefficacité d’autres solutions thérapeutiques | AE28: Souvent ça soulage mais sur une courte durée | AF28: Efficacité perçue, Soulagement temporaire | AG28: Les sages-femmes sont majoritairement pro-ostéopathie | AH28: Favorable à l'intégration de l'ostéopathie | AI28: La prise en charge doit toujours être globale et pluridisciplinaire (osteo, kiné, sf, médecin, acupuncture...) | AJ28: Collaboration interprofessionnelle, Favorable à l'intégration de l'ostéopathie
A29: Sage-femme diplômé(e) | B29: Moins de 2 ans | C29: Hospitalier | D29: 3 | E29: 5 | F29: 3 | G29: Oui | H29: Oui, occasionnellement (> ou = à 1 fois par mois) | I29: Suivi prénatal de grossesse, Douleurs lombaires et/ou pelviennes, Post-partum | J29: 3 | K29: Interrogatoire, Examen clinique, En excluant d’autres causes possibles de douleurs pelviennes pendant la grossesse | L29: Rarement (> ou = à 1 fois tous les 3 mois) | M29: Oui | N29: Absence de formation spécifique sur le syndrome, Assimilation du syndrome à des lombalgies non spécifiques | O29: Exercices/Etirements | P29: Ostéopathie | Q29: Conseils posturaux | R29: Ceinture de maintien/Support pelvien | S29: Repos/Limitation de mouvement | T29: Traitements médicamenteux (antalgiques/analgésiques) | U29: 5 | V29: Prise en charge prénatale et post-partum | W29: 2 | X29: Contenus pédagogiques sur les principes ostéopathiques inscrits au parcours académique, Retours de patientes, Preuves scientifiques, Réduction du coût des séances pour les patientes, Intégration de l’ostéopathie dans les structures de santé | Y29: Peu de contenus pédagogiques sur les principes ostéopathiques inscrits au parcours académique, Coût pour les patientes | Z29: Motivation des patientes pour une prise en charge manuelle complémentaire, Collaboration interprofessionnelle préexistante, Convictions personnelles concernant cette approche thérapeutique, Expérience personnelle antérieure positive ou négative avec l’ostéopathie | AA29: Non | AB29: Oui | AC29: Oui | AD29: Mise en place de protocoles règlementés, Encadrement institutionnel et recommandations officielles | AE29: 0 | AF29: 0 | AG29: 0 | AH29: 0 | AI29: 0 | AJ29: 0
A30: Sage-femme diplômé(e) | B30: Plus de 10 ans | C30: Libéral | D30: 4 | E30: 5 | F30: 4 | G30: Oui | H30: Oui, régulièrement (> ou = à 1 fois par semaine) | I30: Suivi prénatal de grossesse, Préparation à l’accouchement, Douleurs lombaires et/ou pelviennes, Troubles digestifs associés, Post-partum, Fertilité, Allaitement, Sphère émotionnelle | J30: 3 | K30: Interrogatoire, Examen clinique, En excluant d’autres causes possibles de douleurs pelviennes pendant la grossesse | L30: Fréquemment (> ou = à 1 fois par semaine) | M30: Sans avis | N30: 0 | O30: Exercices/Etirements | P30: Ostéopathie | Q30: Conseils posturaux | R30: Repos/Limitation de mouvement | S30: Ceinture de maintien/Support pelvien | T30: Traitements médicamenteux (antalgiques/analgésiques) | U30: 5 | V30: Dès les premiers symptômes | W30: 3 | X30: Preuves scientifiques, Réduction du coût des séances pour les patientes, Reconnaissance institutionnelle | Y30: Insuffisance de preuves scientifiques, Coût pour les patientes, Absence de reconnaissance institutionnelle | Z30: Caractère chronique ou aigu des douleurs, Motivation des patientes pour une prise en charge manuelle complémentaire | AA30: Non | AB30: Oui | AC30: Oui | AD30: Preuves de résultats positifs des traitements ostéopathiques, Encadrement institutionnel et recommandations officielles | AE30: 0 | AF30: 0 | AG30: 0 | AH30: 0 | AI30: 0 | AJ30: 0
A31: Sage-femme diplômé(e) | B31: Moins de 2 ans | C31: Hospitalier | D31: 1 | E31: 1 | F31: 2 | G31: Sans avis | H31: Non | I31: 0 | J31: 3 | K31: Interrogatoire, Examen clinique, En excluant d’autres causes possibles de douleurs pelviennes pendant la grossesse | L31: Occasionnellement (> ou = à 1 fois par mois) | M31: Sans avis | N31: 0 | O31: Exercices/Etirements | P31: Traitements médicamenteux (antalgiques/analgésiques) | Q31: Conseils posturaux | R31: Ceinture de maintien/Support pelvien | S31: Repos/Limitation de mouvement | T31: Ostéopathie | U31: 1 | V31: 0 | W31: 3 | X31: 0 | Y31: Absence de reconnaissance institutionnelle, Insuffisance de preuves scientifiques | Z31: Convictions personnelles concernant cette approche thérapeutique | AA31: Sans avis | AB31: Non | AC31: Non | AD31: Preuves de résultats positifs des traitements ostéopathiques | AE31: 0 | AF31: 0 | AG31: 0 | AH31: 0 | AI31: 0 | AJ31: 0
A32: Sage-femme diplômé(e) | B32: Plus de 10 ans | C32: Libéral | D32: 4 | E32: 5 | F32: 4 | G32: Oui | H32: Oui, régulièrement (> ou = à 1 fois par semaine) | I32: Suivi prénatal de grossesse, Douleurs lombaires et/ou pelviennes, Post-partum, Fertilité | J32: 4 | K32: Interrogatoire, En excluant d’autres causes possibles de douleurs pelviennes pendant la grossesse | L32: Occasionnellement (> ou = à 1 fois par mois) | M32: Sans avis | N32: Assimilation du syndrome à des lombalgies non spécifiques, Sous-estimation des plaintes des patientes, Absence de recommandations professionnelles claires | O32: Ceinture de maintien/Support pelvien | P32: Ostéopathie | Q32: Exercices/Etirements | R32: Conseils posturaux | S32: Traitements médicamenteux (antalgiques/analgésiques) | T32: Repos/Limitation de mouvement | U32: 4 | V32: Dès les premiers symptômes | W32: 3 | X32: Preuves scientifiques, Reconnaissance institutionnelle, Intégration de l’ostéopathie dans les structures de santé | Y32: Insuffisance de preuves scientifiques, Coût pour les patientes | Z32: Spécialisation de l’ostéopathe en périnatalité, Motivation des patientes pour une prise en charge manuelle complémentaire, Collaboration interprofessionnelle préexistante, Expérience personnelle antérieure positive ou négative avec l’ostéopathie | AA32: Sans avis | AB32: Oui | AC32: Oui | AD32: Preuves de résultats positifs des traitements ostéopathiques, Demande des patientes, Formations sémiologiques supplémentaires des ostéopathes, Encadrement institutionnel et recommandations officielles | AE32: 0 | AF32: 0 | AG32: J ai eu la chance de collaborer à l’hôpital avec une ostéopathe qui venait proposer des consultations au sein de laMaternité et plus tard en cabinet libéral avec une collègue osteo, amis aussi des sage-femmes ostéopathes( deux formation distinctes) | AH32: Collaboration interprofessionnelle, Favorable à l'intégration de l'ostéopathie | AI32: 0 | AJ32: 0
A33: Sage-femme diplômé(e) | B33: Plus de 10 ans | C33: Hospitalier | D33: 4 | E33: 5 | F33: 4 | G33: Non | H33: Non | I33: 0 | J33: 4 | K33: Interrogatoire, Examen clinique, En excluant d’autres causes possibles de douleurs pelviennes pendant la grossesse | L33: Fréquemment (> ou = à 1 fois par semaine) | M33: Oui | N33: Absence de formation spécifique sur le syndrome, Sous-estimation des plaintes des patientes, Difficultés d’accès aux thérapies non médicamenteuses | O33: Traitements médicamenteux (antalgiques/analgésiques) | P33: Ostéopathie | Q33: Conseils posturaux | R33: Ceinture de maintien/Support pelvien | S33: Exercices/Etirements | T33: Repos/Limitation de mouvement | U33: 5 | V33: Dès les premiers symptômes | W33: 3 | X33: Réduction du coût des séances pour les patientes, Reconnaissance institutionnelle, Intégration de l’ostéopathie dans les structures de santé | Y33: Absence de connaissances sur la pratique ostéopathique, Insuffisance de collaboration interprofessionnelle avec des ostéopathes, Coût pour les patientes, Absence de reconnaissance institutionnelle | Z33: Caractère chronique ou aigu des douleurs, Réponse ou non aux autres traitements, Motivation des patientes pour une prise en charge manuelle complémentaire, Disponibilité et/ou accessibilité d’ostéopathes dans votre réseau, Convictions personnelles concernant cette approche thérapeutique, Expérience personnelle antérieure positive ou négative avec l’ostéopathie | AA33: Non | AB33: Oui | AC33: Oui | AD33: Demande des patientes, Encadrement institutionnel et recommandations officielles | AE33: 0 | AF33: 0 | AG33: 0 | AH33: 0 | AI33: 0 | AJ33: 0
A34: Sage-femme diplômé(e) | B34: 2 à 5 ans | C34: Libéral | D34: 4 | E34: 5 | F34: 4 | G34: Oui | H34: Oui, régulièrement (> ou = à 1 fois par semaine) | I34: Suivi prénatal de grossesse, Préparation à l’accouchement, Douleurs lombaires et/ou pelviennes, Troubles digestifs associés, Post-partum | J34: 4 | K34: Interrogatoire, En excluant d’autres causes possibles de douleurs pelviennes pendant la grossesse | L34: Occasionnellement (> ou = à 1 fois par mois) | M34: Oui | N34: Absence de formation spécifique sur le syndrome, Assimilation du syndrome à des lombalgies non spécifiques, Sous-estimation des plaintes des patientes, Difficultés d’accès aux thérapies non médicamenteuses, Absence de recommandations professionnelles claires | O34: Ostéopathie | P34: Ceinture de maintien/Support pelvien | Q34: Exercices/Etirements | R34: Conseils posturaux | S34: Traitements médicamenteux (antalgiques/analgésiques) | T34: Repos/Limitation de mouvement | U34: 5 | V34: Dès les premiers symptômes | W34: 2 | X34: Contenus pédagogiques sur les principes ostéopathiques inscrits au parcours académique, Preuves scientifiques, Reconnaissance institutionnelle, Intégration de l’ostéopathie dans les structures de santé | Y34: Peu de contenus pédagogiques sur les principes ostéopathiques inscrits au parcours académique, Absence de connaissances sur la pratique ostéopathique, Insuffisance de preuves scientifiques, Insuffisance de collaboration interprofessionnelle avec des ostéopathes, Coût pour les patientes, Absence de reconnaissance institutionnelle | Z34: Caractère chronique ou aigu des douleurs, Réponse ou non aux autres traitements, Motivation des patientes pour une prise en charge manuelle complémentaire, Disponibilité et/ou accessibilité d’ostéopathes dans votre réseau, Convictions personnelles concernant cette approche thérapeutique, Expérience personnelle antérieure positive ou négative avec l’ostéopathie | AA34: Non | AB34: Oui | AC34: Oui | AD34: Preuves de résultats positifs des traitements ostéopathiques, Formations sémiologiques supplémentaires des ostéopathes, Recommandations par d’autres professionnels de santé, Mise en place de protocoles règlementés, Encadrement institutionnel et recommandations officielles | AE34: Je trouve que dans la plupart des cas, mes patientes sont soulagées avec peu de séances ! Mais parfois le côté "mécanique" de la grossesse et e la posture de l'enfant est impossible à dépasser... | AF34: Efficacité perçue, Limites des pratiques ostéopathiques | AG34: Notre cabinet collabore volontiers et de façon systématique. Les SF du Haut Rhin en général sont ouvertes à cette collaboration je pense. | AH34: Collaboration interprofessionnelle, Favorable à l'intégration de l'ostéopathie | AI34: 0 | AJ34: 0
A35: Sage-femme diplômé(e) | B35: 5 à 10 ans | C35: Libéral | D35: 3 | E35: 5 | F35: 4 | G35: Oui | H35: Oui, régulièrement (> ou = à 1 fois par semaine) | I35: Suivi prénatal de grossesse, Douleurs lombaires et/ou pelviennes, Troubles digestifs associés, Post-partum, Allaitement | J35: 3 | K35: Interrogatoire, Examen clinique | L35: Fréquemment (> ou = à 1 fois par semaine) | M35: Oui | N35: Absence de formation spécifique sur le syndrome, Assimilation du syndrome à des lombalgies non spécifiques, Sous-estimation des plaintes des patientes | O35: Exercices/Etirements | P35: Ostéopathie | Q35: Conseils posturaux | R35: Ceinture de maintien/Support pelvien | S35: Traitements médicamenteux (antalgiques/analgésiques) | T35: Repos/Limitation de mouvement | U35: 4 | V35: Dès les premiers symptômes | W35: 1 | X35: Retours de patientes, Preuves scientifiques, Médiatisation/Réseaux sociaux, Réduction du coût des séances pour les patientes, Reconnaissance institutionnelle, Intégration de l’ostéopathie dans les structures de santé | Y35: Peu de contenus pédagogiques sur les principes ostéopathiques inscrits au parcours académique, Absence de connaissances sur la pratique ostéopathique, Insuffisance de preuves scientifiques, Coût pour les patientes | Z35: Caractère chronique ou aigu des douleurs, Collaboration interprofessionnelle préexistante, Convictions personnelles concernant cette approche thérapeutique, Expérience personnelle antérieure positive ou négative avec l’ostéopathie | AA35: Non | AB35: Oui | AC35: Oui | AD35: Preuves de résultats positifs des traitements ostéopathiques, Demande des patientes, Recommandations par d’autres professionnels de santé | AE35: 0 | AF35: 0 | AG35: 0 | AH35: 0 | AI35: 0 | AJ35: 0
A36: Sage-femme diplômé(e) | B36: Plus de 10 ans | C36: Libéral | D36: 5 | E36: 5 | F36: 5 | G36: Oui | H36: Oui, régulièrement (> ou = à 1 fois par semaine) | I36: Suivi prénatal de grossesse, Préparation à l’accouchement, Douleurs lombaires et/ou pelviennes, Troubles digestifs associés, Post-partum, Fertilité, Allaitement | J36: 4 | K36: Interrogatoire, Examen clinique, En excluant d’autres causes possibles de douleurs pelviennes pendant la grossesse | L36: Fréquemment (> ou = à 1 fois par semaine) | M36: Sans avis | N36: Assimilation du syndrome à des lombalgies non spécifiques, Sous-estimation des plaintes des patientes, Difficultés d’accès aux thérapies non médicamenteuses, Absence de recommandations professionnelles claires | O36: Exercices/Etirements | P36: Conseils posturaux | Q36: Ostéopathie | R36: Ceinture de maintien/Support pelvien | S36: Traitements médicamenteux (antalgiques/analgésiques) | T36: Repos/Limitation de mouvement | U36: 5 | V36: Dès les premiers symptômes | W36: 2 | X36: Contenus pédagogiques sur les principes ostéopathiques inscrits au parcours académique, Retours de patientes, Réduction du coût des séances pour les patientes, Reconnaissance institutionnelle, Intégration de l’ostéopathie dans les structures de santé | Y36: Peu de contenus pédagogiques sur les principes ostéopathiques inscrits au parcours académique, Coût pour les patientes | Z36: Caractère chronique ou aigu des douleurs, Motivation des patientes pour une prise en charge manuelle complémentaire, Convictions personnelles concernant cette approche thérapeutique, Expérience personnelle antérieure positive ou négative avec l’ostéopathie | AA36: Sans avis | AB36: Oui | AC36: Oui | AD36: Preuves de résultats positifs des traitements ostéopathiques, Demande des patientes, Encadrement institutionnel et recommandations officielles | AE36: 0 | AF36: 0 | AG36: 0 | AH36: 0 | AI36: 0 | AJ36: 0
A37: Sage-femme diplômé(e) | B37: Plus de 10 ans | C37: Libéral | D37: 2 | E37: 4 | F37: 3 | G37: Non | H37: Oui, occasionnellement (> ou = à 1 fois par mois) | I37: Suivi prénatal de grossesse, Préparation à l’accouchement, Douleurs lombaires et/ou pelviennes, Allaitement | J37: 3 | K37: Interrogatoire, Examen clinique, En excluant d’autres causes possibles de douleurs pelviennes pendant la grossesse | L37: Occasionnellement (> ou = à 1 fois par mois) | M37: Oui | N37: Absence de formation spécifique sur le syndrome, Assimilation du syndrome à des lombalgies non spécifiques, Sous-estimation des plaintes des patientes, Difficultés d’accès aux thérapies non médicamenteuses, Absence de recommandations professionnelles claires | O37: Conseils posturaux | P37: Exercices/Etirements | Q37: Ostéopathie | R37: Ceinture de maintien/Support pelvien | S37: Traitements médicamenteux (antalgiques/analgésiques) | T37: Repos/Limitation de mouvement | U37: 5 | V37: Dès les premiers symptômes | W37: 1 | X37: Réduction du coût des séances pour les patientes, Reconnaissance institutionnelle | Y37: Absence de connaissances sur la pratique ostéopathique, Insuffisance de preuves scientifiques, Coût pour les patientes | Z37: Réponse ou non aux autres traitements, Spécialisation de l’ostéopathe en périnatalité, Collaboration interprofessionnelle préexistante | AA37: Oui | AB37: Oui | AC37: Oui | AD37: Preuves de résultats positifs des traitements ostéopathiques | AE37: 0 | AF37: 0 | AG37: 0 | AH37: 0 | AI37: 0 | AJ37: 0
A38: Sage-femme diplômé(e) | B38: Moins de 2 ans | C38: Hospitalier | D38: 3 | E38: 3 | F38: 2 | G38: Sans avis | H38: Non | I38: 0 | J38: 3 | K38: Interrogatoire, Examen clinique, En excluant d’autres causes possibles de douleurs pelviennes pendant la grossesse | L38: Rarement (> ou = à 1 fois tous les 3 mois) | M38: Sans avis | N38: 0 | O38: Repos/Limitation de mouvement | P38: Conseils posturaux | Q38: Traitements médicamenteux (antalgiques/analgésiques) | R38: Ceinture de maintien/Support pelvien | S38: Ostéopathie | T38: Exercices/Etirements | U38: 4 | V38: Dès les premiers symptômes | W38: 2 | X38: Contenus pédagogiques sur les principes ostéopathiques inscrits au parcours académique, Preuves scientifiques, Réduction du coût des séances pour les patientes, Intégration de l’ostéopathie dans les structures de santé | Y38: Peu de contenus pédagogiques sur les principes ostéopathiques inscrits au parcours académique | Z38: Spécialisation de l’ostéopathe en périnatalité, Motivation des patientes pour une prise en charge manuelle complémentaire | AA38: Sans avis | AB38: Oui | AC38: Oui | AD38: Preuves de résultats positifs des traitements ostéopathiques, Recommandations par d’autres professionnels de santé, Encadrement institutionnel et recommandations officielles | AE38: 0 | AF38: 0 | AG38: 0 | AH38: 0 | AI38: 0 | AJ38: 0
A39: Sage-femme diplômé(e) | B39: 5 à 10 ans | C39: Libéral | D39: 4 | E39: 4 | F39: 4 | G39: Non | H39: Oui, régulièrement (> ou = à 1 fois par semaine) | I39: Suivi prénatal de grossesse, Préparation à l’accouchement, Douleurs lombaires et/ou pelviennes, Troubles digestifs associés, Post-partum, Allaitement | J39: 3 | K39: Interrogatoire, En excluant d’autres causes possibles de douleurs pelviennes pendant la grossesse | L39: Occasionnellement (> ou = à 1 fois par mois) | M39: Oui | N39: Absence de formation spécifique sur le syndrome, Assimilation du syndrome à des lombalgies non spécifiques, Sous-estimation des plaintes des patientes, Absence de recommandations professionnelles claires | O39: Ostéopathie | P39: Ceinture de maintien/Support pelvien | Q39: Traitements médicamenteux (antalgiques/analgésiques) | R39: Repos/Limitation de mouvement | S39: Exercices/Etirements | T39: Conseils posturaux | U39: 5 | V39: Dès les premiers symptômes | W39: 2 | X39: Contenus pédagogiques sur les principes ostéopathiques inscrits au parcours académique, Retours de patientes, Preuves scientifiques, Réduction du coût des séances pour les patientes, Reconnaissance institutionnelle, Intégration de l’ostéopathie dans les structures de santé | Y39: Insuffisance de preuves scientifiques, Insuffisance de collaboration interprofessionnelle avec des ostéopathes, Coût pour les patientes, Absence de reconnaissance institutionnelle | Z39: Spécialisation de l’ostéopathe en périnatalité, Motivation des patientes pour une prise en charge manuelle complémentaire, Moment de la douleur, Disponibilité et/ou accessibilité d’ostéopathes dans votre réseau, Collaboration interprofessionnelle préexistante, Convictions personnelles concernant cette approche thérapeutique, Expérience personnelle antérieure positive ou négative avec l’ostéopathie | AA39: Non | AB39: Oui | AC39: Oui | AD39: Preuves de résultats positifs des traitements ostéopathiques, Formations sémiologiques supplémentaires des ostéopathes, Recommandations par d’autres professionnels de santé, Mise en place de protocoles règlementés, Encadrement institutionnel et recommandations officielles | AE39: 0 | AF39: 0 | AG39: 0 | AH39: 0 | AI39: 0 | AJ39: 0
A40: Sage-femme diplômé(e) | B40: Plus de 10 ans | C40: Libéral | D40: 3 | E40: 5 | F40: 3 | G40: Oui | H40: Oui, régulièrement (> ou = à 1 fois par semaine) | I40: Suivi prénatal de grossesse, Douleurs lombaires et/ou pelviennes, Post-partum | J40: 3 | K40: Interrogatoire | L40: Occasionnellement (> ou = à 1 fois par mois) | M40: Oui | N40: Absence de formation spécifique sur le syndrome, Assimilation du syndrome à des lombalgies non spécifiques, Sous-estimation des plaintes des patientes, Difficultés d’accès aux thérapies non médicamenteuses, Absence de recommandations professionnelles claires | O40: Ostéopathie | P40: Ceinture de maintien/Support pelvien | Q40: Exercices/Etirements | R40: Conseils posturaux | S40: Repos/Limitation de mouvement | T40: Traitements médicamenteux (antalgiques/analgésiques) | U40: 4 | V40: Dès les premiers symptômes | W40: 1 | X40: Preuves scientifiques, Réduction du coût des séances pour les patientes, Reconnaissance institutionnelle | Y40: Peu de contenus pédagogiques sur les principes ostéopathiques inscrits au parcours académique, Absence de connaissances sur la pratique ostéopathique, Insuffisance de collaboration interprofessionnelle avec des ostéopathes, Coût pour les patientes, Absence de reconnaissance institutionnelle | Z40: Spécialisation de l’ostéopathe en périnatalité, Disponibilité et/ou accessibilité d’ostéopathes dans votre réseau, Convictions personnelles concernant cette approche thérapeutique | AA40: Sans avis | AB40: Oui | AC40: Oui | AD40: Preuves de résultats positifs des traitements ostéopathiques, Recommandations par d’autres professionnels de santé, Mise en place de protocoles règlementés | AE40: 0 | AF40: 0 | AG40: 0 | AH40: 0 | AI40: 0 | AJ40: 0
A41: Sage-femme diplômé(e) | B41: Plus de 10 ans | C41: Hospitalier | D41: 4 | E41: 5 | F41: 4 | G41: Non | H41: Oui, rarement (< à 1 fois par mois) | I41: Suivi prénatal de grossesse, Douleurs lombaires et/ou pelviennes, Post-partum, Allaitement | J41: 4 | K41: Interrogatoire, Examen clinique, En excluant d’autres causes possibles de douleurs pelviennes pendant la grossesse | L41: Occasionnellement (> ou = à 1 fois par mois) | M41: Sans avis | N41: Assimilation du syndrome à des lombalgies non spécifiques, Sous-estimation des plaintes des patientes, Absence de recommandations professionnelles claires | O41: Conseils posturaux | P41: Traitements médicamenteux (antalgiques/analgésiques) | Q41: Ostéopathie | R41: Exercices/Etirements | S41: Ceinture de maintien/Support pelvien | T41: Repos/Limitation de mouvement, Ceinture de maintien/Support pelvien, Exercices/Etirements | U41: 5 | V41: Dès les premiers symptômes | W41: 2 | X41: Contenus pédagogiques sur les principes ostéopathiques inscrits au parcours académique, Retours de patientes, Preuves scientifiques, Réduction du coût des séances pour les patientes, Reconnaissance institutionnelle, Intégration de l’ostéopathie dans les structures de santé | Y41: Peu de contenus pédagogiques sur les principes ostéopathiques inscrits au parcours académique, Absence de connaissances sur la pratique ostéopathique, Insuffisance de collaboration interprofessionnelle avec des ostéopathes, Coût pour les patientes | Z41: Spécialisation de l’ostéopathe en périnatalité, Motivation des patientes pour une prise en charge manuelle complémentaire, Disponibilité et/ou accessibilité d’ostéopathes dans votre réseau, Collaboration interprofessionnelle préexistante | AA41: Non | AB41: Oui | AC41: Oui | AD41: Preuves de résultats positifs des traitements ostéopathiques, Demande des patientes, Recommandations par d’autres professionnels de santé, Mise en place de protocoles règlementés, Encadrement institutionnel et recommandations officielles | AE41: 0 | AF41: 0 | AG41: 0 | AH41: 0 | AI41: 0 | AJ41: 0
A42: Étudiant(e) sage-femme en 5e année | B42: 0 | C42: 0 | D42: 3 | E42: 3 | F42: 4 | G42: Non | H42: Non | I42: 0 | J42: 4 | K42: Interrogatoire | L42: Rarement (> ou = à 1 fois tous les 3 mois) | M42: Oui | N42: Absence de formation spécifique sur le syndrome, Assimilation du syndrome à des lombalgies non spécifiques, Sous-estimation des plaintes des patientes, Absence de recommandations professionnelles claires | O42: Exercices/Etirements | P42: Traitements médicamenteux (antalgiques/analgésiques) | Q42: Conseils posturaux | R42: Ostéopathie | S42: Ceinture de maintien/Support pelvien | T42: Repos/Limitation de mouvement | U42: 4 | V42: En cas d’absence de réussite d’autres prises en charge | W42: 1 | X42: Contenus pédagogiques sur les principes ostéopathiques inscrits au parcours académique, Retours de patientes, Preuves scientifiques, Médiatisation/Réseaux sociaux, Reconnaissance institutionnelle, Intégration de l’ostéopathie dans les structures de santé | Y42: Absence de connaissances sur la pratique ostéopathique, Insuffisance de preuves scientifiques, Insuffisance de collaboration interprofessionnelle avec des ostéopathes, Coût pour les patientes | Z42: Caractère chronique ou aigu des douleurs, Réponse ou non aux autres traitements, Spécialisation de l’ostéopathe en périnatalité, Motivation des patientes pour une prise en charge manuelle complémentaire, Disponibilité et/ou accessibilité d’ostéopathes dans votre réseau, Expérience personnelle antérieure positive ou négative avec l’ostéopathie | AA42: Oui | AB42: Oui | AC42: Oui | AD42: Preuves de résultats positifs des traitements ostéopathiques, Demande des patientes, Formations sémiologiques supplémentaires des ostéopathes, Recommandations par d’autres professionnels de santé, Mise en place de protocoles règlementés, Encadrement institutionnel et recommandations officielles | AE42: 0 | AF42: 0 | AG42: 0 | AH42: 0 | AI42: 0 | AJ42: 0
A43: Étudiant(e) sage-femme en 5e année | B43: 0 | C43: 0 | D43: 1 | E43: 2 | F43: 1 | G43: Non | H43: Oui, rarement (< à 1 fois par mois) | I43: Douleurs lombaires et/ou pelviennes, Sphère émotionnelle | J43: 2 | K43: Interrogatoire, Examen clinique | L43: Occasionnellement (> ou = à 1 fois par mois) | M43: Oui | N43: Absence de formation spécifique sur le syndrome, Assimilation du syndrome à des lombalgies non spécifiques, Sous-estimation des plaintes des patientes, Difficultés d’accès aux thérapies non médicamenteuses, Absence de recommandations professionnelles claires | O43: Repos/Limitation de mouvement | P43: Ceinture de maintien/Support pelvien | Q43: Exercices/Etirements | R43: Ostéopathie | S43: Traitements médicamenteux (antalgiques/analgésiques) | T43: Conseils posturaux | U43: 5 | V43: Dès les premiers symptômes | W43: 1 | X43: Contenus pédagogiques sur les principes ostéopathiques inscrits au parcours académique, Médiatisation/Réseaux sociaux, Réduction du coût des séances pour les patientes, Reconnaissance institutionnelle, Intégration de l’ostéopathie dans les structures de santé | Y43: Peu de contenus pédagogiques sur les principes ostéopathiques inscrits au parcours académique, Absence de connaissances sur la pratique ostéopathique, Insuffisance de collaboration interprofessionnelle avec des ostéopathes, Coût pour les patientes, Absence de reconnaissance institutionnelle | Z43: Caractère chronique ou aigu des douleurs, Spécialisation de l’ostéopathe en périnatalité, Moment de la douleur, Disponibilité et/ou accessibilité d’ostéopathes dans votre réseau, Collaboration interprofessionnelle préexistante | AA43: Oui | AB43: Oui | AC43: Oui | AD43: Demande des patientes, Formations sémiologiques supplémentaires des ostéopathes, Recommandations par d’autres professionnels de santé, Mise en place de protocoles règlementés, Encadrement institutionnel et recommandations officielles | AE43: 0 | AF43: 0 | AG43: 0 | AH43: 0 | AI43: 0 | AJ43: 0
A44: Étudiant(e) sage-femme en 5e année | B44: 0 | C44: 0 | D44: 2 | E44: 2 | F44: 4 | G44: Sans avis | H44: Non | I44: 0 | J44: 5 | K44: Interrogatoire, Examen clinique, En excluant d’autres causes possibles de douleurs pelviennes pendant la grossesse | L44: Fréquemment (> ou = à 1 fois par semaine) | M44: Oui | N44: Absence de recommandations professionnelles claires | O44: Conseils posturaux | P44: Ceinture de maintien/Support pelvien | Q44: Exercices/Etirements | R44: Traitements médicamenteux (antalgiques/analgésiques) | S44: Repos/Limitation de mouvement | T44: Ostéopathie | U44: 2 | V44: En cas d’absence de réussite d’autres prises en charge | W44: 4 | X44: Preuves scientifiques | Y44: Insuffisance de preuves scientifiques, Coût pour les patientes, Absence de reconnaissance institutionnelle | Z44: Convictions personnelles concernant cette approche thérapeutique, Expérience personnelle antérieure positive ou négative avec l’ostéopathie | AA44: Oui | AB44: Non | AC44: Non | AD44: Preuves de résultats positifs des traitements ostéopathiques, Demande des patientes | AE44: 0 | AF44: 0 | AG44: 0 | AH44: 0 | AI44: 0 | AJ44: 0
A45: Sage-femme diplômé(e) | B45: Plus de 10 ans | C45: Hospitalier | D45: 2 | E45: 4 | F45: 3 | G45: Non | H45: Non | I45: 0 | J45: 2 | K45: Interrogatoire, Examen clinique | L45: Occasionnellement (> ou = à 1 fois par mois) | M45: Oui | N45: Absence de formation spécifique sur le syndrome, Absence de recommandations professionnelles claires | O45: Ceinture de maintien/Support pelvien | P45: Conseils posturaux | Q45: Ostéopathie | R45: Exercices/Etirements | S45: Repos/Limitation de mouvement | T45: Traitements médicamenteux (antalgiques/analgésiques) | U45: 4 | V45: Dès les premiers symptômes | W45: 1 | X45: Contenus pédagogiques sur les principes ostéopathiques inscrits au parcours académique, Preuves scientifiques, Réduction du coût des séances pour les patientes, Reconnaissance institutionnelle, Intégration de l’ostéopathie dans les structures de santé | Y45: Absence de connaissances sur la pratique ostéopathique, Absence de reconnaissance institutionnelle | Z45: Disponibilité et/ou accessibilité d’ostéopathes dans votre réseau, Collaboration interprofessionnelle préexistante, Expérience personnelle antérieure positive ou négative avec l’ostéopathie | AA45: Oui | AB45: Oui | AC45: Oui | AD45: Preuves de résultats positifs des traitements ostéopathiques, Mise en place de protocoles règlementés, Encadrement institutionnel et recommandations officielles | AE45: 0 | AF45: 0 | AG45: 0 | AH45: 0 | AI45: 0 | AJ45: 0
A46: Sage-femme diplômé(e) | B46: Plus de 10 ans | C46: Hospitalier | D46: 3 | E46: 4 | F46: 4 | G46: Oui | H46: Oui, régulièrement (> ou = à 1 fois par semaine) | I46: Suivi prénatal de grossesse, Préparation à l’accouchement, Nouveau-né | J46: 5 | K46: Interrogatoire, Examen clinique | L46: Occasionnellement (> ou = à 1 fois par mois) | M46: Non | N46: Absence de recommandations professionnelles claires | O46: Traitements médicamenteux (antalgiques/analgésiques) | P46: Ostéopathie | Q46: Conseils posturaux | R46: Exercices/Etirements | S46: Ceinture de maintien/Support pelvien | T46: Repos/Limitation de mouvement | U46: 5 | V46: En fin de grossesse | W46: 3 | X46: Réduction du coût des séances pour les patientes, Reconnaissance institutionnelle, Intégration de l’ostéopathie dans les structures de santé | Y46: Coût pour les patientes | Z46: Motivation des patientes pour une prise en charge manuelle complémentaire, Collaboration interprofessionnelle préexistante, Convictions personnelles concernant cette approche thérapeutique | AA46: Non | AB46: Oui | AC46: Oui | AD46: Encadrement institutionnel et recommandations officielles | AE46: 0 | AF46: 0 | AG46: 0 | AH46: 0 | AI46: 0 | AJ46: 0
A47: Sage-femme diplômé(e) | B47: Plus de 10 ans | C47: Mixte | D47: 4 | E47: 4 | F47: 4 | G47: Oui | H47: Oui, occasionnellement (> ou = à 1 fois par mois) | I47: Douleurs lombaires et/ou pelviennes, Post-partum | J47: 4 | K47: Interrogatoire, En excluant d’autres causes possibles de douleurs pelviennes pendant la grossesse | L47: Fréquemment (> ou = à 1 fois par semaine) | M47: Non | N47: 0 | O47: Ostéopathie | P47: Exercices/Etirements | Q47: Conseils posturaux | R47: Ceinture de maintien/Support pelvien | S47: Traitements médicamenteux (antalgiques/analgésiques) | T47: Repos/Limitation de mouvement | U47: 5 | V47: Dès les premiers symptômes | W47: 3 | X47: Contenus pédagogiques sur les principes ostéopathiques inscrits au parcours académique, Retours de patientes | Y47: Peu de contenus pédagogiques sur les principes ostéopathiques inscrits au parcours académique | Z47: Caractère chronique ou aigu des douleurs | AA47: Sans avis | AB47: Oui | AC47: Oui | AD47: Mise en place de protocoles règlementés | AE47: 0 | AF47: 0 | AG47: 0 | AH47: 0 | AI47: 0 | AJ47: 0
A48: Sage-femme diplômé(e) | B48: Plus de 10 ans | C48: Hospitalier | D48: 4 | E48: 4 | F48: 4 | G48: Non | H48: Non | I48: 0 | J48: 3 | K48: Interrogatoire, Examen clinique, En excluant d’autres causes possibles de douleurs pelviennes pendant la grossesse | L48: Occasionnellement (> ou = à 1 fois par mois) | M48: Sans avis | N48: Assimilation du syndrome à des lombalgies non spécifiques, Sous-estimation des plaintes des patientes, Absence de recommandations professionnelles claires | O48: Conseils posturaux | P48: Exercices/Etirements | Q48: Ostéopathie | R48: Ceinture de maintien/Support pelvien | S48: Traitements médicamenteux (antalgiques/analgésiques) | T48: Repos/Limitation de mouvement | U48: 4 | V48: Dès les premiers symptômes | W48: 2 | X48: Preuves scientifiques, Réduction du coût des séances pour les patientes | Y48: Insuffisance de preuves scientifiques, Coût pour les patientes | Z48: Caractère chronique ou aigu des douleurs, Spécialisation de l’ostéopathe en périnatalité, Motivation des patientes pour une prise en charge manuelle complémentaire, Convictions personnelles concernant cette approche thérapeutique, Expérience personnelle antérieure positive ou négative avec l’ostéopathie | AA48: Oui | AB48: Oui | AC48: Non | AD48: Preuves de résultats positifs des traitements ostéopathiques, Absence ou inefficacité d’autres solutions thérapeutiques, Encadrement institutionnel et recommandations officielles | AE48: 0 | AF48: 0 | AG48: 0 | AH48: 0 | AI48: 0 | AJ48: 0
A49: Sage-femme diplômé(e) | B49: Plus de 10 ans | C49: Hospitalier | D49: 3 | E49: 5 | F49: 4 | G49: Non | H49: Oui, régulièrement (> ou = à 1 fois par semaine) | I49: Suivi prénatal de grossesse, Douleurs lombaires et/ou pelviennes, Post-partum | J49: 3 | K49: Interrogatoire, Examen clinique, En excluant d’autres causes possibles de douleurs pelviennes pendant la grossesse | L49: Fréquemment (> ou = à 1 fois par semaine) | M49: Oui | N49: Assimilation du syndrome à des lombalgies non spécifiques, Sous-estimation des plaintes des patientes, Absence de recommandations professionnelles claires | O49: Ceinture de maintien/Support pelvien | P49: Ostéopathie | Q49: Conseils posturaux | R49: Exercices/Etirements | S49: Traitements médicamenteux (antalgiques/analgésiques) | T49: Repos/Limitation de mouvement | U49: 3 | V49: En fin de grossesse | W49: 2 | X49: Contenus pédagogiques sur les principes ostéopathiques inscrits au parcours académique, Réduction du coût des séances pour les patientes, Reconnaissance institutionnelle, Intégration de l’ostéopathie dans les structures de santé | Y49: Peu de contenus pédagogiques sur les principes ostéopathiques inscrits au parcours académique, Coût pour les patientes, Absence de reconnaissance institutionnelle | Z49: Réponse ou non aux autres traitements, Spécialisation de l’ostéopathe en périnatalité, Expérience personnelle antérieure positive ou négative avec l’ostéopathie | AA49: Oui | AB49: Oui | AC49: Oui | AD49: Demande des patientes, Mise en place de protocoles règlementés, Encadrement institutionnel et recommandations officielles | AE49: 0 | AF49: 0 | AG49: 0 | AH49: 0 | AI49: 0 | AJ49: 0
A50: Sage-femme diplômé(e) | B50: Plus de 10 ans | C50: Libéral | D50: 4 | E50: 3 | F50: 4 | G50: Oui | H50: Oui, occasionnellement (> ou = à 1 fois par mois) | I50: Suivi prénatal de grossesse, Douleurs lombaires et/ou pelviennes, Troubles digestifs associés, Post-partum, Fertilité | J50: 5 | K50: Interrogatoire, Examen clinique, En excluant d’autres causes possibles de douleurs pelviennes pendant la grossesse | L50: Fréquemment (> ou = à 1 fois par semaine) | M50: Oui | N50: Absence de formation spécifique sur le syndrome, Assimilation du syndrome à des lombalgies non spécifiques, Sous-estimation des plaintes des patientes, Difficultés d’accès aux thérapies non médicamenteuses, Absence de recommandations professionnelles claires, Insuffisance d'examen clinique spécifique | O50: Conseils posturaux | P50: Exercices/Etirements | Q50: Ceinture de maintien/Support pelvien | R50: Ostéopathie | S50: Traitements médicamenteux (antalgiques/analgésiques) | T50: Repos/Limitation de mouvement | U50: 4 | V50: 0 | W50: 3 | X50: Contenus pédagogiques sur les principes ostéopathiques inscrits au parcours académique, Preuves scientifiques, Reconnaissance institutionnelle, Intégration de l’ostéopathie dans les structures de santé | Y50: Peu de contenus pédagogiques sur les principes ostéopathiques inscrits au parcours académique, Absence de connaissances sur la pratique ostéopathique, Insuffisance de preuves scientifiques, Absence de reconnaissance institutionnelle | Z50: Caractère chronique ou aigu des douleurs, Réponse ou non aux autres traitements, Spécialisation de l’ostéopathe en périnatalité, Motivation des patientes pour une prise en charge manuelle complémentaire, Collaboration interprofessionnelle préexistante | AA50: Non | AB50: Oui | AC50: Oui | AD50: Preuves de résultats positifs des traitements ostéopathiques, Demande des patientes, Encadrement institutionnel et recommandations officielles | AE50: Travail au sein d'un même lieu ; j'encourage les patientes a 3 4 visites annuelles ou 1 par trimestre dans le cadre de la grossesse pour etre au maximum dans la prevention ! Ce qui respe te les decrets regissant les ostéopathes | AF50: Collaboration interprofessionnelle, Suivi régulier préventif, Recommandation institutionnelle, Favorable à l'intégration de l'ostéopathie | AG50: 0 | AH50: 0 | AI50: 0 | AJ50: 0
A51: Étudiant(e) sage-femme en 5e année | B51: 0 | C51: 0 | D51: 2 | E51: 4 | F51: 2 | G51: Non | H51: Oui, rarement (< à 1 fois par mois) | I51: Douleurs lombaires et/ou pelviennes, Post-partum | J51: 2 | K51: Interrogatoire | L51: Fréquemment (> ou = à 1 fois par semaine) | M51: Sans avis | N51: Absence de formation spécifique sur le syndrome, Assimilation du syndrome à des lombalgies non spécifiques, Absence de recommandations professionnelles claires | O51: Conseils posturaux | P51: Exercices/Etirements | Q51: Repos/Limitation de mouvement | R51: Ceinture de maintien/Support pelvien | S51: Ostéopathie | T51: Traitements médicamenteux (antalgiques/analgésiques) | U51: 4 | V51: Dès les premiers symptômes | W51: 2 | X51: Contenus pédagogiques sur les principes ostéopathiques inscrits au parcours académique, Retours de patientes, Preuves scientifiques, Reconnaissance institutionnelle, Intégration de l’ostéopathie dans les structures de santé | Y51: Peu de contenus pédagogiques sur les principes ostéopathiques inscrits au parcours académique, Absence de connaissances sur la pratique ostéopathique, Insuffisance de collaboration interprofessionnelle avec des ostéopathes, Absence de reconnaissance institutionnelle | Z51: Caractère chronique ou aigu des douleurs | AA51: Oui | AB51: Oui | AC51: Oui | AD51: Preuves de résultats positifs des traitements ostéopathiques, Demande des patientes, Mise en place de protocoles règlementés, Encadrement institutionnel et recommandations officielles | AE51: 0 | AF51: 0 | AG51: 0 | AH51: 0 | AI51: 0 | AJ51: 0
A52: Étudiant(e) sage-femme en 5e année | B52: 0 | C52: 0 | D52: 2 | E52: 3 | F52: 2 | G52: Non | H52: Oui, rarement (< à 1 fois par mois) | I52: Douleurs lombaires et/ou pelviennes | J52: 4 | K52: Interrogatoire, En excluant d’autres causes possibles de douleurs pelviennes pendant la grossesse | L52: Fréquemment (> ou = à 1 fois par semaine) | M52: Non | N52: 0 | O52: Traitements médicamenteux (antalgiques/analgésiques) | P52: Exercices/Etirements | Q52: Repos/Limitation de mouvement | R52: Conseils posturaux | S52: Ostéopathie | T52: Ceinture de maintien/Support pelvien | U52: 3 | V52: En cas d’absence de réussite d’autres prises en charge | W52: 1 | X52: Contenus pédagogiques sur les principes ostéopathiques inscrits au parcours académique, Preuves scientifiques, Reconnaissance institutionnelle | Y52: Peu de contenus pédagogiques sur les principes ostéopathiques inscrits au parcours académique, Absence de connaissances sur la pratique ostéopathique, Insuffisance de preuves scientifiques, Insuffisance de collaboration interprofessionnelle avec des ostéopathes | Z52: Réponse ou non aux autres traitements, Disponibilité et/ou accessibilité d’ostéopathes dans votre réseau, Convictions personnelles concernant cette approche thérapeutique | AA52: Non | AB52: Oui | AC52: Oui | AD52: Preuves de résultats positifs des traitements ostéopathiques, Demande des patientes, Mise en place de protocoles règlementés, Encadrement institutionnel et recommandations officielles | AE52: 0 | AF52: 0 | AG52: 0 | AH52: 0 | AI52: 0 | AJ52: 0
A53: Étudiant(e) sage-femme en 5e année | B53: 0 | C53: 0 | D53: 3 | E53: 4 | F53: 2 | G53: Sans avis | H53: Oui, rarement (< à 1 fois par mois) | I53: Douleurs lombaires et/ou pelviennes, Post-partum | J53: 3 | K53: Interrogatoire, En excluant d’autres causes possibles de douleurs pelviennes pendant la grossesse | L53: Occasionnellement (> ou = à 1 fois par mois) | M53: Oui | N53: Absence de formation spécifique sur le syndrome, Assimilation du syndrome à des lombalgies non spécifiques, Sous-estimation des plaintes des patientes, Absence de recommandations professionnelles claires | O53: Exercices/Etirements | P53: Conseils posturaux | Q53: Ceinture de maintien/Support pelvien | R53: Ostéopathie | S53: Traitements médicamenteux (antalgiques/analgésiques) | T53: Repos/Limitation de mouvement | U53: 4 | V53: En cas d’absence de réussite d’autres prises en charge | W53: 2 | X53: Contenus pédagogiques sur les principes ostéopathiques inscrits au parcours académique, Preuves scientifiques, Réduction du coût des séances pour les patientes, Reconnaissance institutionnelle, Intégration de l’ostéopathie dans les structures de santé | Y53: Peu de contenus pédagogiques sur les principes ostéopathiques inscrits au parcours académique, Insuffisance de preuves scientifiques, Coût pour les patientes, Absence de reconnaissance institutionnelle | Z53: Réponse ou non aux autres traitements, Disponibilité et/ou accessibilité d’ostéopathes dans votre réseau, Convictions personnelles concernant cette approche thérapeutique | AA53: Oui | AB53: Oui | AC53: Oui | AD53: Preuves de résultats positifs des traitements ostéopathiques, Encadrement institutionnel et recommandations officielles | AE53: 0 | AF53: 0 | AG53: 0 | AH53: 0 | AI53: 0 | AJ53: 0
A54: Étudiant(e) sage-femme en 5e année | B54: 0 | C54: 0 | D54: 2 | E54: 3 | F54: 2 | G54: Sans avis | H54: Oui, rarement (< à 1 fois par mois) | I54: Douleurs lombaires et/ou pelviennes | J54: 3 | K54: Interrogatoire, En excluant d’autres causes possibles de douleurs pelviennes pendant la grossesse | L54: Occasionnellement (> ou = à 1 fois par mois) | M54: Oui | N54: Absence de formation spécifique sur le syndrome, Sous-estimation des plaintes des patientes, Absence de recommandations professionnelles claires | O54: Ceinture de maintien/Support pelvien | P54: Ostéopathie | Q54: Repos/Limitation de mouvement | R54: Exercices/Etirements | S54: Conseils posturaux | T54: Traitements médicamenteux (antalgiques/analgésiques) | U54: 5 | V54: Dès les premiers symptômes | W54: 2 | X54: Contenus pédagogiques sur les principes ostéopathiques inscrits au parcours académique, Preuves scientifiques, Reconnaissance institutionnelle, Intégration de l’ostéopathie dans les structures de santé | Y54: Peu de contenus pédagogiques sur les principes ostéopathiques inscrits au parcours académique, Absence de connaissances sur la pratique ostéopathique, Insuffisance de preuves scientifiques, Insuffisance de collaboration interprofessionnelle avec des ostéopathes, Absence de reconnaissance institutionnelle | Z54: Caractère chronique ou aigu des douleurs, Spécialisation de l’ostéopathe en périnatalité, Motivation des patientes pour une prise en charge manuelle complémentaire, Collaboration interprofessionnelle préexistante, Convictions personnelles concernant cette approche thérapeutique | AA54: Sans avis | AB54: Oui | AC54: Oui | AD54: Preuves de résultats positifs des traitements ostéopathiques, Formations sémiologiques supplémentaires des ostéopathes | AE54: 0 | AF54: 0 | AG54: En tant qu'étudiante j'ai surtout vu des collaborations SF/ostéo dans des cabinets pluriprofessionnels. | AH54: Collaboration interprofessionnelle, Favorable à l'intégration de l'ostéopathie | AI54: 0 | AJ54: 0
A55: Étudiant(e) sage-femme en 5e année | B55: 0 | C55: 0 | D55: 2 | E55: 3 | F55: 1 | G55: Non | H55: Non | I55: 0 | J55: 4 | K55: Interrogatoire, En excluant d’autres causes possibles de douleurs pelviennes pendant la grossesse | L55: Fréquemment (> ou = à 1 fois par semaine) | M55: Oui | N55: Absence de formation spécifique sur le syndrome, Assimilation du syndrome à des lombalgies non spécifiques, Absence de recommandations professionnelles claires | O55: Exercices/Etirements | P55: Conseils posturaux | Q55: Ceinture de maintien/Support pelvien | R55: Traitements médicamenteux (antalgiques/analgésiques) | S55: Ostéopathie | T55: Repos/Limitation de mouvement | U55: 3 | V55: Dès les premiers symptômes | W55: 2 | X55: Contenus pédagogiques sur les principes ostéopathiques inscrits au parcours académique, Preuves scientifiques, Réduction du coût des séances pour les patientes, Reconnaissance institutionnelle, Intégration de l’ostéopathie dans les structures de santé | Y55: Peu de contenus pédagogiques sur les principes ostéopathiques inscrits au parcours académique, Absence de connaissances sur la pratique ostéopathique, Insuffisance de preuves scientifiques, Coût pour les patientes, Absence de reconnaissance institutionnelle | Z55: Caractère chronique ou aigu des douleurs, Spécialisation de l’ostéopathe en périnatalité, Motivation des patientes pour une prise en charge manuelle complémentaire | AA55: Oui | AB55: Oui | AC55: Oui | AD55: Preuves de résultats positifs des traitements ostéopathiques, Demande des patientes, Formations sémiologiques supplémentaires des ostéopathes, Absence ou inefficacité d’autres solutions thérapeutiques, Encadrement institutionnel et recommandations officielles | AE55: 0 | AF55: 0 | AG55: 0 | AH55: 0 | AI55: 0 | AJ55: 0
A56: Étudiant(e) sage-femme en 5e année | B56: 0 | C56: 0 | D56: 4 | E56: 3 | F56: 1 | G56: Non | H56: Oui, rarement (< à 1 fois par mois) | I56: Douleurs lombaires et/ou pelviennes, Post-partum | J56: 4 | K56: Interrogatoire, En excluant d’autres causes possibles de douleurs pelviennes pendant la grossesse | L56: Fréquemment (> ou = à 1 fois par semaine) | M56: Sans avis | N56: 0 | O56: Exercices/Etirements | P56: Conseils posturaux | Q56: Ostéopathie | R56: Traitements médicamenteux (antalgiques/analgésiques) | S56: Ceinture de maintien/Support pelvien | T56: Repos/Limitation de mouvement | U56: 4 | V56: En cas d’absence de réussite d’autres prises en charge | W56: 2 | X56: Retours de patientes, Preuves scientifiques, Réduction du coût des séances pour les patientes | Y56: Peu de contenus pédagogiques sur les principes ostéopathiques inscrits au parcours académique, Absence de connaissances sur la pratique ostéopathique, Coût pour les patientes, Absence de reconnaissance institutionnelle | Z56: Caractère chronique ou aigu des douleurs, Motivation des patientes pour une prise en charge manuelle complémentaire, Disponibilité et/ou accessibilité d’ostéopathes dans votre réseau | AA56: Sans avis | AB56: Oui | AC56: Oui | AD56: Preuves de résultats positifs des traitements ostéopathiques, Encadrement institutionnel et recommandations officielles | AE56: 0 | AF56: 0 | AG56: 0 | AH56: 0 | AI56: mon seul frein est l'accessibilité aux soins pour toutes, inegalité des soins en fonction des moyens financiers des patientes du fait du prix des séances, on ne peut pas à ce jour proposer ça à tout le monde | AJ56: Coût pour les patientes
A57: Étudiant(e) sage-femme en 5e année | B57: 0 | C57: 0 | D57: 3 | E57: 4 | F57: 2 | G57: Non | H57: Oui, rarement (< à 1 fois par mois) | I57: Suivi prénatal de grossesse, Douleurs lombaires et/ou pelviennes, Post-partum | J57: 3 | K57: Interrogatoire, En excluant d’autres causes possibles de douleurs pelviennes pendant la grossesse | L57: Fréquemment (> ou = à 1 fois par semaine) | M57: Oui | N57: Absence de formation spécifique sur le syndrome, Assimilation du syndrome à des lombalgies non spécifiques, Sous-estimation des plaintes des patientes, Absence de recommandations professionnelles claires | O57: Conseils posturaux | P57: Exercices/Etirements | Q57: Ceinture de maintien/Support pelvien | R57: Ostéopathie | S57: Traitements médicamenteux (antalgiques/analgésiques) | T57: Repos/Limitation de mouvement | U57: 5 | V57: En cas d’absence de réussite d’autres prises en charge | W57: 2 | X57: Contenus pédagogiques sur les principes ostéopathiques inscrits au parcours académique, Réduction du coût des séances pour les patientes, Intégration de l’ostéopathie dans les structures de santé | Y57: Peu de contenus pédagogiques sur les principes ostéopathiques inscrits au parcours académique, Absence de connaissances sur la pratique ostéopathique, Insuffisance de collaboration interprofessionnelle avec des ostéopathes, Coût pour les patientes | Z57: Caractère chronique ou aigu des douleurs, Réponse ou non aux autres traitements, Disponibilité et/ou accessibilité d’ostéopathes dans votre réseau | AA57: Oui | AB57: Oui | AC57: Oui | AD57: Recommandations par d’autres professionnels de santé, Absence ou inefficacité d’autres solutions thérapeutiques, Encadrement institutionnel et recommandations officielles | AE57: 0 | AF57: 0 | AG57: 0 | AH57: 0 | AI57: 0 | AJ57: 0
A58: Étudiant(e) sage-femme en 5e année | B58: 0 | C58: 0 | D58: 3 | E58: 3 | F58: 3 | G58: Non | H58: Oui, occasionnellement (> ou = à 1 fois par mois) | I58: Suivi prénatal de grossesse, Douleurs lombaires et/ou pelviennes, Post-partum | J58: 4 | K58: Interrogatoire, Examen clinique, En excluant d’autres causes possibles de douleurs pelviennes pendant la grossesse | L58: Fréquemment (> ou = à 1 fois par semaine) | M58: Non | N58: 0 | O58: Ceinture de maintien/Support pelvien | P58: Exercices/Etirements | Q58: Ostéopathie | R58: Conseils posturaux | S58: Repos/Limitation de mouvement | T58: Traitements médicamenteux (antalgiques/analgésiques) | U58: 4 | V58: En cas d’absence de réussite d’autres prises en charge | W58: 3 | X58: Réduction du coût des séances pour les patientes, Intégration de l’ostéopathie dans les structures de santé | Y58: Insuffisance de preuves scientifiques, Coût pour les patientes | Z58: Réponse ou non aux autres traitements, Spécialisation de l’ostéopathe en périnatalité, Motivation des patientes pour une prise en charge manuelle complémentaire, Disponibilité et/ou accessibilité d’ostéopathes dans votre réseau | AA58: Oui | AB58: Oui | AC58: Oui | AD58: Preuves de résultats positifs des traitements ostéopathiques, Mise en place de protocoles règlementés, Encadrement institutionnel et recommandations officielles | AE58: 0 | AF58: 0 | AG58: 0 | AH58: 0 | AI58: 0 | AJ58: 0
A59: Étudiant(e) sage-femme en 5e année | B59: 0 | C59: 0 | D59: 1 | E59: 3 | F59: 1 | G59: Oui | H59: Oui, régulièrement (> ou = à 1 fois par semaine) | I59: Douleurs lombaires et/ou pelviennes | J59: 3 | K59: Interrogatoire, En excluant d’autres causes possibles de douleurs pelviennes pendant la grossesse | L59: Fréquemment (> ou = à 1 fois par semaine) | M59: Oui | N59: Absence de formation spécifique sur le syndrome, Assimilation du syndrome à des lombalgies non spécifiques, Difficultés d’accès aux thérapies non médicamenteuses, Absence de recommandations professionnelles claires | O59: Conseils posturaux | P59: Ceinture de maintien/Support pelvien | Q59: Ostéopathie | R59: Exercices/Etirements | S59: Traitements médicamenteux (antalgiques/analgésiques) | T59: Repos/Limitation de mouvement | U59: 4 | V59: En fin de grossesse | W59: 2 | X59: Contenus pédagogiques sur les principes ostéopathiques inscrits au parcours académique, Retours de patientes, Preuves scientifiques, Reconnaissance institutionnelle, Intégration de l’ostéopathie dans les structures de santé | Y59: Peu de contenus pédagogiques sur les principes ostéopathiques inscrits au parcours académique, Absence de connaissances sur la pratique ostéopathique, Insuffisance de preuves scientifiques, Insuffisance de collaboration interprofessionnelle avec des ostéopathes, Coût pour les patientes, Absence de reconnaissance institutionnelle | Z59: Caractère chronique ou aigu des douleurs, Réponse ou non aux autres traitements, Spécialisation de l’ostéopathe en périnatalité, Motivation des patientes pour une prise en charge manuelle complémentaire, Disponibilité et/ou accessibilité d’ostéopathes dans votre réseau, Collaboration interprofessionnelle préexistante, Convictions personnelles concernant cette approche thérapeutique | AA59: Oui | AB59: Oui | AC59: Oui | AD59: Preuves de résultats positifs des traitements ostéopathiques, Demande des patientes, Formations sémiologiques supplémentaires des ostéopathes, Recommandations par d’autres professionnels de santé, Mise en place de protocoles règlementés, Encadrement institutionnel et recommandations officielles | AE59: 0 | AF59: 0 | AG59: 0 | AH59: 0 | AI59: 0 | AJ59: 0
A60: Étudiant(e) sage-femme en 5e année | B60: 0 | C60: 0 | D60: 2 | E60: 4 | F60: 3 | G60: Sans avis | H60: Non | I60: 0 | J60: 3 | K60: Interrogatoire, Examen clinique, En excluant d’autres causes possibles de douleurs pelviennes pendant la grossesse | L60: Jamais | M60: Sans avis | N60: 0 | O60: Conseils posturaux | P60: Repos/Limitation de mouvement | Q60: Exercices/Etirements | R60: Ceinture de maintien/Support pelvien | S60: Ostéopathie | T60: Traitements médicamenteux (antalgiques/analgésiques) | U60: 4 | V60: Dès les premiers symptômes | W60: 3 | X60: Réduction du coût des séances pour les patientes, Reconnaissance institutionnelle, Intégration de l’ostéopathie dans les structures de santé | Y60: Peu de contenus pédagogiques sur les principes ostéopathiques inscrits au parcours académique, Absence de connaissances sur la pratique ostéopathique, Insuffisance de collaboration interprofessionnelle avec des ostéopathes, Coût pour les patientes | Z60: Réponse ou non aux autres traitements, Spécialisation de l’ostéopathe en périnatalité, Motivation des patientes pour une prise en charge manuelle complémentaire, Disponibilité et/ou accessibilité d’ostéopathes dans votre réseau, Collaboration interprofessionnelle préexistante | AA60: Sans avis | AB60: Oui | AC60: Oui | AD60: Preuves de résultats positifs des traitements ostéopathiques, Demande des patientes, Mise en place de protocoles règlementés, Encadrement institutionnel et recommandations officielles | AE60: 0 | AF60: 0 | AG60: 0 | AH60: 0 | AI60: 0 | AJ60: 0
A61: Sage-femme diplômé(e) | B61: Plus de 10 ans | C61: Hospitalier | D61: 3 | E61: 5 | F61: 5 | G61: Oui | H61: Oui, régulièrement (> ou = à 1 fois par semaine) | I61: Suivi prénatal de grossesse, Fertilité | J61: 4 | K61: Interrogatoire, Examen clinique | L61: Fréquemment (> ou = à 1 fois par semaine) | M61: Non | N61: 0 | O61: Ostéopathie | P61: Ceinture de maintien/Support pelvien | Q61: Exercices/Etirements | R61: Conseils posturaux | S61: Ceinture de maintien/Support pelvien | T61: Traitements médicamenteux (antalgiques/analgésiques) | U61: 5 | V61: Dès les premiers symptômes | W61: 2 | X61: Réduction du coût des séances pour les patientes, Reconnaissance institutionnelle, Intégration de l’ostéopathie dans les structures de santé | Y61: Coût pour les patientes | Z61: Spécialisation de l’ostéopathe en périnatalité, Motivation des patientes pour une prise en charge manuelle complémentaire | AA61: Non | AB61: Oui | AC61: Oui | AD61: Absence ou inefficacité d’autres solutions thérapeutiques | AE61: Tres positif mais certains medecins deconseillent aux patientes et du coup elles les écoutent | AF61: Efficacité perçue, Impact des avis médicaux, Recommandation institutionnelle | AG61: Demande de notre maternité de collaborer avec les osteopathe mais l'administration refuse | AH61: Limites institutionnelles à la mise en place de collaborations interprofessionnelles, Favorable à l'intégration de l'ostéopathie | AI61: 0 | AJ61: 0
A62: Étudiant(e) sage-femme en 5e année | B62: 0 | C62: 0 | D62: 3 | E62: 4 | F62: 2 | G62: Non | H62: Oui, occasionnellement (> ou = à 1 fois par mois) | I62: Suivi prénatal de grossesse, Douleurs lombaires et/ou pelviennes, Post-partum | J62: 4 | K62: Interrogatoire, Examen clinique, En excluant d’autres causes possibles de douleurs pelviennes pendant la grossesse | L62: Fréquemment (> ou = à 1 fois par semaine) | M62: Sans avis | N62: 0 | O62: Conseils posturaux | P62: Ceinture de maintien/Support pelvien | Q62: Ostéopathie | R62: Repos/Limitation de mouvement | S62: Exercices/Etirements | T62: Traitements médicamenteux (antalgiques/analgésiques) | U62: 4 | V62: En fin de grossesse | W62: 2 | X62: Retours de patientes, Réduction du coût des séances pour les patientes | Y62: Peu de contenus pédagogiques sur les principes ostéopathiques inscrits au parcours académique, Insuffisance de preuves scientifiques, Insuffisance de collaboration interprofessionnelle avec des ostéopathes, Coût pour les patientes | Z62: Caractère chronique ou aigu des douleurs, Motivation des patientes pour une prise en charge manuelle complémentaire, Expérience personnelle antérieure positive ou négative avec l’ostéopathie | AA62: Sans avis | AB62: Oui | AC62: Oui | AD62: Preuves de résultats positifs des traitements ostéopathiques, Demande des patientes, Encadrement institutionnel et recommandations officielles | AE62: 0 | AF62: 0 | AG62: 0 | AH62: 0 | AI62: 0 | AJ62: 0
A63: Étudiant(e) sage-femme en 5e année | B63: 0 | C63: 0 | D63: 4 | E63: 3 | F63: 3 | G63: Sans avis | H63: Oui, occasionnellement (> ou = à 1 fois par mois) | I63: Suivi prénatal de grossesse, Douleurs lombaires et/ou pelviennes, Post-partum | J63: 3 | K63: Interrogatoire, Examen clinique, Recours aux examens complémentaires, En excluant d’autres causes possibles de douleurs pelviennes pendant la grossesse | L63: Occasionnellement (> ou = à 1 fois par mois) | M63: Oui | N63: Sous-estimation des plaintes des patientes, Difficultés d’accès aux thérapies non médicamenteuses | O63: Ceinture de maintien/Support pelvien | P63: Ostéopathie | Q63: Exercices/Etirements | R63: Repos/Limitation de mouvement | S63: Conseils posturaux | T63: Traitements médicamenteux (antalgiques/analgésiques) | U63: 4 | V63: En cas d’absence de réussite d’autres prises en charge | W63: 3 | X63: Contenus pédagogiques sur les principes ostéopathiques inscrits au parcours académique, Retours de patientes, Preuves scientifiques, Réduction du coût des séances pour les patientes, Reconnaissance institutionnelle, Intégration de l’ostéopathie dans les structures de santé | Y63: Insuffisance de collaboration interprofessionnelle avec des ostéopathes, Coût pour les patientes, Absence de reconnaissance institutionnelle | Z63: Caractère chronique ou aigu des douleurs, Spécialisation de l’ostéopathe en périnatalité, Motivation des patientes pour une prise en charge manuelle complémentaire, Moment de la douleur, Disponibilité et/ou accessibilité d’ostéopathes dans votre réseau, Collaboration interprofessionnelle préexistante | AA63: Oui | AB63: Oui | AC63: Oui | AD63: Preuves de résultats positifs des traitements ostéopathiques, Demande des patientes, Formations sémiologiques supplémentaires des ostéopathes, Mise en place de protocoles règlementés, Encadrement institutionnel et recommandations officielles | AE63: 0 | AF63: 0 | AG63: 0 | AH63: 0 | AI63: 0 | AJ63: 0
A64: Étudiant(e) sage-femme en 5e année | B64: 0 | C64: 0 | D64: 2 | E64: 3 | F64: 1 | G64: Non | H64: Non | I64: 0 | J64: 2 | K64: Interrogatoire, Examen clinique, En excluant d’autres causes possibles de douleurs pelviennes pendant la grossesse | L64: Fréquemment (> ou = à 1 fois par semaine) | M64: Non | N64: 0 | O64: Traitements médicamenteux (antalgiques/analgésiques) | P64: Conseils posturaux | Q64: Exercices/Etirements | R64: Repos/Limitation de mouvement | S64: Ceinture de maintien/Support pelvien | T64: Conseils posturaux | U64: 3 | V64: En cas d’absence de réussite d’autres prises en charge | W64: 2 | X64: Contenus pédagogiques sur les principes ostéopathiques inscrits au parcours académique, Retours de patientes, Preuves scientifiques, Réduction du coût des séances pour les patientes, Reconnaissance institutionnelle, Intégration de l’ostéopathie dans les structures de santé | Y64: Peu de contenus pédagogiques sur les principes ostéopathiques inscrits au parcours académique, Absence de connaissances sur la pratique ostéopathique, Insuffisance de preuves scientifiques, Insuffisance de collaboration interprofessionnelle avec des ostéopathes, Absence de reconnaissance institutionnelle | Z64: Réponse ou non aux autres traitements, Spécialisation de l’ostéopathe en périnatalité, Motivation des patientes pour une prise en charge manuelle complémentaire, Disponibilité et/ou accessibilité d’ostéopathes dans votre réseau, Collaboration interprofessionnelle préexistante, Expérience personnelle antérieure positive ou négative avec l’ostéopathie | AA64: Non | AB64: Oui | AC64: Oui | AD64: Preuves de résultats positifs des traitements ostéopathiques, Formations sémiologiques supplémentaires des ostéopathes, Recommandations par d’autres professionnels de santé, Mise en place de protocoles règlementés, Encadrement institutionnel et recommandations officielles | AE64: 0 | AF64: 0 | AG64: 0 | AH64: 0 | AI64: 0 | AJ64: 0
A65: Étudiant(e) sage-femme en 5e année | B65: 0 | C65: 0 | D65: 2 | E65: 4 | F65: 2 | G65: Non | H65: Oui, occasionnellement (> ou = à 1 fois par mois) | I65: Douleurs lombaires et/ou pelviennes | J65: 2 | K65: Interrogatoire, En excluant d’autres causes possibles de douleurs pelviennes pendant la grossesse | L65: Fréquemment (> ou = à 1 fois par semaine) | M65: Oui | N65: Absence de formation spécifique sur le syndrome, Assimilation du syndrome à des lombalgies non spécifiques, Absence de recommandations professionnelles claires | O65: Ostéopathie | P65: Ceinture de maintien/Support pelvien | Q65: Conseils posturaux | R65: Exercices/Etirements | S65: Traitements médicamenteux (antalgiques/analgésiques) | T65: Repos/Limitation de mouvement | U65: 3 | V65: Dès les premiers symptômes | W65: 1 | X65: Contenus pédagogiques sur les principes ostéopathiques inscrits au parcours académique, Retours de patientes, Preuves scientifiques, Réduction du coût des séances pour les patientes | Y65: Peu de contenus pédagogiques sur les principes ostéopathiques inscrits au parcours académique, Insuffisance de collaboration interprofessionnelle avec des ostéopathes, Coût pour les patientes | Z65: Spécialisation de l’ostéopathe en périnatalité | AA65: Oui | AB65: Oui | AC65: Oui | AD65: Preuves de résultats positifs des traitements ostéopathiques, Formations sémiologiques supplémentaires des ostéopathes, Mise en place de protocoles règlementés, Encadrement institutionnel et recommandations officielles | AE65: 0 | AF65: 0 | AG65: 0 | AH65: 0 | AI65: 0 | AJ65: 0
A66: Étudiant(e) sage-femme en 5e année | B66: 0 | C66: 0 | D66: 2 | E66: 4 | F66: 2 | G66: Non | H66: Oui, occasionnellement (> ou = à 1 fois par mois) | I66: Douleurs lombaires et/ou pelviennes, Post-partum | J66: 3 | K66: Interrogatoire, En excluant d’autres causes possibles de douleurs pelviennes pendant la grossesse | L66: Fréquemment (> ou = à 1 fois par semaine) | M66: Non | N66: 0 | O66: Repos/Limitation de mouvement | P66: Exercices/Etirements | Q66: Ceinture de maintien/Support pelvien | R66: Conseils posturaux | S66: Traitements médicamenteux (antalgiques/analgésiques) | T66: Ostéopathie | U66: 4 | V66: En cas d’absence de réussite d’autres prises en charge | W66: 1 | X66: Contenus pédagogiques sur les principes ostéopathiques inscrits au parcours académique, Médiatisation/Réseaux sociaux, Réduction du coût des séances pour les patientes | Y66: Peu de contenus pédagogiques sur les principes ostéopathiques inscrits au parcours académique, Coût pour les patientes, Absence de reconnaissance institutionnelle | Z66: Caractère chronique ou aigu des douleurs, Réponse ou non aux autres traitements, Spécialisation de l’ostéopathe en périnatalité, Motivation des patientes pour une prise en charge manuelle complémentaire, Disponibilité et/ou accessibilité d’ostéopathes dans votre réseau, Collaboration interprofessionnelle préexistante, Convictions personnelles concernant cette approche thérapeutique, Expérience personnelle antérieure positive ou négative avec l’ostéopathie | AA66: Oui | AB66: Oui | AC66: Oui | AD66: Preuves de résultats positifs des traitements ostéopathiques, Demande des patientes, Formations sémiologiques supplémentaires des ostéopathes, Recommandations par d’autres professionnels de santé, Mise en place de protocoles règlementés, Encadrement institutionnel et recommandations officielles | AE66: 0 | AF66: 0 | AG66: 0 | AH66: 0 | AI66: 0 | AJ66: 0
A67: Sage-femme diplômé(e) | B67: Plus de 10 ans | C67: Hospitalier | D67: 1 | E67: 2 | F67: 1 | G67: Non | H67: Non | I67: 0 | J67: 3 | K67: Interrogatoire, Examen clinique, En excluant d’autres causes possibles de douleurs pelviennes pendant la grossesse | L67: Fréquemment (> ou = à 1 fois par semaine) | M67: Sans avis | N67: 0 | O67: Conseils posturaux | P67: Ceinture de maintien/Support pelvien | Q67: Ostéopathie, Traitements médicamenteux (antalgiques/analgésiques) | R67: Exercices/Etirements | S67: Traitements médicamenteux (antalgiques/analgésiques) | T67: Repos/Limitation de mouvement | U67: 2 | V67: Dès les premiers symptômes | W67: 1 | X67: Contenus pédagogiques sur les principes ostéopathiques inscrits au parcours académique, Preuves scientifiques, Intégration de l’ostéopathie dans les structures de santé | Y67: Insuffisance de preuves scientifiques, Absence de reconnaissance institutionnelle | Z67: Caractère chronique ou aigu des douleurs, Réponse ou non aux autres traitements, Moment de la douleur | AA67: Non | AB67: Oui | AC67: Oui | AD67: Preuves de résultats positifs des traitements ostéopathiques, Mise en place de protocoles règlementés, Encadrement institutionnel et recommandations officielles | AE67: 0 | AF67: 0 | AG67: 0 | AH67: 0 | AI67: 0 | AJ67: 0
A68: Étudiant(e) sage-femme en 5e année | B68: 0 | C68: 0 | D68: 3 | E68: 4 | F68: 3 | G68: Sans avis | H68: Oui, rarement (< à 1 fois par mois) | I68: Suivi prénatal de grossesse, Préparation à l’accouchement, Douleurs lombaires et/ou pelviennes, Troubles digestifs associés, Post-partum | J68: 3 | K68: Interrogatoire, Examen clinique, En excluant d’autres causes possibles de douleurs pelviennes pendant la grossesse | L68: Fréquemment (> ou = à 1 fois par semaine) | M68: Oui | N68: Absence de formation spécifique sur le syndrome, Assimilation du syndrome à des lombalgies non spécifiques, Sous-estimation des plaintes des patientes, Absence de recommandations professionnelles claires | O68: Exercices/Etirements | P68: Ostéopathie | Q68: Ceinture de maintien/Support pelvien | R68: Conseils posturaux | S68: Traitements médicamenteux (antalgiques/analgésiques) | T68: Repos/Limitation de mouvement | U68: 4 | V68: Dès les premiers symptômes | W68: 2 | X68: Contenus pédagogiques sur les principes ostéopathiques inscrits au parcours académique, Retours de patientes, Preuves scientifiques, Médiatisation/Réseaux sociaux, Réduction du coût des séances pour les patientes, Reconnaissance institutionnelle, Intégration de l’ostéopathie dans les structures de santé | Y68: Peu de contenus pédagogiques sur les principes ostéopathiques inscrits au parcours académique, Absence de connaissances sur la pratique ostéopathique, Insuffisance de preuves scientifiques, Insuffisance de collaboration interprofessionnelle avec des ostéopathes, Coût pour les patientes, Absence de reconnaissance institutionnelle | Z68: Caractère chronique ou aigu des douleurs, Réponse ou non aux autres traitements, Spécialisation de l’ostéopathe en périnatalité, Motivation des patientes pour une prise en charge manuelle complémentaire, Disponibilité et/ou accessibilité d’ostéopathes dans votre réseau, Collaboration interprofessionnelle préexistante, Convictions personnelles concernant cette approche thérapeutique | AA68: Oui | AB68: Oui | AC68: Oui | AD68: Preuves de résultats positifs des traitements ostéopathiques, Demande des patientes, Formations sémiologiques supplémentaires des ostéopathes, Recommandations par d’autres professionnels de santé, Mise en place de protocoles règlementés, Encadrement institutionnel et recommandations officielles | AE68: 0 | AF68: 0 | AG68: 0 | AH68: 0 | AI68: 0 | AJ68: 0
A69: Étudiant(e) sage-femme en 5e année | B69: 0 | C69: 0 | D69: 2 | E69: 4 | F69: 2 | G69: Non | H69: Non | I69: 0 | J69: 3 | K69: Interrogatoire, Examen clinique, En excluant d’autres causes possibles de douleurs pelviennes pendant la grossesse | L69: Fréquemment (> ou = à 1 fois par semaine) | M69: Sans avis | N69: Absence de formation spécifique sur le syndrome, Sous-estimation des plaintes des patientes, Absence de recommandations professionnelles claires | O69: Conseils posturaux | P69: Exercices/Etirements | Q69: Ostéopathie | R69: Ceinture de maintien/Support pelvien | S69: Repos/Limitation de mouvement | T69: Traitements médicamenteux (antalgiques/analgésiques) | U69: 5 | V69: Dès les premiers symptômes | W69: 2 | X69: Contenus pédagogiques sur les principes ostéopathiques inscrits au parcours académique, Preuves scientifiques, Reconnaissance institutionnelle, Intégration de l’ostéopathie dans les structures de santé | Y69: Peu de contenus pédagogiques sur les principes ostéopathiques inscrits au parcours académique, Absence de connaissances sur la pratique ostéopathique, Insuffisance de preuves scientifiques, Insuffisance de collaboration interprofessionnelle avec des ostéopathes, Absence de reconnaissance institutionnelle | Z69: Motivation des patientes pour une prise en charge manuelle complémentaire | AA69: Non | AB69: Oui | AC69: Oui | AD69: Preuves de résultats positifs des traitements ostéopathiques, Mise en place de protocoles règlementés, Encadrement institutionnel et recommandations officielles | AE69: 0 | AF69: 0 | AG69: 0 | AH69: 0 | AI69: 0 | AJ69: 0
A70: Étudiant(e) sage-femme en 5e année | B70: 0 | C70: 0 | D70: 3 | E70: 4 | F70: 4 | G70: Non | H70: Oui, occasionnellement (> ou = à 1 fois par mois) | I70: Douleurs lombaires et/ou pelviennes, Post-partum | J70: 2 | K70: Interrogatoire, Examen clinique, En excluant d’autres causes possibles de douleurs pelviennes pendant la grossesse | L70: Fréquemment (> ou = à 1 fois par semaine) | M70: Oui | N70: Absence de formation spécifique sur le syndrome, Difficultés d’accès aux thérapies non médicamenteuses, Absence de recommandations professionnelles claires | O70: Conseils posturaux | P70: Exercices/Etirements | Q70: Ostéopathie | R70: Ceinture de maintien/Support pelvien | S70: Ostéopathie | T70: Repos/Limitation de mouvement | U70: 5 | V70: Dès les premiers symptômes | W70: 1 | X70: Contenus pédagogiques sur les principes ostéopathiques inscrits au parcours académique, Retours de patientes, Preuves scientifiques, Médiatisation/Réseaux sociaux, Réduction du coût des séances pour les patientes, Reconnaissance institutionnelle, Intégration de l’ostéopathie dans les structures de santé | Y70: Peu de contenus pédagogiques sur les principes ostéopathiques inscrits au parcours académique, Absence de connaissances sur la pratique ostéopathique, Insuffisance de collaboration interprofessionnelle avec des ostéopathes, Coût pour les patientes | Z70: Caractère chronique ou aigu des douleurs, Spécialisation de l’ostéopathe en périnatalité, Convictions personnelles concernant cette approche thérapeutique, Expérience personnelle antérieure positive ou négative avec l’ostéopathie | AA70: Sans avis | AB70: Oui | AC70: Oui | AD70: Demande des patientes, Formations sémiologiques supplémentaires des ostéopathes, Recommandations par d’autres professionnels de santé, Encadrement institutionnel et recommandations officielles | AE70: en tant qu'étudiante, je n'ai encore jamais entendu de collègues sages-femmes parler d'ostéopathie pour ce syndrome, en revanche je l'ai déjà conseillé, mais n'ai pas pu avoir de retour (c'était lors d'un stage) | AF70: Collaboration interprofessionnelle, Absence de connaissances sur la pratique ostéopathique, Favorable à l'intégration de l'ostéopathie | AG70: 0 | AH70: 0 | AI70: L'ostéopathie me soulage énormément mes problèmes de dos, de contractures de partout, ça fait un bien fou une ptite séance de temps en temps ! Alors avec plaisir une collab' SF - ostéo !! bon courage pour ton mémoire :)) | AJ70: Expérience personnelle positive, Favorable à l'intégration de l'ostéopathie, Collaboration interprofessionnelle
A71: Étudiant(e) sage-femme en 5e année | B71: 0 | C71: 0 | D71: 2 | E71: 4 | F71: 1 | G71: Non | H71: Oui, occasionnellement (> ou = à 1 fois par mois) | I71: Douleurs lombaires et/ou pelviennes, Post-partum | J71: 1 | K71: Interrogatoire, En excluant d’autres causes possibles de douleurs pelviennes pendant la grossesse | L71: 0 | M71: Sans avis | N71: 0 | O71: Exercices/Etirements | P71: Ostéopathie | Q71: Conseils posturaux | R71: Traitements médicamenteux (antalgiques/analgésiques) | S71: Repos/Limitation de mouvement | T71: Ceinture de maintien/Support pelvien | U71: 4 | V71: Dès les premiers symptômes | W71: 1 | X71: Contenus pédagogiques sur les principes ostéopathiques inscrits au parcours académique, Preuves scientifiques, Réduction du coût des séances pour les patientes, Reconnaissance institutionnelle, Intégration de l’ostéopathie dans les structures de santé | Y71: Peu de contenus pédagogiques sur les principes ostéopathiques inscrits au parcours académique, Absence de connaissances sur la pratique ostéopathique, Insuffisance de collaboration interprofessionnelle avec des ostéopathes, Absence de reconnaissance institutionnelle | Z71: Spécialisation de l’ostéopathe en périnatalité, Motivation des patientes pour une prise en charge manuelle complémentaire, Convictions personnelles concernant cette approche thérapeutique, Expérience personnelle antérieure positive ou négative avec l’ostéopathie | AA71: Oui | AB71: Oui | AC71: Oui | AD71: Preuves de résultats positifs des traitements ostéopathiques, Recommandations par d’autres professionnels de santé, Encadrement institutionnel et recommandations officielles | AE71: 0 | AF71: 0 | AG71: 0 | AH71: 0 | AI71: 0 | AJ71: 0
A72: Étudiant(e) sage-femme en 5e année | B72: 0 | C72: 0 | D72: 3 | E72: 3 | F72: 2 | G72: Sans avis | H72: Oui, rarement (< à 1 fois par mois) | I72: Douleurs lombaires et/ou pelviennes, Post-partum | J72: 1 | K72: Interrogatoire, En excluant d’autres causes possibles de douleurs pelviennes pendant la grossesse | L72: Occasionnellement (> ou = à 1 fois par mois) | M72: Oui | N72: Absence de formation spécifique sur le syndrome, Assimilation du syndrome à des lombalgies non spécifiques, Sous-estimation des plaintes des patientes, Difficultés d’accès aux thérapies non médicamenteuses, Absence de recommandations professionnelles claires | O72: Traitements médicamenteux (antalgiques/analgésiques) | P72: Ostéopathie | Q72: Ceinture de maintien/Support pelvien | R72: Exercices/Etirements | S72: Conseils posturaux | T72: Repos/Limitation de mouvement | U72: 4 | V72: Dès les premiers symptômes | W72: 1 | X72: Contenus pédagogiques sur les principes ostéopathiques inscrits au parcours académique, Retours de patientes, Preuves scientifiques, Réduction du coût des séances pour les patientes | Y72: Peu de contenus pédagogiques sur les principes ostéopathiques inscrits au parcours académique, Absence de connaissances sur la pratique ostéopathique, Insuffisance de preuves scientifiques, Coût pour les patientes | Z72: Caractère chronique ou aigu des douleurs, Réponse ou non aux autres traitements, Spécialisation de l’ostéopathe en périnatalité, Motivation des patientes pour une prise en charge manuelle complémentaire, Disponibilité et/ou accessibilité d’ostéopathes dans votre réseau | AA72: Oui | AB72: Oui | AC72: Oui | AD72: Preuves de résultats positifs des traitements ostéopathiques, Formations sémiologiques supplémentaires des ostéopathes, Mise en place de protocoles règlementés, Encadrement institutionnel et recommandations officielles | AE72: 9 | AF72: 0 | AG72: 0 | AH72: 0 | AI72: 0 | AJ72: 0
A73: Sage-femme diplômé(e) | B73: 5 à 10 ans | C73: Libéral | D73: 1 | E73: 5 | F73: 3 | G73: Oui | H73: Oui, régulièrement (> ou = à 1 fois par semaine) | I73: Suivi prénatal de grossesse, Préparation à l’accouchement, Douleurs lombaires et/ou pelviennes, Troubles digestifs associés, Post-partum, Fertilité, Allaitement, Sphère émotionnelle | J73: 2 | K73: Interrogatoire, En excluant d’autres causes possibles de douleurs pelviennes pendant la grossesse | L73: Fréquemment (> ou = à 1 fois par semaine) | M73: Sans avis | N73: 0 | O73: Ostéopathie | P73: Conseils posturaux | Q73: Exercices/Etirements | R73: Ceinture de maintien/Support pelvien | S73: Repos/Limitation de mouvement | T73: Traitements médicamenteux (antalgiques/analgésiques) | U73: 5 | V73: Dès les premiers symptômes | W73: 2 | X73: Retours de patientes, Médiatisation/Réseaux sociaux, Reconnaissance institutionnelle, Intégration de l’ostéopathie dans les structures de santé | Y73: Peu de contenus pédagogiques sur les principes ostéopathiques inscrits au parcours académique, Absence de connaissances sur la pratique ostéopathique | Z73: Caractère chronique ou aigu des douleurs, Réponse ou non aux autres traitements, Spécialisation de l’ostéopathe en périnatalité, Motivation des patientes pour une prise en charge manuelle complémentaire, Moment de la douleur, Disponibilité et/ou accessibilité d’ostéopathes dans votre réseau, Collaboration interprofessionnelle préexistante, Convictions personnelles concernant cette approche thérapeutique, Expérience personnelle antérieure positive ou négative avec l’ostéopathie | AA73: Sans avis | AB73: Oui | AC73: Oui | AD73: Formations sémiologiques supplémentaires des ostéopathes, Mise en place de protocoles règlementés, Encadrement institutionnel et recommandations officielles | AE73: Merci les ostéos d'exister! | AF73: Favorable à l'intégration de l'ostéopathie | AG73: 0 | AH73: 0 | AI73: 0 | AJ73: 0
A74: Sage-femme diplômé(e) | B74: Plus de 10 ans | C74: Hospitalier | D74: 3 | E74: 4 | F74: 3 | G74: Non | H74: Oui, rarement (< à 1 fois par mois) | I74: Douleurs lombaires et/ou pelviennes, Post-partum | J74: 4 | K74: Interrogatoire, Examen clinique, En excluant d’autres causes possibles de douleurs pelviennes pendant la grossesse | L74: Occasionnellement (> ou = à 1 fois par mois) | M74: Non | N74: 0 | O74: Conseils posturaux | P74: Traitements médicamenteux (antalgiques/analgésiques) | Q74: Exercices/Etirements | R74: Ostéopathie | S74: Ceinture de maintien/Support pelvien | T74: Repos/Limitation de mouvement | U74: 3 | V74: 0 | W74: 3 | X74: Preuves scientifiques | Y74: Insuffisance de preuves scientifiques, Insuffisance de collaboration interprofessionnelle avec des ostéopathes, Coût pour les patientes | Z74: Spécialisation de l’ostéopathe en périnatalité, Motivation des patientes pour une prise en charge manuelle complémentaire, Disponibilité et/ou accessibilité d’ostéopathes dans votre réseau | AA74: Sans avis | AB74: Sans avis | AC74: Sans avis | AD74: Encadrement institutionnel et recommandations officielles | AE74: 0 | AF74: 0 | AG74: 0 | AH74: 0 | AI74: 0 | AJ74: 0
A75: Sage-femme diplômé(e) | B75: 5 à 10 ans | C75: Libéral | D75: 3 | E75: 5 | F75: 4 | G75: Oui | H75: Oui, régulièrement (> ou = à 1 fois par semaine) | I75: Suivi prénatal de grossesse, Préparation à l’accouchement, Douleurs lombaires et/ou pelviennes, Troubles digestifs associés, Post-partum, Allaitement | J75: 4 | K75: Interrogatoire, Examen clinique, En excluant d’autres causes possibles de douleurs pelviennes pendant la grossesse | L75: Occasionnellement (> ou = à 1 fois par mois) | M75: Non | N75: 0 | O75: Ostéopathie | P75: Conseils posturaux | Q75: Exercices/Etirements | R75: Ceinture de maintien/Support pelvien | S75: Repos/Limitation de mouvement | T75: Traitements médicamenteux (antalgiques/analgésiques) | U75: 4 | V75: Dès les premiers symptômes | W75: 4 | X75: Retours de patientes, Preuves scientifiques, Réduction du coût des séances pour les patientes, Reconnaissance institutionnelle, Intégration de l’ostéopathie dans les structures de santé | Y75: Coût pour les patientes, Absence de reconnaissance institutionnelle | Z75: Caractère chronique ou aigu des douleurs, Réponse ou non aux autres traitements, Spécialisation de l’ostéopathe en périnatalité, Motivation des patientes pour une prise en charge manuelle complémentaire, Moment de la douleur, Disponibilité et/ou accessibilité d’ostéopathes dans votre réseau, Collaboration interprofessionnelle préexistante, Convictions personnelles concernant cette approche thérapeutique, Expérience personnelle antérieure positive ou négative avec l’ostéopathie | AA75: Sans avis | AB75: Oui | AC75: Oui | AD75: Preuves de résultats positifs des traitements ostéopathiques, Demande des patientes, Recommandations par d’autres professionnels de santé, Mise en place de protocoles règlementés | AE75: 0 | AF75: 0 | AG75: 0 | AH75: 0 | AI75: 0 | AJ75: 0
A76: Étudiant(e) sage-femme en 5e année | B76: 0 | C76: 0 | D76: 1 | E76: 3 | F76: 2 | G76: Non | H76: Non | I76: 0 | J76: 3 | K76: Interrogatoire | L76: Fréquemment (> ou = à 1 fois par semaine) | M76: Oui | N76: Absence de formation spécifique sur le syndrome, Sous-estimation des plaintes des patientes, Absence de recommandations professionnelles claires | O76: Exercices/Etirements | P76: Conseils posturaux | Q76: Ostéopathie | R76: Ceinture de maintien/Support pelvien | S76: Traitements médicamenteux (antalgiques/analgésiques) | T76: Repos/Limitation de mouvement | U76: 5 | V76: En fin de grossesse | W76: 1 | X76: Contenus pédagogiques sur les principes ostéopathiques inscrits au parcours académique, Retours de patientes, Preuves scientifiques, Médiatisation/Réseaux sociaux, Réduction du coût des séances pour les patientes, Reconnaissance institutionnelle, Intégration de l’ostéopathie dans les structures de santé | Y76: Peu de contenus pédagogiques sur les principes ostéopathiques inscrits au parcours académique, Absence de connaissances sur la pratique ostéopathique, Insuffisance de collaboration interprofessionnelle avec des ostéopathes | Z76: Spécialisation de l’ostéopathe en périnatalité, Disponibilité et/ou accessibilité d’ostéopathes dans votre réseau, Collaboration interprofessionnelle préexistante, Convictions personnelles concernant cette approche thérapeutique, Expérience personnelle antérieure positive ou négative avec l’ostéopathie | AA76: Oui | AB76: Oui | AC76: Oui | AD76: Preuves de résultats positifs des traitements ostéopathiques, Formations sémiologiques supplémentaires des ostéopathes, Mise en place de protocoles règlementés, Encadrement institutionnel et recommandations officielles | AE76: 0 | AF76: 0 | AG76: 0 | AH76: 0 | AI76: 0 | AJ76: 0
A77: Étudiant(e) sage-femme en 5e année | B77: 0 | C77: 0 | D77: 2 | E77: 3 | F77: 2 | G77: Non | H77: Oui, occasionnellement (> ou = à 1 fois par mois) | I77: Douleurs lombaires et/ou pelviennes | J77: 2 | K77: Interrogatoire, Examen clinique, En excluant d’autres causes possibles de douleurs pelviennes pendant la grossesse | L77: Fréquemment (> ou = à 1 fois par semaine) | M77: Non | N77: Sous-estimation des plaintes des patientes, Difficultés d’accès aux thérapies non médicamenteuses | O77: Ceinture de maintien/Support pelvien | P77: Exercices/Etirements | Q77: Conseils posturaux | R77: Ostéopathie | S77: Repos/Limitation de mouvement | T77: Traitements médicamenteux (antalgiques/analgésiques) | U77: 3 | V77: En cas d’absence de réussite d’autres prises en charge | W77: 4 | X77: Contenus pédagogiques sur les principes ostéopathiques inscrits au parcours académique, Retours de patientes, Preuves scientifiques, Réduction du coût des séances pour les patientes, Reconnaissance institutionnelle | Y77: Peu de contenus pédagogiques sur les principes ostéopathiques inscrits au parcours académique, Insuffisance de preuves scientifiques, Coût pour les patientes, Absence de reconnaissance institutionnelle | Z77: Réponse ou non aux autres traitements, Spécialisation de l’ostéopathe en périnatalité, Motivation des patientes pour une prise en charge manuelle complémentaire, Disponibilité et/ou accessibilité d’ostéopathes dans votre réseau, Convictions personnelles concernant cette approche thérapeutique | AA77: Oui | AB77: Oui | AC77: Oui | AD77: Preuves de résultats positifs des traitements ostéopathiques, Demande des patientes, Recommandations par d’autres professionnels de santé, Mise en place de protocoles règlementés, Encadrement institutionnel et recommandations officielles | AE77: 0 | AF77: 0 | AG77: 0 | AH77: 0 | AI77: 0 | AJ77: 0
A78: Étudiant(e) sage-femme en 5e année | B78: 0 | C78: 0 | D78: 1 | E78: 4 | F78: 1 | G78: Sans avis | H78: Oui, rarement (< à 1 fois par mois) | I78: Douleurs lombaires et/ou pelviennes | J78: 1 | K78: Interrogatoire, Examen clinique | L78: Occasionnellement (> ou = à 1 fois par mois) | M78: Oui | N78: Absence de formation spécifique sur le syndrome | O78: Conseils posturaux | P78: Exercices/Etirements | Q78: Ceinture de maintien/Support pelvien | R78: Repos/Limitation de mouvement | S78: Ostéopathie | T78: Traitements médicamenteux (antalgiques/analgésiques) | U78: 5 | V78: Dès les premiers symptômes | W78: 1 | X78: Contenus pédagogiques sur les principes ostéopathiques inscrits au parcours académique | Y78: Peu de contenus pédagogiques sur les principes ostéopathiques inscrits au parcours académique, Absence de connaissances sur la pratique ostéopathique | Z78: Motivation des patientes pour une prise en charge manuelle complémentaire | AA78: Sans avis | AB78: Oui | AC78: Oui | AD78: Formations sémiologiques supplémentaires des ostéopathes, Mise en place de protocoles règlementés | AE78: 0 | AF78: 0 | AG78: 0 | AH78: 0 | AI78: 0 | AJ78: 0
A79: Étudiant(e) sage-femme en 5e année | B79: 0 | C79: 0 | D79: 2 | E79: 3 | F79: 1 | G79: Non | H79: Oui, rarement (< à 1 fois par mois) | I79: Post-partum | J79: 2 | K79: Interrogatoire, En excluant d’autres causes possibles de douleurs pelviennes pendant la grossesse, Démarche de la patiente | L79: Fréquemment (> ou = à 1 fois par semaine) | M79: Oui | N79: Assimilation du syndrome à des lombalgies non spécifiques, Sous-estimation des plaintes des patientes, Absence de recommandations professionnelles claires | O79: Conseils posturaux | P79: Ceinture de maintien/Support pelvien | Q79: Exercices/Etirements | R79: Traitements médicamenteux (antalgiques/analgésiques) | S79: Ostéopathie | T79: Repos/Limitation de mouvement | U79: 4 | V79: Dès les premiers symptômes | W79: 2 | X79: Contenus pédagogiques sur les principes ostéopathiques inscrits au parcours académique, Retours de patientes, Réduction du coût des séances pour les patientes | Y79: Peu de contenus pédagogiques sur les principes ostéopathiques inscrits au parcours académique, Insuffisance de collaboration interprofessionnelle avec des ostéopathes, Coût pour les patientes | Z79: Caractère chronique ou aigu des douleurs, Réponse ou non aux autres traitements, Collaboration interprofessionnelle préexistante, Convictions personnelles concernant cette approche thérapeutique, Expérience personnelle antérieure positive ou négative avec l’ostéopathie | AA79: Oui | AB79: Oui | AC79: Oui | AD79: Preuves de résultats positifs des traitements ostéopathiques, Demande des patientes | AE79: 0 | AF79: 0 | AG79: En post partum, lorsqu’une patiente se plains de douleurs (notamment au niveau du coccyx) on va lui conseiller un osteo en post partum. Mais pendant la grossesse dès qu’une femme a des douleurs, lombaires surtout, on va la supplementer en magnésium… et pas forcément diriger vers un autre spécialiste, j’ai rarement vu cela. | AH79: Collaboration interprofessionnelle, Favorable à l'intégration de l'ostéopathie, Manque d’informations sur les pratiques ostéopathiques en périnatalité | AI79: 0 | AJ79: 0
A80: Étudiant(e) sage-femme en 5e année | B80: 0 | C80: 0 | D80: 1 | E80: 2 | F80: 3 | G80: Sans avis | H80: Oui, rarement (< à 1 fois par mois) | I80: Sphère émotionnelle | J80: 2 | K80: Interrogatoire, Examen clinique, Recours aux examens complémentaires, En excluant d’autres causes possibles de douleurs pelviennes pendant la grossesse | L80: Occasionnellement (> ou = à 1 fois par mois) | M80: Oui | N80: Assimilation du syndrome à des lombalgies non spécifiques, Sous-estimation des plaintes des patientes | O80: Exercices/Etirements | P80: Conseils posturaux | Q80: Ceinture de maintien/Support pelvien | R80: Traitements médicamenteux (antalgiques/analgésiques) | S80: Repos/Limitation de mouvement | T80: Ostéopathie | U80: 1 | V80: 0 | W80: 5 | X80: Preuves scientifiques | Y80: Insuffisance de preuves scientifiques, Coût pour les patientes | Z80: Motivation des patientes pour une prise en charge manuelle complémentaire | AA80: Oui | AB80: Sans avis | AC80: Non | AD80: Preuves de résultats positifs des traitements ostéopathiques, Formations sémiologiques supplémentaires des ostéopathes, Mise en place de protocoles règlementés, Encadrement institutionnel et recommandations officielles | AE80: 0 | AF80: 0 | AG80: 0 | AH80: 0 | AI80: 0 | AJ80: 0
A81: Étudiant(e) sage-femme en 5e année | B81: 0 | C81: 0 | D81: 2 | E81: 4 | F81: 2 | G81: Non | H81: Non | I81: 0 | J81: 4 | K81: Interrogatoire, En excluant d’autres causes possibles de douleurs pelviennes pendant la grossesse | L81: Fréquemment (> ou = à 1 fois par semaine) | M81: Oui | N81: Absence de formation spécifique sur le syndrome, Difficultés d’accès aux thérapies non médicamenteuses, Absence de recommandations professionnelles claires | O81: Exercices/Etirements | P81: Conseils posturaux | Q81: Ceinture de maintien/Support pelvien | R81: Traitements médicamenteux (antalgiques/analgésiques) | S81: Ostéopathie | T81: Repos/Limitation de mouvement | U81: 4 | V81: En cas d’absence de réussite d’autres prises en charge | W81: 2 | X81: Contenus pédagogiques sur les principes ostéopathiques inscrits au parcours académique, Retours de patientes, Réduction du coût des séances pour les patientes, Intégration de l’ostéopathie dans les structures de santé | Y81: Absence de connaissances sur la pratique ostéopathique, Insuffisance de collaboration interprofessionnelle avec des ostéopathes, Coût pour les patientes | Z81: Caractère chronique ou aigu des douleurs, Réponse ou non aux autres traitements, Spécialisation de l’ostéopathe en périnatalité, Motivation des patientes pour une prise en charge manuelle complémentaire | AA81: Non | AB81: Oui | AC81: Oui | AD81: Preuves de résultats positifs des traitements ostéopathiques, Demande des patientes, Encadrement institutionnel et recommandations officielles | AE81: 0 | AF81: 0 | AG81: 0 | AH81: 0 | AI81: 0 | AJ81: 0
A82: Étudiant(e) sage-femme en 5e année | B82: 0 | C82: 0 | D82: 3 | E82: 5 | F82: 3 | G82: Sans avis | H82: Oui, occasionnellement (> ou = à 1 fois par mois) | I82: Douleurs lombaires et/ou pelviennes, Troubles digestifs associés, Post-partum | J82: 3 | K82: Interrogatoire, En excluant d’autres causes possibles de douleurs pelviennes pendant la grossesse | L82: Occasionnellement (> ou = à 1 fois par mois) | M82: Oui | N82: Absence de formation spécifique sur le syndrome, Assimilation du syndrome à des lombalgies non spécifiques, Sous-estimation des plaintes des patientes, Absence de recommandations professionnelles claires | O82: Ceinture de maintien/Support pelvien | P82: Ostéopathie | Q82: Conseils posturaux | R82: Traitements médicamenteux (antalgiques/analgésiques) | S82: Exercices/Etirements | T82: Repos/Limitation de mouvement | U82: 4 | V82: Dès les premiers symptômes | W82: 2 | X82: Contenus pédagogiques sur les principes ostéopathiques inscrits au parcours académique, Retours de patientes, Preuves scientifiques, Réduction du coût des séances pour les patientes, Reconnaissance institutionnelle, Intégration de l’ostéopathie dans les structures de santé | Y82: Peu de contenus pédagogiques sur les principes ostéopathiques inscrits au parcours académique, Absence de connaissances sur la pratique ostéopathique, Insuffisance de preuves scientifiques, Insuffisance de collaboration interprofessionnelle avec des ostéopathes, Coût pour les patientes, Absence de reconnaissance institutionnelle | Z82: Réponse ou non aux autres traitements, Spécialisation de l’ostéopathe en périnatalité, Motivation des patientes pour une prise en charge manuelle complémentaire, Collaboration interprofessionnelle préexistante, Convictions personnelles concernant cette approche thérapeutique | AA82: Oui | AB82: Oui | AC82: Oui | AD82: Preuves de résultats positifs des traitements ostéopathiques, Demande des patientes, Mise en place de protocoles règlementés, Encadrement institutionnel et recommandations officielles | AE82: 0 | AF82: 0 | AG82: 0 | AH82: 0 | AI82: 0 | AJ82: 0
A83: Étudiant(e) sage-femme en 5e année | B83: 0 | C83: 0 | D83: 2 | E83: 4 | F83: 2 | G83: Non | H83: Oui, occasionnellement (> ou = à 1 fois par mois) | I83: Douleurs lombaires et/ou pelviennes, Post-partum | J83: 3 | K83: Interrogatoire, Examen clinique, En excluant d’autres causes possibles de douleurs pelviennes pendant la grossesse | L83: Occasionnellement (> ou = à 1 fois par mois) | M83: Oui | N83: Assimilation du syndrome à des lombalgies non spécifiques, Difficultés d’accès aux thérapies non médicamenteuses, Absence de recommandations professionnelles claires | O83: Conseils posturaux | P83: Exercices/Etirements | Q83: Ostéopathie | R83: Repos/Limitation de mouvement | S83: Ceinture de maintien/Support pelvien | T83: Traitements médicamenteux (antalgiques/analgésiques) | U83: 5 | V83: Dès les premiers symptômes | W83: 2 | X83: Retours de patientes, Intégration de l’ostéopathie dans les structures de santé | Y83: Insuffisance de collaboration interprofessionnelle avec des ostéopathes | Z83: Spécialisation de l’ostéopathe en périnatalité, Motivation des patientes pour une prise en charge manuelle complémentaire, Collaboration interprofessionnelle préexistante, Expérience personnelle antérieure positive ou négative avec l’ostéopathie | AA83: Oui | AB83: Oui | AC83: Oui | AD83: Formations sémiologiques supplémentaires des ostéopathes, Mise en place de protocoles règlementés | AE83: 0 | AF83: 0 | AG83: 0 | AH83: 0 | AI83: 0 | AJ83: 0
A84: Étudiant(e) sage-femme en 5e année | B84: 0 | C84: 0 | D84: 1 | E84: 3 | F84: 2 | G84: Sans avis | H84: Oui, rarement (< à 1 fois par mois) | I84: Douleurs lombaires et/ou pelviennes | J84: 2 | K84: Interrogatoire, Examen clinique, En excluant d’autres causes possibles de douleurs pelviennes pendant la grossesse | L84: Rarement (> ou = à 1 fois tous les 3 mois) | M84: Oui | N84: Assimilation du syndrome à des lombalgies non spécifiques, Sous-estimation des plaintes des patientes | O84: Conseils posturaux | P84: Repos/Limitation de mouvement | Q84: Traitements médicamenteux (antalgiques/analgésiques) | R84: Ostéopathie | S84: Exercices/Etirements | T84: Ceinture de maintien/Support pelvien | U84: 3 | V84: Dès les premiers symptômes | W84: 2 | X84: Contenus pédagogiques sur les principes ostéopathiques inscrits au parcours académique, Retours de patientes, Preuves scientifiques | Y84: Peu de contenus pédagogiques sur les principes ostéopathiques inscrits au parcours académique, Absence de connaissances sur la pratique ostéopathique, Insuffisance de collaboration interprofessionnelle avec des ostéopathes | Z84: Caractère chronique ou aigu des douleurs, Réponse ou non aux autres traitements, Collaboration interprofessionnelle préexistante, Convictions personnelles concernant cette approche thérapeutique | AA84: Oui | AB84: Oui | AC84: Oui | AD84: Preuves de résultats positifs des traitements ostéopathiques, Demande des patientes, Absence ou inefficacité d’autres solutions thérapeutiques, Encadrement institutionnel et recommandations officielles | AE84: 0 | AF84: 0 | AG84: 0 | AH84: 0 | AI84: 0 | AJ84: 0
A85: Étudiant(e) sage-femme en 5e année | B85: 0 | C85: 0 | D85: 1 | E85: 1 | F85: 1 | G85: Non | H85: Non | I85: 0 | J85: 3 | K85: Interrogatoire, Examen clinique | L85: Occasionnellement (> ou = à 1 fois par mois) | M85: Sans avis | N85: Absence de formation spécifique sur le syndrome, Assimilation du syndrome à des lombalgies non spécifiques, Sous-estimation des plaintes des patientes | O85: Ceinture de maintien/Support pelvien | P85: Exercices/Etirements | Q85: Repos/Limitation de mouvement | R85: Conseils posturaux | S85: Traitements médicamenteux (antalgiques/analgésiques) | T85: Ostéopathie | U85: 1 | V85: Dès les premiers symptômes | W85: 3 | X85: Preuves scientifiques | Y85: Insuffisance de preuves scientifiques | Z85: 0 | AA85: Oui | AB85: Non | AC85: Non | AD85: Preuves de résultats positifs des traitements ostéopathiques | AE85: 0 | AF85: 0 | AG85: 0 | AH85: 0 | AI85: 0 | AJ85: 0
A86: Sage-femme diplômé(e) | B86: 5 à 10 ans | C86: Hospitalier | D86: 1 | E86: 4 | F86: 2 | G86: Non | H86: Non | I86: 0 | J86: 2 | K86: Interrogatoire, Examen clinique, En excluant d’autres causes possibles de douleurs pelviennes pendant la grossesse | L86: Occasionnellement (> ou = à 1 fois par mois) | M86: Oui | N86: Assimilation du syndrome à des lombalgies non spécifiques, Sous-estimation des plaintes des patientes, Absence de recommandations professionnelles claires | O86: Ceinture de maintien/Support pelvien | P86: Ostéopathie | Q86: Traitements médicamenteux (antalgiques/analgésiques) | R86: Repos/Limitation de mouvement | S86: Exercices/Etirements | T86: Conseils posturaux | U86: 4 | V86: Dès les premiers symptômes | W86: 1 | X86: Contenus pédagogiques sur les principes ostéopathiques inscrits au parcours académique, Retours de patientes, Preuves scientifiques, Médiatisation/Réseaux sociaux, Réduction du coût des séances pour les patientes, Reconnaissance institutionnelle, Intégration de l’ostéopathie dans les structures de santé | Y86: Absence de connaissances sur la pratique ostéopathique, Insuffisance de preuves scientifiques, Insuffisance de collaboration interprofessionnelle avec des ostéopathes | Z86: Caractère chronique ou aigu des douleurs, Convictions personnelles concernant cette approche thérapeutique | AA86: Sans avis | AB86: Oui | AC86: Oui | AD86: Preuves de résultats positifs des traitements ostéopathiques, Demande des patientes, Mise en place de protocoles règlementés, Encadrement institutionnel et recommandations officielles | AE86: 0 | AF86: 0 | AG86: 0 | AH86: 0 | AI86: 0 | AJ86: 0
A87: Étudiant(e) sage-femme en 5e année | B87: 0 | C87: 0 | D87: 2 | E87: 4 | F87: 2 | G87: Non | H87: Oui, rarement (< à 1 fois par mois) | I87: Suivi prénatal de grossesse, Douleurs lombaires et/ou pelviennes, Post-partum | J87: 3 | K87: Interrogatoire, Examen clinique | L87: Occasionnellement (> ou = à 1 fois par mois) | M87: Oui | N87: Assimilation du syndrome à des lombalgies non spécifiques, Sous-estimation des plaintes des patientes | O87: Exercices/Etirements | P87: Ostéopathie | Q87: Conseils posturaux | R87: Ceinture de maintien/Support pelvien | S87: Traitements médicamenteux (antalgiques/analgésiques) | T87: Repos/Limitation de mouvement | U87: 5 | V87: Dès les premiers symptômes | W87: 2 | X87: Contenus pédagogiques sur les principes ostéopathiques inscrits au parcours académique, Preuves scientifiques, Réduction du coût des séances pour les patientes | Y87: Absence de connaissances sur la pratique ostéopathique, Coût pour les patientes | Z87: Spécialisation de l’ostéopathe en périnatalité, Disponibilité et/ou accessibilité d’ostéopathes dans votre réseau, Collaboration interprofessionnelle préexistante, Convictions personnelles concernant cette approche thérapeutique | AA87: Oui | AB87: Oui | AC87: Oui | AD87: Mise en place de protocoles règlementés, Encadrement institutionnel et recommandations officielles | AE87: Les patientes décrivent un soulagement mais temporaire | AF87: Efficacité perçue, Soulagement temporaire | AG87: L'ostéopathie permet de soulager de beaucoup de maux, notament après l'accouchement pour remettre en place le bassin mais aussi durant la grossesse pour corriger les mauvaises postures. J'ai pu voir des orientations chez l'ostéo aussi pour les NN qui ont des troubles digestifs et cela a plutôt été efficace | AH87: Efficacité perçue, Collaboration interprofessionnelle, Favorable à l'intégration de l'ostéopathie, Nouveaux-nés | AI87: 0 | AJ87: 0
A88: Sage-femme diplômé(e) | B88: Plus de 10 ans | C88: Hospitalier | D88: 3 | E88: 4 | F88: 2 | G88: Non | H88: Oui, occasionnellement (> ou = à 1 fois par mois) | I88: Douleurs lombaires et/ou pelviennes, Troubles digestifs associés | J88: 1 | K88: En excluant d’autres causes possibles de douleurs pelviennes pendant la grossesse | L88: Fréquemment (> ou = à 1 fois par semaine) | M88: Non | N88: 0 | O88: Exercices/Etirements, Conseils posturaux | P88: Ceinture de maintien/Support pelvien | Q88: Ostéopathie | R88: Traitements médicamenteux (antalgiques/analgésiques) | S88: Repos/Limitation de mouvement | T88: Traitements médicamenteux (antalgiques/analgésiques) | U88: 5 | V88: Dès les premiers symptômes | W88: 4 | X88: Preuves scientifiques, Réduction du coût des séances pour les patientes | Y88: Insuffisance de collaboration interprofessionnelle avec des ostéopathes, Coût pour les patientes | Z88: Caractère chronique ou aigu des douleurs, Expérience personnelle antérieure positive ou négative avec l’ostéopathie | AA88: Non | AB88: Oui | AC88: Oui | AD88: Recommandations par d’autres professionnels de santé | AE88: 0 | AF88: 0 | AG88: 0 | AH88: 0 | AI88: 0 | AJ88: 0
A89: Étudiant(e) sage-femme en 5e année | B89: 0 | C89: 0 | D89: 2 | E89: 3 | F89: 4 | G89: Oui | H89: Oui, occasionnellement (> ou = à 1 fois par mois) | I89: Douleurs lombaires et/ou pelviennes, Post-partum | J89: 4 | K89: Interrogatoire | L89: Rarement (> ou = à 1 fois tous les 3 mois) | M89: Sans avis | N89: 0 | O89: Repos/Limitation de mouvement | P89: Traitements médicamenteux (antalgiques/analgésiques) | Q89: Ostéopathie | R89: Ceinture de maintien/Support pelvien | S89: Conseils posturaux | T89: Exercices/Etirements | U89: 5 | V89: Dès les premiers symptômes | W89: 3 | X89: Contenus pédagogiques sur les principes ostéopathiques inscrits au parcours académique, Preuves scientifiques, Réduction du coût des séances pour les patientes, Reconnaissance institutionnelle, Intégration de l’ostéopathie dans les structures de santé | Y89: Peu de contenus pédagogiques sur les principes ostéopathiques inscrits au parcours académique, Absence de connaissances sur la pratique ostéopathique, Coût pour les patientes | Z89: Caractère chronique ou aigu des douleurs, Réponse ou non aux autres traitements, Spécialisation de l’ostéopathe en périnatalité, Motivation des patientes pour une prise en charge manuelle complémentaire | AA89: Oui | AB89: Oui | AC89: Oui | AD89: Demande des patientes, Formations sémiologiques supplémentaires des ostéopathes, Encadrement institutionnel et recommandations officielles | AE89: 0 | AF89: 0 | AG89: 0 | AH89: 0 | AI89: 0 | AJ89: 0
A90: Étudiant(e) sage-femme en 5e année | B90: 0 | C90: 0 | D90: 3 | E90: 4 | F90: 3 | G90: Non | H90: Oui, occasionnellement (> ou = à 1 fois par mois) | I90: Douleurs lombaires et/ou pelviennes, Post-partum | J90: 3 | K90: Interrogatoire, Examen clinique, En excluant d’autres causes possibles de douleurs pelviennes pendant la grossesse | L90: Fréquemment (> ou = à 1 fois par semaine) | M90: Sans avis | N90: 0 | O90: Conseils posturaux | P90: Exercices/Etirements | Q90: Ostéopathie | R90: Repos/Limitation de mouvement | S90: Ceinture de maintien/Support pelvien | T90: Traitements médicamenteux (antalgiques/analgésiques) | U90: 4 | V90: En fin de grossesse | W90: 2 | X90: Contenus pédagogiques sur les principes ostéopathiques inscrits au parcours académique, Médiatisation/Réseaux sociaux, Réduction du coût des séances pour les patientes, Intégration de l’ostéopathie dans les structures de santé | Y90: Peu de contenus pédagogiques sur les principes ostéopathiques inscrits au parcours académique, Insuffisance de preuves scientifiques, Coût pour les patientes | Z90: Caractère chronique ou aigu des douleurs, Réponse ou non aux autres traitements, Spécialisation de l’ostéopathe en périnatalité, Motivation des patientes pour une prise en charge manuelle complémentaire, Convictions personnelles concernant cette approche thérapeutique, Expérience personnelle antérieure positive ou négative avec l’ostéopathie | AA90: Sans avis | AB90: Oui | AC90: Oui | AD90: Preuves de résultats positifs des traitements ostéopathiques, Encadrement institutionnel et recommandations officielles | AE90: 0 | AF90: 0 | AG90: 0 | AH90: 0 | AI90: 0 | AJ90: 0
A91: Sage-femme diplômé(e) | B91: 2 à 5 ans | C91: Libéral | D91: 3 | E91: 5 | F91: 4 | G91: Oui | H91: Oui, occasionnellement (> ou = à 1 fois par mois) | I91: Suivi prénatal de grossesse, Douleurs lombaires et/ou pelviennes, Post-partum, Allaitement | J91: 3 | K91: En excluant d’autres causes possibles de douleurs pelviennes pendant la grossesse | L91: Rarement (> ou = à 1 fois tous les 3 mois) | M91: Oui | N91: Assimilation du syndrome à des lombalgies non spécifiques, Sous-estimation des plaintes des patientes, Absence de recommandations professionnelles claires | O91: Conseils posturaux | P91: Exercices/Etirements | Q91: Ceinture de maintien/Support pelvien | R91: Ostéopathie | S91: Traitements médicamenteux (antalgiques/analgésiques) | T91: Repos/Limitation de mouvement | U91: 5 | V91: En cas d’absence de réussite d’autres prises en charge | W91: 2 | X91: Preuves scientifiques, Réduction du coût des séances pour les patientes | Y91: Insuffisance de preuves scientifiques, Coût pour les patientes, Absence de reconnaissance institutionnelle | Z91: Caractère chronique ou aigu des douleurs, Réponse ou non aux autres traitements | AA91: Sans avis | AB91: Oui | AC91: Oui | AD91: Preuves de résultats positifs des traitements ostéopathiques, Encadrement institutionnel et recommandations officielles | AE91: 0 | AF91: 0 | AG91: 0 | AH91: 0 | AI91: 0 | AJ91: 0
A92: Sage-femme diplômé(e) | B92: Plus de 10 ans | C92: Hospitalier | D92: 3 | E92: 4 | F92: 4 | G92: Non | H92: Oui, régulièrement (> ou = à 1 fois par semaine) | I92: Suivi prénatal de grossesse, Douleurs lombaires et/ou pelviennes, Post-partum, Allaitement | J92: 4 | K92: Interrogatoire, En excluant d’autres causes possibles de douleurs pelviennes pendant la grossesse | L92: Fréquemment (> ou = à 1 fois par semaine) | M92: Oui | N92: Absence de formation spécifique sur le syndrome, Absence de recommandations professionnelles claires | O92: Exercices/Etirements, Conseils posturaux | P92: Exercices/Etirements, Ostéopathie | Q92: Ostéopathie | R92: Ceinture de maintien/Support pelvien | S92: Traitements médicamenteux (antalgiques/analgésiques) | T92: Repos/Limitation de mouvement | U92: 5 | V92: Dès les premiers symptômes | W92: 4 | X92: Retours de patientes, Preuves scientifiques, Réduction du coût des séances pour les patientes, Reconnaissance institutionnelle | Y92: Insuffisance de preuves scientifiques, Coût pour les patientes, Absence de reconnaissance institutionnelle | Z92: Caractère chronique ou aigu des douleurs, Réponse ou non aux autres traitements, Motivation des patientes pour une prise en charge manuelle complémentaire, Expérience personnelle antérieure positive ou négative avec l’ostéopathie | AA92: Non | AB92: Oui | AC92: Oui | AD92: Preuves de résultats positifs des traitements ostéopathiques, Encadrement institutionnel et recommandations officielles | AE92: 0 | AF92: 0 | AG92: 0 | AH92: 0 | AI92: 0 | AJ92: 0
A93: Sage-femme diplômé(e) | B93: 5 à 10 ans | C93: Hospitalier | D93: 2 | E93: 3 | F93: 2 | G93: Oui | H93: Non | I93: 0 | J93: 4 | K93: Interrogatoire, Examen clinique, En excluant d’autres causes possibles de douleurs pelviennes pendant la grossesse | L93: Fréquemment (> ou = à 1 fois par semaine) | M93: Oui | N93: Absence de formation spécifique sur le syndrome, Assimilation du syndrome à des lombalgies non spécifiques, Absence de recommandations professionnelles claires | O93: Repos/Limitation de mouvement | P93: Ostéopathie | Q93: Exercices/Etirements | R93: Ceinture de maintien/Support pelvien | S93: Conseils posturaux | T93: Traitements médicamenteux (antalgiques/analgésiques) | U93: 4 | V93: Dès les premiers symptômes | W93: 1 | X93: Contenus pédagogiques sur les principes ostéopathiques inscrits au parcours académique, Preuves scientifiques, Reconnaissance institutionnelle | Y93: Peu de contenus pédagogiques sur les principes ostéopathiques inscrits au parcours académique, Absence de connaissances sur la pratique ostéopathique, Insuffisance de preuves scientifiques, Absence de reconnaissance institutionnelle | Z93: Réponse ou non aux autres traitements, Spécialisation de l’ostéopathe en périnatalité, Moment de la douleur, Collaboration interprofessionnelle préexistante | AA93: Non | AB93: Oui | AC93: Oui | AD93: Preuves de résultats positifs des traitements ostéopathiques, Mise en place de protocoles règlementés, Encadrement institutionnel et recommandations officielles | AE93: 0 | AF93: 0 | AG93: 0 | AH93: 0 | AI93: 0 | AJ93: 0
A94: Sage-femme diplômé(e) | B94: 5 à 10 ans | C94: Libéral | D94: 3 | E94: 5 | F94: 4 | G94: Oui | H94: Oui, régulièrement (> ou = à 1 fois par semaine) | I94: Suivi prénatal de grossesse, Douleurs lombaires et/ou pelviennes, Troubles digestifs associés, Post-partum | J94: 4 | K94: Interrogatoire, En excluant d’autres causes possibles de douleurs pelviennes pendant la grossesse | L94: Fréquemment (> ou = à 1 fois par semaine) | M94: Sans avis | N94: 0 | O94: Conseils posturaux | P94: Ostéopathie | Q94: Exercices/Etirements | R94: Repos/Limitation de mouvement | S94: Ceinture de maintien/Support pelvien | T94: Traitements médicamenteux (antalgiques/analgésiques) | U94: 4 | V94: Dès les premiers symptômes | W94: 2 | X94: Contenus pédagogiques sur les principes ostéopathiques inscrits au parcours académique, Preuves scientifiques, Médiatisation/Réseaux sociaux | Y94: Peu de contenus pédagogiques sur les principes ostéopathiques inscrits au parcours académique, Insuffisance de preuves scientifiques, Coût pour les patientes | Z94: Spécialisation de l’ostéopathe en périnatalité, Motivation des patientes pour une prise en charge manuelle complémentaire, Collaboration interprofessionnelle préexistante, Convictions personnelles concernant cette approche thérapeutique, Expérience personnelle antérieure positive ou négative avec l’ostéopathie | AA94: Non | AB94: Oui | AC94: Oui | AD94: Preuves de résultats positifs des traitements ostéopathiques, Mise en place de protocoles règlementés, Encadrement institutionnel et recommandations officielles | AE94: 0 | AF94: 0 | AG94: Nécessité +++ en ce qui me concerne d’avoir une formation en périnatalité. Mais adepte +++ de la PÊCHE ostéopathe pour la femme enceinte | AH94: Favorable à l'intégration de l'ostéopathie, Formation en périnatalité, Collaboration interprofessionnelle | AI94: 0 | AJ94: 0
A95: Sage-femme diplômé(e) | B95: Plus de 10 ans | C95: Libéral | D95: 4 | E95: 4 | F95: 4 | G95: Oui | H95: Oui, occasionnellement (> ou = à 1 fois par mois) | I95: Suivi prénatal de grossesse, Douleurs lombaires et/ou pelviennes, Troubles digestifs associés, Post-partum, Allaitement | J95: 3 | K95: Interrogatoire | L95: Rarement (> ou = à 1 fois tous les 3 mois) | M95: Oui | N95: Absence de formation spécifique sur le syndrome, Sous-estimation des plaintes des patientes | O95: Ostéopathie | P95: Conseils posturaux | Q95: Exercices/Etirements | R95: Repos/Limitation de mouvement | S95: Ceinture de maintien/Support pelvien | T95: Traitements médicamenteux (antalgiques/analgésiques) | U95: 5 | V95: Dès les premiers symptômes | W95: 2 | X95: Retours de patientes, Réduction du coût des séances pour les patientes, Reconnaissance institutionnelle | Y95: Absence de connaissances sur la pratique ostéopathique, Insuffisance de preuves scientifiques, Coût pour les patientes | Z95: Caractère chronique ou aigu des douleurs, Réponse ou non aux autres traitements, Spécialisation de l’ostéopathe en périnatalité, Motivation des patientes pour une prise en charge manuelle complémentaire, Convictions personnelles concernant cette approche thérapeutique | AA95: Non | AB95: Oui | AC95: Oui | AD95: Demande des patientes, Recommandations par d’autres professionnels de santé | AE95: 0 | AF95: 0 | AG95: 0 | AH95: 0 | AI95: 0 | AJ95: 0
A96: Étudiant(e) sage-femme en 5e année | B96: 0 | C96: 0 | D96: 2 | E96: 4 | F96: 2 | G96: Oui | H96: Oui, occasionnellement (> ou = à 1 fois par mois) | I96: Suivi prénatal de grossesse, Douleurs lombaires et/ou pelviennes, Troubles digestifs associés, Post-partum | J96: 4 | K96: Interrogatoire, Examen clinique, En excluant d’autres causes possibles de douleurs pelviennes pendant la grossesse | L96: Fréquemment (> ou = à 1 fois par semaine) | M96: Non | N96: 0 | O96: Repos/Limitation de mouvement | P96: Conseils posturaux | Q96: Exercices/Etirements | R96: Ostéopathie | S96: Traitements médicamenteux (antalgiques/analgésiques) | T96: Ceinture de maintien/Support pelvien | U96: 4 | V96: En cas d’absence de réussite d’autres prises en charge | W96: 1 | X96: Contenus pédagogiques sur les principes ostéopathiques inscrits au parcours académique, Retours de patientes, Preuves scientifiques, Réduction du coût des séances pour les patientes | Y96: Peu de contenus pédagogiques sur les principes ostéopathiques inscrits au parcours académique, Absence de connaissances sur la pratique ostéopathique, Coût pour les patientes, Absence de reconnaissance institutionnelle | Z96: Réponse ou non aux autres traitements, Motivation des patientes pour une prise en charge manuelle complémentaire, Convictions personnelles concernant cette approche thérapeutique, Expérience personnelle antérieure positive ou négative avec l’ostéopathie | AA96: Oui | AB96: Oui | AC96: Sans avis | AD96: Preuves de résultats positifs des traitements ostéopathiques, Demande des patientes, Recommandations par d’autres professionnels de santé, Absence ou inefficacité d’autres solutions thérapeutiques, Encadrement institutionnel et recommandations officielles | AE96: 0 | AF96: 0 | AG96: 0 | AH96: 0 | AI96: 0 | AJ96: 0
A97: Sage-femme diplômé(e) | B97: Plus de 10 ans | C97: Libéral | D97: 4 | E97: 4 | F97: 4 | G97: Oui | H97: Oui, régulièrement (> ou = à 1 fois par semaine) | I97: Douleurs lombaires et/ou pelviennes, Post-partum, Sphère émotionnelle | J97: 4 | K97: Examen clinique | L97: Fréquemment (> ou = à 1 fois par semaine) | M97: Oui | N97: Absence de formation spécifique sur le syndrome, Assimilation du syndrome à des lombalgies non spécifiques | O97: Ostéopathie | P97: Exercices/Etirements | Q97: Conseils posturaux | R97: Traitements médicamenteux (antalgiques/analgésiques) | S97: Ceinture de maintien/Support pelvien | T97: Repos/Limitation de mouvement | U97: 5 | V97: Dès les premiers symptômes | W97: 2 | X97: Contenus pédagogiques sur les principes ostéopathiques inscrits au parcours académique, Retours de patientes, Réduction du coût des séances pour les patientes | Y97: Peu de contenus pédagogiques sur les principes ostéopathiques inscrits au parcours académique | Z97: Motivation des patientes pour une prise en charge manuelle complémentaire, Convictions personnelles concernant cette approche thérapeutique, Expérience personnelle antérieure positive ou négative avec l’ostéopathie | AA97: Non | AB97: Oui | AC97: Oui | AD97: Demande des patientes, Formations sémiologiques supplémentaires des ostéopathes | AE97: 0 | AF97: 0 | AG97: Des fo pnctuelles en osteopathie en maieitique | AH97: 0 | AI97: 0 | AJ97: 0
A98: Sage-femme diplômé(e) | B98: Plus de 10 ans | C98: Libéral | D98: 3 | E98: 4 | F98: 3 | G98: Oui | H98: Oui, régulièrement (> ou = à 1 fois par semaine) | I98: Suivi prénatal de grossesse, Post-partum | J98: 2 | K98: Interrogatoire | L98: Occasionnellement (> ou = à 1 fois par mois) | M98: Oui | N98: Absence de formation spécifique sur le syndrome | O98: Ostéopathie | P98: Exercices/Etirements | Q98: Traitements médicamenteux (antalgiques/analgésiques) | R98: Ceinture de maintien/Support pelvien | S98: Conseils posturaux | T98: Repos/Limitation de mouvement | U98: 5 | V98: Dès les premiers symptômes | W98: 2 | X98: Contenus pédagogiques sur les principes ostéopathiques inscrits au parcours académique, Réduction du coût des séances pour les patientes | Y98: Absence de connaissances sur la pratique ostéopathique, Coût pour les patientes | Z98: Spécialisation de l’ostéopathe en périnatalité | AA98: Oui | AB98: Oui | AC98: Oui | AD98: Preuves de résultats positifs des traitements ostéopathiques | AE98: 0 | AF98: 0 | AG98: 0 | AH98: 0 | AI98: 0 | AJ98: 0
A99: Étudiant(e) sage-femme en 5e année | B99: 0 | C99: 0 | D99: 2 | E99: 3 | F99: 2 | G99: Non | H99: Non | I99: 0 | J99: 3 | K99: Interrogatoire, Examen clinique, En excluant d’autres causes possibles de douleurs pelviennes pendant la grossesse | L99: Fréquemment (> ou = à 1 fois par semaine) | M99: Oui | N99: Absence de formation spécifique sur le syndrome, Assimilation du syndrome à des lombalgies non spécifiques, Sous-estimation des plaintes des patientes | O99: Ceinture de maintien/Support pelvien | P99: Ostéopathie | Q99: Conseils posturaux | R99: Exercices/Etirements | S99: Repos/Limitation de mouvement | T99: Traitements médicamenteux (antalgiques/analgésiques) | U99: 5 | V99: En fin de grossesse | W99: 1 | X99: Contenus pédagogiques sur les principes ostéopathiques inscrits au parcours académique, Réduction du coût des séances pour les patientes, Intégration de l’ostéopathie dans les structures de santé | Y99: Peu de contenus pédagogiques sur les principes ostéopathiques inscrits au parcours académique, Insuffisance de collaboration interprofessionnelle avec des ostéopathes, Coût pour les patientes | Z99: Caractère chronique ou aigu des douleurs, Spécialisation de l’ostéopathe en périnatalité, Motivation des patientes pour une prise en charge manuelle complémentaire, Disponibilité et/ou accessibilité d’ostéopathes dans votre réseau, Convictions personnelles concernant cette approche thérapeutique | AA99: Oui | AB99: Oui | AC99: Oui | AD99: Formations sémiologiques supplémentaires des ostéopathes, Recommandations par d’autres professionnels de santé, Mise en place de protocoles règlementés, Encadrement institutionnel et recommandations officielles | AE99: 0 | AF99: 0 | AG99: 0 | AH99: 0 | AI99: 0 | AJ99: 0
A100: Sage-femme diplômé(e) | B100: Plus de 10 ans | C100: Libéral | D100: 3 | E100: 5 | F100: 4 | G100: Oui | H100: Oui, occasionnellement (> ou = à 1 fois par mois) | I100: Douleurs lombaires et/ou pelviennes, Troubles digestifs associés, Post-partum, Allaitement | J100: 3 | K100: Interrogatoire, En excluant d’autres causes possibles de douleurs pelviennes pendant la grossesse | L100: Occasionnellement (> ou = à 1 fois par mois) | M100: Sans avis | N100: Assimilation du syndrome à des lombalgies non spécifiques, Sous-estimation des plaintes des patientes, Difficultés d’accès aux thérapies non médicamenteuses | O100: Ceinture de maintien/Support pelvien | P100: Ostéopathie | Q100: Exercices/Etirements | R100: Repos/Limitation de mouvement | S100: Traitements médicamenteux (antalgiques/analgésiques) | T100: Conseils posturaux | U100: 5 | V100: Dès les premiers symptômes | W100: 4 | X100: Retours de patientes | Y100: Coût pour les patientes, Absence de reconnaissance institutionnelle | Z100: Caractère chronique ou aigu des douleurs, Réponse ou non aux autres traitements, Motivation des patientes pour une prise en charge manuelle complémentaire, Convictions personnelles concernant cette approche thérapeutique, Expérience personnelle antérieure positive ou négative avec l’ostéopathie | AA100: Non | AB100: Oui | AC100: Oui | AD100: Demande des patientes, Absence ou inefficacité d’autres solutions thérapeutiques | AE100: 0 | AF100: 0 | AG100: Nous avons des ostéo dans notre cabinet et nous avons toujours eu des retours positifs de leurs prises en charges. | AH100: Collaboration interprofessionnelle, Favorable à l'intégration de l'ostéopathie, Efficacité perçue | AI100: 0 | AJ100: 0
...

Sheet Q1
A3: Êtes-vous | B3: Count of Êtes-vous | E3: =A3&" ? " -> Êtes-vous ?
A4: Étudiant(e) sage-femme en 5e année | B4: 61 | D4: =A4&" "&"(n="&B4&")" -> Étudiant(e) sage-femme en 5e année (n=61) | E4: =B4/B6 -> 0.40397351
A5: Sage-femme diplômé(e) | B5: 90 | D5: =A5&" "&"(n="&B5&")" -> Sage-femme diplômé(e) (n=90) | E5: =B5/B6 -> 0.59602649
A6: Total général | B6: 151 | E6: =SUM(E4:E5) -> 1

Sheet Q2
A3: Étiquettes de lignes | B3: Nombre de Si vous avez coché sage-femme diplômé(e), depuis combien de temps exercez-vous ? | E3: =Feuil1!B1 -> Q2 : Si vous avez coché sage-femme diplômé(e), depuis combien de temps exercez-vous ?
A4: Moins de 2 ans | B4: 9 | D4: =A4&" "&"(n="&B4&")" -> Moins de 2 ans (n=9) | E4: =B4/B$8 -> 0.1
A5: 2 à 5 ans | B5: 7 | D5: =A5&" "&"(n="&B5&")" -> 2 à 5 ans (n=7) | E5: =B5/B$8 -> 0.077777778
A6: 5 à 10 ans | B6: 15 | D6: =A6&" "&"(n="&B6&")" -> 5 à 10 ans (n=15) | E6: =B6/B$8 -> 0.16666667
A7: Plus de 10 ans | B7: 59 | D7: =A7&" "&"(n="&B7&")" -> Plus de 10 ans (n=59) | E7: =B7/B$8 -> 0.65555556
A8: Total général | B8: 90 | E8: =SUM(E4:E7) -> 1

Sheet Q3
A3: Dans quelle structure exercez-vous ? | B3: Count of Dans quelle structure exercez-vous ? | E3: =A3 -> Dans quelle structure exercez-vous ?
A4: Mixte | B4: 3 | D4: =A4&" "&"(n="&B4&")" -> Mixte (n=3) | E4: =B4/B$7 -> 0.033333333
A5: Hospitalier | B5: 57 | D5: =A5&" "&"(n="&B5&")" -> Hospitalier (n=57) | E5: =B5/B$7 -> 0.63333333
A6: Libéral | B6: 30 | D6: =A6&" "&"(n="&B6&")" -> Libéral (n=30) | E6: =B6/B$7 -> 0.33333333
A7: Total général | B7: 90 | E7: =SUM(E4:E6) -> 1

Sheet Q4
A3: Somme de %
A4: Sur une échelle de 1 à 5, comment évalueriez-vous votre niveau de connaissance de l’ostéopathie ? | B4: Total
A5: 1 = Aucune connaissance (n=22) | B5: 0.14569536
A6: 2 = Peu de connaissances (n=53) | B6: 0.35099338
A7: 3 = Connaissances générales (n=45) | B7: 0.29801325
A8: 4 = Bonnes connaissances (n=28) | B8: 0.18543046
A9: 5 = Très bonnes connaissances (n=3) | B9: 0.01986755
A10: Total général | B10: 1

Sheet TQ4
A1: Sur une échelle de 1 à 5, comment évalueriez-vous votre niveau de connaissance de l’ostéopathie ? | C1: Sur une échelle de 1 à 5, comment évalueriez-vous votre niveau de connaissance de l’ostéopathie ? | D1: Total | F1: =C1 -> Sur une échelle de 1 à 5, comment évalueriez-vous votre niveau de connaissance de l’ostéopathie ? | G1: %
A2: 4 | C2: 1 = Aucune connaissance | D2: =COUNTIF(A2:A152,"1") -> 22 | F2: =C2&" "&"(n="&D2&")" -> 1 = Aucune connaissance (n=22) | G2: =D2/SUM(D$2:D$6) -> 0.14569536
A3: 2 | C3: 2 = Peu de connaissances | D3: =COUNTIF(A2:A152,"2") -> 53 | F3: =C3&" "&"(n="&D3&")" -> 2 = Peu de connaissances (n=53) | G3: =D3/SUM(D$2:D$6) -> 0.35099338
A4: 2 | C4: 3 = Connaissances générales | D4: =COUNTIF(A2:A152,"3") -> 45 | F4: =C4&" "&"(n="&D4&")" -> 3 = Connaissances générales (n=45) | G4: =D4/SUM(D$2:D$6) -> 0.29801325
A5: 1 | C5: 4 = Bonnes connaissances | D5: =COUNTIF(A2:A152,"4") -> 28 | F5: =C5&" "&"(n="&D5&")" -> 4 = Bonnes connaissances (n=28) | G5: =D5/SUM(D$2:D$6) -> 0.18543046
A6: 1 | C6: 5 = Très bonnes connaissances | D6: =COUNTIF(A2:A152,"5") -> 3 | F6: =C6&" "&"(n="&D6&")" -> 5 = Très bonnes connaissances (n=3) | G6: =D6/SUM(D$2:D$6) -> 0.01986755
A7: 4
A8: 1 | D8: =SUM(D2:D6) -> 151 | G8: =SUM(G2:G6) -> 1
A9: 2
A10: 3
A11: 1
A12: 3
A13: 1
A14: 4
A15: 4
A16: 3
A17: 2
A18: 3
A19: 2
A20: 1
... A152: 2

Sheet Q5
A3: Somme de %
A4: Quelle est selon vous, la place de l’ostéopathie dans la prise en charge globale de la femme enceinte ? | B4: Total
A5: 1 = Sans intérêt (n=3) | B5: 0.01986755
A6: 2 = Peu utile (n=9) | B6: 0.059602649
A7: 3 = Utilité modérée (n=41) | B7: 0.27152318
A8: 4 = Utile (n=60) | B8: 0.39735099
A9: 5 = Très utile (n=38) | B9: 0.25165563
A10: Total général | B10: 1

Sheet TQ5
A1: Quelle est selon vous, la place de l’ostéopathie dans la prise en charge globale de la femme enceinte ? | C1: Quelle est selon vous, la place de l’ostéopathie dans la prise en charge globale de la femme enceinte ? | D1: Total | F1: =C1 -> Quelle est selon vous, la place de l’ostéopathie dans la prise en charge globale de la femme enceinte ? | G1: %
A2: 4 | C2: 1 = Sans intérêt | D2: =COUNTIF(A2:A152,"1") -> 3 | F2: =C2&" "&"(n="&D2&")" -> 1 = Sans intérêt (n=3) | G2: =D2/SUM(D$2:D$6) -> 0.01986755
A3: 3 | C3: 2 = Peu utile | D3: =COUNTIF(A2:A152,"2") -> 9 | F3: =C3&" "&"(n="&D3&")" -> 2 = Peu utile (n=9) | G3: =D3/SUM(D$2:D$6) -> 0.059602649
A4: 3 | C4: 3 = Utilité modérée | D4: =COUNTIF(A2:A152,"3") -> 41 | F4: =C4&" "&"(n="&D4&")" -> 3 = Utilité modérée (n=41) | G4: =D4/SUM(D$2:D$6) -> 0.27152318
A5: 4 | C5: 4 = Utile | D5: =COUNTIF(A2:A152,"4") -> 60 | F5: =C5&" "&"(n="&D5&")" -> 4 = Utile (n=60) | G5: =D5/SUM(D$2:D$6) -> 0.39735099
A6: 3 | C6: 5 = Très utile | D6: =COUNTIF(A2:A152,"5") -> 38 | F6: =C6&" "&"(n="&D6&")" -> 5 = Très utile (n=38) | G6: =D6/SUM(D$2:D$6) -> 0.25165563
A7: 4
A8: 3 | D8: =SUM(D2:D6) -> 151 | G8: =SUM(G2:G6) -> 1
A9: 4
A10: 4
A11: 3
A12: 4
A13: 3
A14: 5
A15: 4
A16: 5
A17: 3
A18: 3
A19: 3
A20: 4
... A152: 4

Sheet Q6
A3: Somme de %
A4: Vous sentez-vous suffisamment informé(e) sur l’ostéopathie et ses indications durant la grossesse ? | B4: Total
A5: 1 = Non pas du tout (n=26) | B5: 0.17218543
A6: 2 = Plutôt non (n=42) | B6: 0.2781457
A7: 3 = Moyennement (n=37) | B7: 0.24503311
A8: 4 = Plutôt oui (n=40) | B8: 0.26490066
A9: 5 = Oui tout à fait (n=6) | B9: 0.039735099
A10: Total général | B10: 1

Sheet TQ6
A1: Vous sentez-vous suffisamment informé(e) sur l’ostéopathie et ses indications durant la grossesse ? | C1: Vous sentez-vous suffisamment informé(e) sur l’ostéopathie et ses indications durant la grossesse ? | D1: Total | F1: =C1 -> Vous sentez-vous suffisamment informé(e) sur l’ostéopathie et ses indications durant la grossesse ? | G1: %
A2: 3 | C2: 1 = Non pas du tout | D2: =COUNTIF(A2:A152,"1") -> 26 | F2: =C2&" "&"(n="&D2&")" -> 1 = Non pas du tout (n=26) | G2: =D2/SUM(D$2:D$6) -> 0.17218543
A3: 3 | C3: 2 = Plutôt non | D3: =COUNTIF(A2:A152,"2") -> 42 | F3: =C3&" "&"(n="&D3&")" -> 2 = Plutôt non (n=42) | G3: =D3/SUM(D$2:D$6) -> 0.2781457
A4: 2 | C4: 3 = Moyennement | D4: =COUNTIF(A2:A152,"3") -> 37 | F4: =C4&" "&"(n="&D4&")" -> 3 = Moyennement (n=37) | G4: =D4/SUM(D$2:D$6) -> 0.24503311
A5: 2 | C5: 4 = Plutôt oui | D5: =COUNTIF(A2:A152,"4") -> 40 | F5: =C5&" "&"(n="&D5&")" -> 4 = Plutôt oui (n=40) | G5: =D5/SUM(D$2:D$6) -> 0.26490066
A6: 2 | C6: 5 = Oui tout à fait | D6: =COUNTIF(A2:A152,"5") -> 6 | F6: =C6&" "&"(n="&D6&")" -> 5 = Oui tout à fait (n=6) | G6: =D6/SUM(D$2:D$6) -> 0.039735099
A7: 4
A8: 1 | D8: =SUM(D2:D6) -> 151 | G8: =SUM(G2:G6) -> 1
A9: 1
A10: 4
A11: 3
A12: 4
A13: 1
A14: 3
A15: 4
A16: 4
A17: 2
A18: 3
A19: 3
A20: 2
... A152: 2

Sheet Q7
A3: Étiquettes de lignes | B3: Nombre de Avez-vous accès, au sein de votre structure, à un réseau d’ostéopathes vers lesquels orienter vos patientes ? | E3: =Feuil1!G1 -> Q7 : Avez-vous accès, au sein de votre structure, à un réseau d’ostéopathes vers lesquels orienter vos patientes ?
A4: Non | B4: 75 | D4: =A4&" "&"(n="&B4&")" -> Non (n=75) | E4: =B4/B$7 -> 0.49668874
A5: Oui | B5: 55 | D5: =A5&" "&"(n="&B5&")" -> Oui (n=55) | E5: =B5/B$7 -> 0.36423841
A6: Sans avis | B6: 21 | D6: =A6&" "&"(n="&B6&")" -> Sans avis (n=21) | E6: =B6/B$7 -> 0.13907285
A7: Total général | B7: 151 | E7: =SUM(E4:E6) -> 1

Sheet Q8
A3: Étiquettes de lignes | B3: Nombre de La collaboration avec un(e) ostéopathe fait-elle partie intégrante de votre pratique ? | E3: =Feuil1!H1 -> Q8 : La collaboration avec un(e) ostéopathe fait-elle partie intégrante de votre pratique ?
A4: Non | B4: 44 | D4: =A4&" "&"(n="&B4&")" -> Non (n=44) | E4: =B4/B$8 -> 0.29139073
A5: Oui, occasionnellement (> ou = à 1 fois par mois) | B5: 44 | D5: =A5&" "&"(n="&B5&")" -> Oui, occasionnellement (> ou = à 1 fois par mois) (n=44) | E5: =B5/B$8 -> 0.29139073
A6: Oui, rarement (< à 1 fois par mois) | B6: 27 | D6: =A6&" "&"(n="&B6&")" -> Oui, rarement (< à 1 fois par mois) (n=27) | E6: =B6/B$8 -> 0.17880795
A7: Oui, régulièrement (> ou = à 1 fois par semaine) | B7: 36 | D7: =A7&" "&"(n="&B7&")" -> Oui, régulièrement (> ou = à 1 fois par semaine) (n=36) | E7: =B7/B$8 -> 0.2384106
A8: Total général | B8: 151 | E8: =SUM(E4:E7) -> 1

Sheet Q9
A3: Somme de %
A4: Si oui, dans quel(s) cadre(s) ? | B4: Total
A5: Allaitement (n=20) | B5: 0.0625
A6: Douleurs lombaires et/ou pelviennes (n=97) | B6: 0.303125
A7: Fertilité (n=11) | B7: 0.034375
A8: Nouveau-né (n=4) | B8: 0.0125
A9: Post-partum (n=85) | B9: 0.265625
A10: Préparation à l'accouchement (n=21) | B10: 0.065625
A11: Sphère émotionnelle (n=10) | B11: 0.03125
A12: Suivi prénatal de grossesse (n=51) | B12: 0.159375
A13: Troubles digestifs associés (n=21) | B13: 0.065625
A14: Total général | B14: 1

Sheet TQ9
A1: Si oui, dans quel(s) cadre(s) ? | C1: =$A1 -> Si oui, dans quel(s) cadre(s) ? | D1: Total | F1: =$A1 -> Si oui, dans quel(s) cadre(s) ? | G1: %
A2: Douleurs lombaires et/ou pelviennes, Post-partum, Allaitement, Nouveau-né | C2: Suivi prénatal de grossesse | D2: =COUNTIF($A$2:$A$152,"*Suivi prénatal de grossesse*") -> 51 | F2: =C2&" "&"(n="&D2&")" -> Suivi prénatal de grossesse (n=51) | G2: =D2/SUM(D$2:D$10) -> 0.159375
A3: Suivi prénatal de grossesse, Douleurs lombaires et/ou pelviennes | C3: Préparation à l'accouchement | D3: =COUNTIF($A$2:$A$152,"*Préparation à l’accouchement*") -> 21 | F3: =C3&" "&"(n="&D3&")" -> Préparation à l'accouchement (n=21) | G3: =D3/SUM(D$2:D$10) -> 0.065625
A4: 0 | C4: Douleurs lombaires et/ou pelviennes | D4: =COUNTIF($A$2:$A$152,"*Douleurs lombaires et/ou pelviennes*") -> 97 | F4: =C4&" "&"(n="&D4&")" -> Douleurs lombaires et/ou pelviennes (n=97) | G4: =D4/SUM(D$2:D$10) -> 0.303125
A5: Douleurs lombaires et/ou pelviennes | C5: Troubles digestifs associés | D5: =COUNTIF($A$2:$A$152,"*Troubles digestifs associés*") -> 21 | F5: =C5&" "&"(n="&D5&")" -> Troubles digestifs associés (n=21) | G5: =D5/SUM(D$2:D$10) -> 0.065625
A6: Douleurs lombaires et/ou pelviennes, Post-partum | C6: Post-partum | D6: =COUNTIF($A$2:$A$152,"*Post-partum*") -> 85 | F6: =C6&" "&"(n="&D6&")" -> Post-partum (n=85) | G6: =D6/SUM(D$2:D$10) -> 0.265625
A7: Suivi prénatal de grossesse, Douleurs lombaires et/ou pelviennes, Post-partum | C7: Fertilité | D7: =COUNTIF($A$2:$A$152,"*Fertilité*") -> 11 | F7: =C7&" "&"(n="&D7&")" -> Fertilité (n=11) | G7: =D7/SUM(D$2:D$10) -> 0.034375
A8: Douleurs lombaires et/ou pelviennes, Nouveau-né | C8: Allaitement | D8: =COUNTIF($A$2:$A$152,"*Allaitement*") -> 20 | F8: =C8&" "&"(n="&D8&")" -> Allaitement (n=20) | G8: =D8/SUM(D$2:D$10) -> 0.0625
A9: Douleurs lombaires et/ou pelviennes | C9: Sphère émotionnelle | D9: =COUNTIF($A$2:$A$152,"*Sphère émotionnelle*") -> 10 | F9: =C9&" "&"(n="&D9&")" -> Sphère émotionnelle (n=10) | G9: =D9/SUM(D$2:D$10) -> 0.03125
A10: Douleurs lombaires et/ou pelviennes, Troubles digestifs associés, Post-partum, Allaitement | C10: Nouveau-né | D10: =COUNTIF($A$2:$A$152,"*Nouveau-né*") -> 4 | F10: =C10&" "&"(n="&D10&")" -> Nouveau-né (n=4) | G10: =D10/SUM(D$2:D$10) -> 0.0125
A11: Douleurs lombaires et/ou pelviennes, Post-partum, Allaitement
A12: Suivi prénatal de grossesse, Préparation à l’accouchement, Douleurs lombaires et/ou pelviennes, Post-partum | D12: =SUM(D2:D10) -> 320 | G12: =SUM(G2:G10) -> 1
A13: 0
A14: Suivi prénatal de grossesse, Douleurs lombaires et/ou pelviennes, Post-partum
A15: Douleurs lombaires et/ou pelviennes, Post-partum
A16: Préparation à l’accouchement, Post-partum
A17: Post-partum
A18: Douleurs lombaires et/ou pelviennes, Post-partum, Fertilité
A19: Douleurs lombaires et/ou pelviennes, Post-partum
A20: 0
A21: 0
A22: 0
A23: 0
A24: Douleurs lombaires et/ou pelviennes, Post-partum, Sphère émotionnelle
A25: Douleurs lombaires et/ou pelviennes, Post-partum
A26: Suivi prénatal de grossesse, Préparation à l’accouchement, Douleurs lombaires et/ou pelviennes, Post-partum
A27: 0
A28: Suivi prénatal de grossesse, Douleurs lombaires et/ou pelviennes, Post-partum, Allaitement
A29: Suivi prénatal de grossesse, Douleurs lombaires et/ou pelviennes, Post-partum
A30: Suivi prénatal de grossesse, Préparation à l’accouchement, Douleurs lombaires et/ou pelviennes, Troubles digestifs associés, Post-partum, Fertilité, Allaitement, Sphère émotionnelle
A31: 0
A32: Suivi prénatal de grossesse, Douleurs lombaires et/ou pelviennes, Post-partum, Fertilité
A33: 0
A34: Suivi prénatal de grossesse, Préparation à l’accouchement, Douleurs lombaires et/ou pelviennes, Troubles digestifs associés, Post-partum
A35: Suivi prénatal de grossesse, Douleurs lombaires et/ou pelviennes, Troubles digestifs associés, Post-partum, Allaitement
A36: Suivi prénatal de grossesse, Préparation à l’accouchement, Douleurs lombaires et/ou pelviennes, Troubles digestifs associés, Post-partum, Fertilité, Allaitement
A37: Suivi prénatal de grossesse, Préparation à l’accouchement, Douleurs lombaires et/ou pelviennes, Allaitement
A38: 0
A39: Suivi prénatal de grossesse, Préparation à l’accouchement, Douleurs lombaires et/ou pelviennes, Troubles digestifs associés, Post-partum, Allaitement
A40: Suivi prénatal de grossesse, Douleurs lombaires et/ou pelviennes, Post-partum
A41: Suivi prénatal de grossesse, Douleurs lombaires et/ou pelviennes, Post-partum, Allaitement
A42: 0
A43: Douleurs lombaires et/ou pelviennes, Sphère émotionnelle
A44: 0
A45: 0
A46: Suivi prénatal de grossesse, Préparation à l’accouchement, Nouveau-né
A47: Douleurs lombaires et/ou pelviennes, Post-partum
A48: 0
A49: Suivi prénatal de grossesse, Douleurs lombaires et/ou pelviennes, Post-partum
A50: Suivi prénatal de grossesse, Douleurs lombaires et/ou pelviennes, Troubles digestifs associés, Post-partum, Fertilité
A51: Douleurs lombaires et/ou pelviennes, Post-partum
A52: Douleurs lombaires et/ou pelviennes
A53: Douleurs lombaires et/ou pelviennes, Post-partum
A54: Douleurs lombaires et/ou pelviennes
A55: 0
A56: Douleurs lombaires et/ou pelviennes, Post-partum
A57: Suivi prénatal de grossesse, Douleurs lombaires et/ou pelviennes, Post-partum
A58: Suivi prénatal de grossesse, Douleurs lombaires et/ou pelviennes, Post-partum
A59: Douleurs lombaires et/ou pelviennes
A60: 0
A61: Suivi prénatal de grossesse, Fertilité
A62: Suivi prénatal de grossesse, Douleurs lombaires et/ou pelviennes, Post-partum
A63: Suivi prénatal de grossesse, Douleurs lombaires et/ou pelviennes, Post-partum
A64: 0
A65: Douleurs lombaires et/ou pelviennes
A66: Douleurs lombaires et/ou pelviennes, Post-partum
A67: 0
A68: Suivi prénatal de grossesse, Préparation à l’accouchement, Douleurs lombaires et/ou pelviennes, Troubles digestifs associés, Post-partum
A69: 0
A70: Douleurs lombaires et/ou pelviennes, Post-partum
A71: Douleurs lombaires et/ou pelviennes, Post-partum
A72: Douleurs lombaires et/ou pelviennes, Post-partum
A73: Suivi prénatal de grossesse, Préparation à l’accouchement, Douleurs lombaires et/ou pelviennes, Troubles digestifs associés, Post-partum, Fertilité, Allaitement, Sphère émotionnelle
A74: Douleurs lombaires et/ou pelviennes, Post-partum
A75: Suivi prénatal de grossesse, Préparation à l’accouchement, Douleurs lombaires et/ou pelviennes, Troubles digestifs associés, Post-partum, Allaitement
A76: 0
A77: Douleurs lombaires et/ou pelviennes
A78: Douleurs lombaires et/ou pelviennes
A79: Post-partum
A80: Sphère émotionnelle
A81: 0
A82: Douleurs lombaires et/ou pelviennes, Troubles digestifs associés, Post-partum
A83: Douleurs lombaires et/ou pelviennes, Post-partum
A84: Douleurs lombaires et/ou pelviennes
A85: 0
A86: 0
A87: Suivi prénatal de grossesse, Douleurs lombaires et/ou pelviennes, Post-partum
A88: Douleurs lombaires et/ou pelviennes, Troubles digestifs associés
A89: Douleurs lombaires et/ou pelviennes, Post-partum
A90: Douleurs lombaires et/ou pelviennes, Post-partum
A91: Suivi prénatal de grossesse, Douleurs lombaires et/ou pelviennes, Post-partum, Allaitement
A92: Suivi prénatal de grossesse, Douleurs lombaires et/ou pelviennes, Post-partum, Allaitement
A93: 0
A94: Suivi prénatal de grossesse, Douleurs lombaires et/ou pelviennes, Troubles digestifs associés, Post-partum
A95: Suivi prénatal de grossesse, Douleurs lombaires et/ou pelviennes, Troubles digestifs associés, Post-partum, Allaitement
A96: Suivi prénatal de grossesse, Douleurs lombaires et/ou pelviennes, Troubles digestifs associés, Post-partum
A97: Douleurs lombaires et/ou pelviennes, Post-partum, Sphère émotionnelle
A98: Suivi prénatal de grossesse, Post-partum
A99: 0
A100: Douleurs lombaires et/ou pelviennes, Troubles digestifs associés, Post-partum, Allaitement
...

Sheet Q10
A3: Somme de %
A4: Comment estimez-vous vos connaissances concernant le syndrome de Lacomme (douleurs ligamentaires lombo-pelviennes de grossesse) ? | B4: Total
A5: 1 = Aucunes connaissances (n=5) | B5: 0.033112583
A6: 2 = Peu de connaissances (n=33) | B6: 0.21854305
A7: 3 = Connaissances générales (n=52) | B7: 0.34437086
A8: 4 = Bonnes connaissances (n=50) | B8: 0.33112583
A9: 5 = Très bonnes connaissances (n=11) | B9: 0.072847682
A10: Total général | B10: 1

Sheet TQ10
A1: Comment estimez-vous vos connaissances concernant le syndrome de Lacomme (douleurs ligamentaires lombo-pelviennes de grossesse) ? | C1: Comment estimez-vous vos connaissances concernant le syndrome de Lacomme (douleurs ligamentaires lombo-pelviennes de grossesse) ? | D1: Total | F1: =$A1 -> Comment estimez-vous vos connaissances concernant le syndrome de Lacomme (douleurs ligamentaires lombo-pelviennes de grossesse) ? | G1: %
A2: 4 | C2: 1 = Aucunes connaissances | D2: =COUNTIF(A2:A152,"1") -> 5 | F2: =C2&" "&"(n="&D2&")" -> 1 = Aucunes connaissances (n=5) | G2: =D2/SUM(D$2:D$6) -> 0.033112583
A3: 2 | C3: 2 = Peu de connaissances | D3: =COUNTIF(A2:A152,"2") -> 33 | F3: =C3&" "&"(n="&D3&")" -> 2 = Peu de connaissances (n=33) | G3: =D3/SUM(D$2:D$6) -> 0.21854305
A4: 4 | C4: 3 = Connaissances générales | D4: =COUNTIF(A2:A152,"3") -> 52 | F4: =C4&" "&"(n="&D4&")" -> 3 = Connaissances générales (n=52) | G4: =D4/SUM(D$2:D$6) -> 0.34437086
A5: 2 | C5: 4 = Bonnes connaissances | D5: =COUNTIF(A2:A152,"4") -> 50 | F5: =C5&" "&"(n="&D5&")" -> 4 = Bonnes connaissances (n=50) | G5: =D5/SUM(D$2:D$6) -> 0.33112583
A6: 4 | C6: 5 = Très bonnes connaissances | D6: =COUNTIF(A2:A152,"5") -> 11 | F6: =C6&" "&"(n="&D6&")" -> 5 = Très bonnes connaissances (n=11) | G6: =D6/SUM(D$2:D$6) -> 0.072847682
A7: 3
A8: 2 | D8: =SUM(D2:D6) -> 151 | G8: =SUM(G2:G6) -> 1
A9: 4
A10: 4
A11: 2
A12: 2
A13: 2
A14: 4
A15: 4
A16: 5
A17: 3
A18: 4
A19: 5
A20: 2
... A152: 4

Sheet Q11
A3: Somme de %
A4: Comment identifiez-vous ce syndrome dans votre pratique ? | B4: Total
A5: Recours aux examens complémentaires (n=2) | B5: 0.0058823529
A6: Démarche de la patiente (n=1) | B6: 0.0029411765
A7: En excluant d’autres causes possibles de douleurs pelviennes pendant la grossesse (n=105) | B7: 0.30882353
A8: Examen clinique (n=89) | B8: 0.26176471
A9: Interrogatoire (n=143) | B9: 0.42058824
A10: Total général | B10: 1

Sheet TQ11
A1: Comment identifiez-vous ce syndrome dans votre pratique ? | C1: Comment identifiez-vous ce syndrome dans votre pratique ? | D1: Total | F1: =$A1 -> Comment identifiez-vous ce syndrome dans votre pratique ? | G1: %
A2: Interrogatoire | C2: Interrogatoire | D2: =COUNTIF($A$2:$A$152,"*Interrogatoire*") -> 143 | F2: =C2&" "&"(n="&D2&")" -> Interrogatoire (n=143) | G2: =D2/SUM(D$2:D$6) -> 0.42058824
A3: Interrogatoire | C3: Examen clinique | D3: =COUNTIF($A$2:$A$152,"*Examen clinique*") -> 89 | F3: =C3&" "&"(n="&D3&")" -> Examen clinique (n=89) | G3: =D3/SUM(D$2:D$6) -> 0.26176471
A4: Interrogatoire, Examen clinique, En excluant d’autres causes possibles de douleurs pelviennes pendant la grossesse | C4: Recours aux examens complémentaires | D4: =COUNTIF($A$2:$A$152,"*Recours aux examens complémentaires*") -> 2 | F4: =C4&" "&"(n="&D4&")" -> Recours aux examens complémentaires (n=2) | G4: =D4/SUM(D$2:D$6) -> 0.0058823529
A5: Interrogatoire, Examen clinique | C5: En excluant d’autres causes possibles de douleurs pelviennes pendant la grossesse | D5: =COUNTIF($A$2:$A$152,"*En excluant d’autres causes possibles de douleurs pelviennes pendant la grossesse*") -> 105 | F5: =C5&" "&"(n="&D5&")" -> En excluant d’autres causes possibles de douleurs pelviennes pendant la grossesse (n=105) | G5: =D5/SUM(D$2:D$6) -> 0.30882353
A6: Interrogatoire, Examen clinique, En excluant d’autres causes possibles de douleurs pelviennes pendant la grossesse | C6: Démarche de la patiente | D6: =COUNTIF($A$2:$A$152,"*Démarche de la patiente*") -> 1 | F6: =C6&" "&"(n="&D6&")" -> Démarche de la patiente (n=1) | G6: =D6/SUM(D$2:D$6) -> 0.0029411765
A7: Interrogatoire, Examen clinique, En excluant d’autres causes possibles de douleurs pelviennes pendant la grossesse
A8: Interrogatoire, En excluant d’autres causes possibles de douleurs pelviennes pendant la grossesse | D8: =SUM(D2:D6) -> 340 | G8: =SUM(G2:G6) -> 1
A9: Interrogatoire, Examen clinique, En excluant d’autres causes possibles de douleurs pelviennes pendant la grossesse
A10: Interrogatoire, Examen clinique, En excluant d’autres causes possibles de douleurs pelviennes pendant la grossesse
A11: Interrogatoire, En excluant d’autres causes possibles de douleurs pelviennes pendant la grossesse
A12: Interrogatoire, Examen clinique, En excluant d’autres causes possibles de douleurs pelviennes pendant la grossesse
A13: Interrogatoire, Examen clinique, En excluant d’autres causes possibles de douleurs pelviennes pendant la grossesse
A14: Interrogatoire, En excluant d’autres causes possibles de douleurs pelviennes pendant la grossesse
A15: Interrogatoire, Examen clinique
A16: Interrogatoire, Examen clinique
A17: Interrogatoire, Examen clinique
A18: Interrogatoire, Examen clinique, En excluant d’autres causes possibles de douleurs pelviennes pendant la grossesse
A19: Interrogatoire, Examen clinique
A20: En excluant d’autres causes possibles de douleurs pelviennes pendant la grossesse
... A152: Interrogatoire, Examen clinique, En excluant d’autres causes possibles de douleurs pelviennes pendant la grossesse

Sheet Q12
A3: Étiquettes de lignes | B3: Nombre de A quelle fréquence rencontrez-vous des patientes présentant un syndrome de Lacomme ? | E3: =Feuil1!L1 -> Q12 : A quelle fréquence rencontrez-vous des patientes présentant un syndrome de Lacomme ?
A4: A chaque suivi | B4: 1 | D4: =A4&" "&"(n="&B4&")" -> A chaque suivi (n=1) | E4: =B4/B$9 -> 0.0067114094
A5: Fréquemment (> ou = à 1 fois par semaine) | B5: 67 | D5: =A5&" "&"(n="&B5&")" -> Fréquemment (> ou = à 1 fois par semaine) (n=67) | E5: =B5/B$9 -> 0.44966443
A6: Occasionnellement (> ou = à 1 fois par mois) | B6: 55 | D6: =A6&" "&"(n="&B6&")" -> Occasionnellement (> ou = à 1 fois par mois) (n=55) | E6: =B6/B$9 -> 0.36912752
A7: Rarement (> ou = à 1 fois tous les 3 mois) | B7: 23 | D7: =A7&" "&"(n="&B7&")" -> Rarement (> ou = à 1 fois tous les 3 mois) (n=23) | E7: =B7/B$9 -> 0.15436242
A8: Jamais | B8: 3 | D8: =A8&" "&"(n="&B8&")" -> Jamais (n=3) | E8: =B8/B$9 -> 0.020134228
A9: Total général | B9: 149 | E9: =SUM(E4:E8) -> 1

Sheet Q13
A3: Étiquettes de lignes | B3: Nombre de Estimez-vous qu’il y a un retard diagnostic à la prise en charge de ce syndrome ? | E3: =Feuil1!M1 -> Q13 : Estimez-vous qu’il y a un retard diagnostic à la prise en charge de ce syndrome ?
A4: Non | B4: 33 | D4: =A4&" "&"(n="&B4&")" -> Non (n=33) | E4: =B4/B$7 -> 0.21854305
A5: Oui | B5: 75 | D5: =A5&" "&"(n="&B5&")" -> Oui (n=75) | E5: =B5/B$7 -> 0.49668874
A6: Sans avis | B6: 43 | D6: =A6&" "&"(n="&B6&")" -> Sans avis (n=43) | E6: =B6/B$7 -> 0.28476821
A7: Total général | B7: 151 | E7: =SUM(E4:E6) -> 1

Sheet Q14
A3: Somme de %
A4: Si oui, quelles sont les principales raisons de ce retard diagnostic ? | B4: Total
A5: Absence de recommandations professionnelles claires (n=63) | B5: 0.46666667
A6: Assimilation du syndrome à des lombalgies non spécifiques (n=54) | B6: 0.2
A7: Difficultés d’accès aux thérapies non médicamenteuses (n=31) | B7: 0.11481481
A8: Insuffisance d'examen clinique spécifique (n=1) | B8: 0.0037037037
A9: Sous-estimation des plaintes des patientes (n=58) | B9: 0.21481481
A10: Total général | B10: 1

Sheet TQ14
A1: Si oui, quelles sont les principales raisons de ce retard diagnostic ? | C1: Si oui, quelles sont les principales raisons de ce retard diagnostic ? | D1: Total | F1: =$A1 -> Si oui, quelles sont les principales raisons de ce retard diagnostic ? | G1: %
A2: Absence de recommandations professionnelles claires | C2: Absence de recommandations professionnelles claires | D2: =COUNTIF($A$2:$A$152,"*Absence de recommandations professionnelles claires*") -> 63 | F2: =C2&" "&"(n="&D2&")" -> Absence de recommandations professionnelles claires (n=63) | G2: =D2/SUM(D$2:D$7) -> 0.23333333
A3: 0 | C3: Assimilation du syndrome à des lombalgies non spécifiques | D3: =COUNTIF($A$2:$A$152,"*Assimilation du syndrome à des lombalgies non spécifiques*") -> 54 | F3: =C3&" "&"(n="&D3&")" -> Assimilation du syndrome à des lombalgies non spécifiques (n=54) | G3: =D3/SUM(D$2:D$7) -> 0.2
A4: Absence de formation spécifique sur le syndrome, Assimilation du syndrome à des lombalgies non spécifiques | C4: Sous-estimation des plaintes des patientes | D4: =COUNTIF($A$2:$A$152,"*Sous-estimation des plaintes des patientes*") -> 58 | F4: =C4&" "&"(n="&D4&")" -> Sous-estimation des plaintes des patientes (n=58) | G4: =D4/SUM(D$2:D$7) -> 0.21481481
A5: Sous-estimation des plaintes des patientes | C5: Difficultés d’accès aux thérapies non médicamenteuses | D5: =COUNTIF($A$2:$A$152,"*Difficultés d’accès aux thérapies non médicamenteuses*") -> 31 | F5: =C5&" "&"(n="&D5&")" -> Difficultés d’accès aux thérapies non médicamenteuses (n=31) | G5: =D5/SUM(D$2:D$7) -> 0.11481481
A6: Absence de formation spécifique sur le syndrome, Assimilation du syndrome à des lombalgies non spécifiques | C6: Absence de recommandations professionnelles claires | D6: =COUNTIF($A$2:$A$152,"*Absence de recommandations professionnelles claires*") -> 63 | F6: =C6&" "&"(n="&D6&")" -> Absence de recommandations professionnelles claires (n=63) | G6: =D6/SUM(D$2:D$7) -> 0.23333333
A7: 0 | C7: Insuffisance d'examen clinique spécifique | D7: =COUNTIF($A$2:$A$152,"*Insuffisance d'examen clinique spécifique*") -> 1 | F7: =C7&" "&"(n="&D7&")" -> Insuffisance d'examen clinique spécifique (n=1) | G7: =D7/SUM(D$2:D$7) -> 0.0037037037
A8: Absence de formation spécifique sur le syndrome, Sous-estimation des plaintes des patientes
A9: Absence de formation spécifique sur le syndrome, Sous-estimation des plaintes des patientes, Absence de recommandations professionnelles claires | D9: =SUM(D2:D7) -> 270 | G9: =SUM(G2:G7) -> 1
A10: Absence de formation spécifique sur le syndrome, Assimilation du syndrome à des lombalgies non spécifiques, Difficultés d’accès aux thérapies non médicamenteuses, Absence de recommandations professionnelles claires
A11: Absence de formation spécifique sur le syndrome, Assimilation du syndrome à des lombalgies non spécifiques, Absence de recommandations professionnelles claires
A12: Absence de formation spécifique sur le syndrome, Difficultés d’accès aux thérapies non médicamenteuses, Absence de recommandations professionnelles claires
A13: Absence de formation spécifique sur le syndrome
A14: Assimilation du syndrome à des lombalgies non spécifiques, Absence de recommandations professionnelles claires
A15: Sous-estimation des plaintes des patientes, Difficultés d’accès aux thérapies non médicamenteuses
A16: Assimilation du syndrome à des lombalgies non spécifiques
A17: 0
A18: Assimilation du syndrome à des lombalgies non spécifiques, Sous-estimation des plaintes des patientes, Absence de recommandations professionnelles claires
A19: 0
A20: 0
A21: Absence de formation spécifique sur le syndrome, Assimilation du syndrome à des lombalgies non spécifiques, Sous-estimation des plaintes des patientes
A22: 0
A23: Absence de formation spécifique sur le syndrome, Assimilation du syndrome à des lombalgies non spécifiques, Sous-estimation des plaintes des patientes, Difficultés d’accès aux thérapies non médicamenteuses, Absence de recommandations professionnelles claires
A24: 0
A25: 0
A26: Sous-estimation des plaintes des patientes, Absence de recommandations professionnelles claires
A27: Absence de formation spécifique sur le syndrome, Assimilation du syndrome à des lombalgies non spécifiques, Sous-estimation des plaintes des patientes, Absence de recommandations professionnelles claires
A28: Sous-estimation des plaintes des patientes, Absence de recommandations professionnelles claires
A29: Absence de formation spécifique sur le syndrome, Assimilation du syndrome à des lombalgies non spécifiques
A30: 0
A31: 0
A32: Assimilation du syndrome à des lombalgies non spécifiques, Sous-estimation des plaintes des patientes, Absence de recommandations professionnelles claires
A33: Absence de formation spécifique sur le syndrome, Sous-estimation des plaintes des patientes, Difficultés d’accès aux thérapies non médicamenteuses
A34: Absence de formation spécifique sur le syndrome, Assimilation du syndrome à des lombalgies non spécifiques, Sous-estimation des plaintes des patientes, Difficultés d’accès aux thérapies non médicamenteuses, Absence de recommandations professionnelles claires
A35: Absence de formation spécifique sur le syndrome, Assimilation du syndrome à des lombalgies non spécifiques, Sous-estimation des plaintes des patientes
A36: Assimilation du syndrome à des lombalgies non spécifiques, Sous-estimation des plaintes des patientes, Difficultés d’accès aux thérapies non médicamenteuses, Absence de recommandations professionnelles claires
A37: Absence de formation spécifique sur le syndrome, Assimilation du syndrome à des lombalgies non spécifiques, Sous-estimation des plaintes des patientes, Difficultés d’accès aux thérapies non médicamenteuses, Absence de recommandations professionnelles claires
A38: 0
A39: Absence de formation spécifique sur le syndrome, Assimilation du syndrome à des lombalgies non spécifiques, Sous-estimation des plaintes des patientes, Absence de recommandations professionnelles claires
A40: Absence de formation spécifique sur le syndrome, Assimilation du syndrome à des lombalgies non spécifiques, Sous-estimation des plaintes des patientes, Difficultés d’accès aux thérapies non médicamenteuses, Absence de recommandations professionnelles claires
A41: Assimilation du syndrome à des lombalgies non spécifiques, Sous-estimation des plaintes des patientes, Absence de recommandations professionnelles claires
A42: Absence de formation spécifique sur le syndrome, Assimilation du syndrome à des lombalgies non spécifiques, Sous-estimation des plaintes des patientes, Absence de recommandations professionnelles claires
A43: Absence de formation spécifique sur le syndrome, Assimilation du syndrome à des lombalgies non spécifiques, Sous-estimation des plaintes des patientes, Difficultés d’accès aux thérapies non médicamenteuses, Absence de recommandations professionnelles claires
A44: Absence de recommandations professionnelles claires
A45: Absence de formation spécifique sur le syndrome, Absence de recommandations professionnelles claires
A46: Absence de recommandations professionnelles claires
A47: 0
A48: Assimilation du syndrome à des lombalgies non spécifiques, Sous-estimation des plaintes des patientes, Absence de recommandations professionnelles claires
A49: Assimilation du syndrome à des lombalgies non spécifiques, Sous-estimation des plaintes des patientes, Absence de recommandations professionnelles claires
